Workbook
Name _1B.05.M.010.0010: #REF!
Name _1B.05.M.010.0010: #REF!
Name _1B.05.M.010.0010: #REF!
Name _1B.05.M.010.0050: #REF!
Name _1B.05.M.010.0050: #REF!
Name _1B.05.M.010.0050: #REF!
Name _1B.05.M.0100.0010: #REF!
Name _1B.05.M.0100.0010: #REF!
Name _1B.05.M.020.0010: #REF!
Name _1B.05.M.020.0010: #REF!
Name _1B.05.M.020.0020: #REF!
Name _1B.05.M.020.0020: #REF!
Name _1B.05.M.020.0030: #REF!
Name _1B.05.M.020.0030: #REF!
Name _1B.05.M.020.0040: #REF!
Name _1B.05.M.020.0040: #REF!
Name _1B.05.M.030.0010: #REF!
Name _1B.05.M.030.0010: #REF!
Name _1B.05.M.030.0020: #REF!
Name _1B.05.M.030.0020: #REF!
Name _1B.05.M.040.0010: #REF!
Name _1B.05.M.040.0010: #REF!
Name _1B.05.M.050.0010: #REF!
Name _1B.05.M.050.0010: #REF!
Name _1B.05.M.050.0020: #REF!
Name _1B.05.M.050.0020: #REF!
Name _1B.05.M.050.0030: #REF!
Name _1B.05.M.050.0030: #REF!
Name _1B.05.M.060.0020: #REF!
Name _1B.05.M.060.0020: #REF!
Name _1B.05.M.060.0100: #REF!
Name _1B.05.M.060.0100: #REF!
Name _1B.05.M.070.0010: #REF!
Name _1B.05.M.070.0010: #REF!
Name _1B.05.M.070.0020: #REF!
Name _1B.05.M.070.0020: #REF!
Name _1B.05.M.070.0030: #REF!
Name _1B.05.M.070.0030: #REF!
Name _1B.05.M.070.0040: #REF!
Name _1B.05.M.070.0040: #REF!
Name _1B.05.M.070.0050: #REF!
Name _1B.05.M.070.0050: #REF!
Name _1B.05.M.080.0010: #REF!
Name _1B.05.M.080.0010: #REF!
Name _1B.05.M.090.0010: #REF!
Name _1B.05.M.090.0010: #REF!
Name _1B.09.P.010.0010: #REF!
Name _1B.09.P.010.0010: #REF!
Name _1B.09.P.010.0020: #REF!
Name _1B.09.P.010.0020: #REF!
Name _1B.09.P.010.0030: #REF!
Name _1B.09.P.010.0030: #REF!
Name _1B.09.P.010.0040: #REF!
Name _1B.09.P.010.0040: #REF!
Name _1B.09.P.010.0050: #REF!
Name _1B.09.P.010.0050: #REF!
Name _1B.09.P.010.0060: #REF!
Name _1B.09.P.010.0060: #REF!
Name _1B.09.P.010.0070: #REF!
Name _1B.09.P.010.0070: #REF!

Sheet DB
A1: ='Weekly Progress Report'!$A$1 -> MODON - Weekly Progress Report - Construction Projects
B2: ='Weekly Progress Report'!$A$2 -> Contract General Information | J2: ='Weekly Progress Report'!G2 -> Key Dates | U2: ='Weekly Progress Report'!$L$2 -> Cost Summary (SR) | AD2: ='Weekly Progress Report'!$T$2 -> Performance Summary | AP2: ='Weekly Progress Report'!A54 -> Shop Drawings | AT2: ='Weekly Progress Report'!A63 -> Material Approval | AW2: ='Weekly Progress Report'!A72 -> Procurement Summary | BD2: ='Weekly Progress Report'!K54 -> Quality Reports | BT2: ='Weekly Progress Report'!K62 -> Key Submittals Approval Status | CD2: ='Weekly Progress Report'!K68 -> Invoices Summary | CR2: ='Weekly Progress Report'!K76 -> Resources at Site | CY2: ='Weekly Progress Report'!V54 -> Safety Statistics | FK2: ='Weekly Progress Report'!A81 -> Primavera P6 Schedule Status | FS2: ='Weekly Progress Report'!A90 -> Weekly Prgoress Photos
A3: ='Weekly Progress Report'!AE1 -> Data Date | B3: ='Weekly Progress Report'!A3 -> Project Name | C3: ='Weekly Progress Report'!A4 -> Project ID | D3: ='Weekly Progress Report'!A5 -> Contractor | E3: ='Weekly Progress Report'!A6 -> Consultant | F3: ='Weekly Progress Report'!D4 -> Stage | G3: ='Weekly Progress Report'!D5 -> Status | H3: ='Weekly Progress Report'!D6 -> Modon PM | I3: ='Weekly Progress Report'!Z2 -> Project Scope | J3: ='Weekly Progress Report'!G3 -> Contract Award | K3: ='Weekly Progress Report'!G4 -> Contract Sign | L3: ='Weekly Progress Report'!G5 -> Site Handover | M3: ='Weekly Progress Report'!G6 -> Original Completion | N3: ='Weekly Progress Report'!$H$3 -> Contract Award (Hijri) | O3: ='Weekly Progress Report'!$H$4 -> Contract Sign (Hijri) | P3: ='Weekly Progress Report'!$H$5 -> Site Handover (Hijri) | Q3: ='Weekly Progress Report'!$H$6 -> Original Completion (Hijri) | R3: ='Weekly Progress Report'!$J$3 -> Revised Completion | S3: ='Weekly Progress Report'!$J$4 -> Committed Completion | T3: ='Weekly Progress Report'!$J$5 -> Forecast Completion | U3: ='Weekly Progress Report'!$L$3 -> Original Contract Value | V3: ='Weekly Progress Report'!$L$4 -> Revised Contract Value | W3: ='Weekly Progress Report'!$L$5 -> Estimate At Completion Value | X3: ='Weekly Progress Report'!$L$6 -> Potential Changes | Y3: ='Weekly Progress Report'!$P$3 -> O&M Value (if any) | Z3: ='Weekly Progress Report'!$P$4 -> Submitted Invoices (Gross Value) | AA3: ='Weekly Progress Report'!$P$5 -> Penalities | AB3: ='Weekly Progress Report'!$P$6 -> FIR Value (Todate) | AC3: Original Plan Value | AD3: ='Weekly Progress Report'!$T$3 -> Plan Value | AE3: ='Weekly Progress Report'!$T$4 -> Earn Value | AF3: ='Weekly Progress Report'!$V$3 -> Phys. Plan Value | AG3: ='Weekly Progress Report'!$V$4 -> Phys. Earn Value | AH3: ='Weekly Progress Report'!$X$3 -> Quality Score | AI3: ='Weekly Progress Report'!$X$5 -> Safety Score | AJ3: Weekly PV (SAR) | AK3: Weekly EV (SAR) | AL3: Weekly PV % | AM3: Weekly PV % | AN3: Weekly Phys PV% | AO3: Weekly Phys PV% | AP3: Total SD Planned | AQ3: SD Remaining | AR3: SD Pending | AS3: Total SD Submittals | AT3: Planned Materials Approv | AU3: Material Pending Approval | AV3: Materila Total Submittals | AW3: ='Weekly Progress Report'!C73 -> Total Materials | AX3: ='Weekly Progress Report'!D73 -> Total Number of P.O. | AY3: ='Weekly Progress Report'!E73 -> Actual P.O. To Date | AZ3: ='Weekly Progress Report'!F73 -> Remaining P.O | BA3: ='Weekly Progress Report'!G73 -> Material on Site | BB3: ='Weekly Progress Report'!#REF! -> #REF! | BC3: ='Weekly Progress Report'!H73 -> Material Delivery Completion (Date) | BD3: ="NCR "&'Weekly Progress Report'!M55 -> NCR Issued | BE3: ="NCR "&'Weekly Progress Report'!N55 -> NCR Closed | BF3: ="NCR "&'Weekly Progress Report'!O55 -> NCR Pending | BG3: ="NCR "&'Weekly Progress Report'!P55 -> NCR Avg. Closing (Days) | BH3: ="SIR "&'Weekly Progress Report'!M55 -> SIR Issued | BI3: ="SIR "&'Weekly Progress Report'!N55 -> SIR Closed | BJ3: ="SIR "&'Weekly Progress Report'!O55 -> SIR Pending | BK3: ="SIR "&'Weekly Progress Report'!P55 -> SIR Avg. Closing (Days) | BL3: ="MIR "&'Weekly Progress Report'!M55 -> MIR Issued | BM3: ="MIR "&'Weekly Progress Report'!N55 -> MIR Closed | BN3: ="MIR "&'Weekly Progress Report'!O55 -> MIR Pending | BO3: ="MIR "&'Weekly Progress Report'!P55 -> MIR Avg. Closing (Days) | BP3: ="FIR "&'Weekly Progress Report'!M55 -> FIR Issued | BQ3: ="FIR "&'Weekly Progress Report'!N55 -> FIR Closed | BR3: ="FIR "&'Weekly Progress Report'!O55 -> FIR Pending | BS3: ="FIR "&'Weekly Progress Report'!P55 -> FIR Avg. Closing (Days) | BT3: ='Weekly Progress Report'!K63 -> 1 Quality Plan Approval | BU3: ='Weekly Progress Report'!K64 -> 2 Quality Plan Last Up | BV3: ='Weekly Progress Report'!K65 -> 3 Safety Plan Approval | BW3: ='Weekly Progress Report'!K66 -> 4 Safety Plan Last Up | BX3: ='Weekly Progress Report'!K67 -> 5 Construction Plan Approval | BY3: ='Weekly Progress Report'!P63 -> 6 Baseline Approval | BZ3: ='Weekly Progress Report'!P64 -> 7 No of Approved Version of Schedule | CA3: ='Weekly Progress Report'!P65 -> 8 Last Approved Schedule | CB3: ='Weekly Progress Report'!P66 -> 9 BOQ Approval Date | CC3: ='Weekly Progress Report'!P67 -> 10 No of Approved Version of BOQ | CD3: ='Weekly Progress Report'!K69 -> Total Submitted Invoices | CE3: ='Weekly Progress Report'!K70 -> PM Approved Invoices | CF3: ='Weekly Progress Report'!K71 -> No of Paid Invoices | CG3: ='Weekly Progress Report'!K72 -> No of Pending Invoices | CH3: ='Weekly Progress Report'!K73 -> Advance Payment % | CI3: ='Weekly Progress Report'!K74 -> Retention % | CJ3: ='Weekly Progress Report'!K75 -> Deduction / Penalties % | CK3: ='Weekly Progress Report'!N69 -> Submitted Invoices (SAR) | CL3: ='Weekly Progress Report'!N70 -> PM Approved Invoices (SAR) | CM3: ='Weekly Progress Report'!N71 -> Paid Invoices (SAR) | CN3: ='Weekly Progress Report'!N72 -> Last Submitted Period | CO3: ='Weekly Progress Report'!N73 -> Advance Payment (SAR) | CP3: ='Weekly Progress Report'!N74 -> Retention (SAR) | CQ3: ='Weekly Progress Report'!N75 -> Deduction / Penalties (SAR) | CR3: Planned Head Count | CS3: Actual Head Count | CT3: Saudi Staff | CU3: Labor Planned | CV3: Labor Actual | CW3: Equipment Planned | CX3: Equipment Actual | CY3: ="This Week "&'Weekly Progress Report'!W57 -> This Week Total Hours Worked | CZ3: ="This Week "&'Weekly Progress Report'!W58 -> This Week Safe Hours Worked | DA3: ="This Week "&'Weekly Progress Report'!W59 -> This Week LTI | DB3: ="This Week "&'Weekly Progress Report'!W60 -> This Week MTC (Healed w/o Disability) | DC3: ="This Week "&'Weekly Progress Report'!W61 -> This Week MTC (Healed w/ Disability) | DD3: ="This Week "&'Weekly Progress Report'!W62 -> This Week Near Miss | DE3: ="This Week "&'Weekly Progress Report'!W63 -> This Week First Aid Cases | DF3: ="This Week "&'Weekly Progress Report'!W64 -> This Week Fatality | DG3: ="This Week "&'Weekly Progress Report'!W65 -> This Week Fire Incident Cases | DH3: ="This Week "&'Weekly Progress Report'!W66 -> This Week Vehicle Incident | DI3: ="This Week "&'Weekly Progress Report'!W67 -> This Week Property Damages | DJ3: ="This Week "&'Weekly Progress Report'!W68 -> This Week Induction Training - Sessions(Headcount) | DK3: ="This Week "&'Weekly Progress Report'!W69 -> This Week No.of Internal Training - Sessions(Headcount) | DL3: ="This Week "&'Weekly Progress Report'!W70 -> This Week No.of Internal Audit | DM3: ="This Week "&'Weekly Progress Report'!W71 -> This Week No. of Toolbox Talks - Sessions(Headcount) | DN3: ="This Week "&'Weekly Progress Report'!W72 -> This Week Safety Awards/Incentives | DO3: ="This Month "&'Weekly Progress Report'!W57 -> This Month Total Hours Worked | DP3: ="This Month "&'Weekly Progress Report'!W58 -> This Month Safe Hours Worked | DQ3: ="This Month "&'Weekly Progress Report'!W59 -> This Month LTI | DR3: ="This Month "&'Weekly Progress Report'!W60 -> This Month MTC (Healed w/o Disability) | DS3: ="This Month "&'Weekly Progress Report'!W61 -> This Month MTC (Healed w/ Disability) | DT3: ="This Month "&'Weekly Progress Report'!W62 -> This Month Near Miss | DU3: ="This Month "&'Weekly Progress Report'!W63 -> This Month First Aid Cases | DV3: ="This Month "&'Weekly Progress Report'!W64 -> This Month Fatality | DW3: ="This Month "&'Weekly Progress Report'!W65 -> This Month Fire Incident Cases | DX3: ="This Month "&'Weekly Progress Report'!W66 -> This Month Vehicle Incident | DY3: ="This Month "&'Weekly Progress Report'!W67 -> This Month Property Damages | DZ3: ="This Month "&'Weekly Progress Report'!W68 -> This Month Induction Training - Sessions(Headcount) | EA3: ="This Month "&'Weekly Progress Report'!W69 -> This Month No.of Internal Training - Sessions(Headcount) | EB3: ="This Month "&'Weekly Progress Report'!W70 -> This Month No.of Internal Audit | EC3: ="This Month "&'Weekly Progress Report'!W71 -> This Month No. of Toolbox Talks - Sessions(Headcount) | ED3: ="This Month "&'Weekly Progress Report'!W72 -> This Month Safety Awards/Incentives | EE3: ="YTD "&'Weekly Progress Report'!W57 -> YTD Total Hours Worked | EF3: ="YTD "&'Weekly Progress Report'!W58 -> YTD Safe Hours Worked | EG3: ="YTD "&'Weekly Progress Report'!W59 -> YTD LTI | EH3: ="YTD "&'Weekly Progress Report'!W60 -> YTD MTC (Healed w/o Disability) | EI3: ="YTD "&'Weekly Progress Report'!W61 -> YTD MTC (Healed w/ Disability) | EJ3: ="YTD "&'Weekly Progress Report'!W62 -> YTD Near Miss | EK3: ="YTD "&'Weekly Progress Report'!W63 -> YTD First Aid Cases | EL3: ="YTD "&'Weekly Progress Report'!W64 -> YTD Fatality | EM3: ="YTD "&'Weekly Progress Report'!W65 -> YTD Fire Incident Cases | EN3: ="YTD "&'Weekly Progress Report'!W66 -> YTD Vehicle Incident | EO3: ="YTD "&'Weekly Progress Report'!W67 -> YTD Property Damages | EP3: ="YTD "&'Weekly Progress Report'!W68 -> YTD Induction Training - Sessions(Headcount) | EQ3: ="YTD "&'Weekly Progress Report'!W69 -> YTD No.of Internal Training - Sessions(Headcount) | ER3: ="YTD "&'Weekly Progress Report'!W70 -> YTD No.of Internal Audit | ES3: ="YTD "&'Weekly Progress Report'!W71 -> YTD No. of Toolbox Talks - Sessions(Headcount) | ET3: ="YTD "&'Weekly Progress Report'!W72 -> YTD Safety Awards/Incentives | EU3: ="Cum "&'Weekly Progress Report'!W57 -> Cum Total Hours Worked | EV3: ="Cum "&'Weekly Progress Report'!W58 -> Cum Safe Hours Worked | EW3: ="Cum "&'Weekly Progress Report'!W59 -> Cum LTI | EX3: ="Cum "&'Weekly Progress Report'!W60 -> Cum MTC (Healed w/o Disability) | EY3: ="Cum "&'Weekly Progress Report'!W61 -> Cum MTC (Healed w/ Disability) | EZ3: ="Cum "&'Weekly Progress Report'!W62 -> Cum Near Miss | FA3: ="Cum "&'Weekly Progress Report'!W63 -> Cum First Aid Cases | FB3: ="Cum "&'Weekly Progress Report'!W64 -> Cum Fatality | FC3: ="Cum "&'Weekly Progress Report'!W65 -> Cum Fire Incident Cases | FD3: ="Cum "&'Weekly Progress Report'!W66 -> Cum Vehicle Incident | FE3: ="Cum "&'Weekly Progress Report'!W67 -> Cum Property Damages | FF3: ="Cum "&'Weekly Progress Report'!W68 -> Cum Induction Training - Sessions(Headcount) | FG3: ="Cum "&'Weekly Progress Report'!W69 -> Cum No.of Internal Training - Sessions(Headcount) | FH3: ="Cum "&'Weekly Progress Report'!W70 -> Cum No.of Internal Audit | FI3: ="Cum "&'Weekly Progress Report'!W71 -> Cum No. of Toolbox Talks - Sessions(Headcount) | FJ3: ="Cum "&'Weekly Progress Report'!W72 -> Cum Safety Awards/Incentives | FK3: ='Weekly Progress Report'!A84 -> Total Act. | FL3: ='Weekly Progress Report'!B84 -> Not Started | FM3: ='Weekly Progress Report'!C84 -> In Progress | FN3: ='Weekly Progress Report'!D84 -> Completed | FO3: Critical Path Act.Last Week | FP3: Critical Path Act.This Week | FQ3: Failed start Last Week | FR3: Failed start This Week | FS3: ='Weekly Progress Report'!B92 -> 0 | FT3: ='Weekly Progress Report'!D92 -> 0 | FU3: ='Weekly Progress Report'!F92 -> 0 | FV3: ='Weekly Progress Report'!#REF! -> #REF! | FW3: ='Weekly Progress Report'!I92 -> 0 | FX3: ='Weekly Progress Report'!K92 -> 0 | FY3: ='Weekly Progress Report'!M92 -> 0 | FZ3: ='Weekly Progress Report'!N92 -> 0 | GA3: ='Weekly Progress Report'!O92 -> 0
A4: ='Weekly Progress Report'!AF1 -> 46286 | B4: ='Weekly Progress Report'!B3 -> Improvement of Waad Al Shamal Industrial City Fence & Gates | C4: ='Weekly Progress Report'!B4 -> WAS1-05-006 | D4: ='Weekly Progress Report'!B5 -> Hamza Mohammad Alderi Construction Co. | E4: ='Weekly Progress Report'!B6 -> Consolidated Consultants Group | F4: ='Weekly Progress Report'!E4 -> Construction | G4: ='Weekly Progress Report'!E5 -> Active | H4: ='Weekly Progress Report'!E6 -> Muhammed H. Al-Essa | I4: ='Weekly Progress Report'!Z3 -> #REF! | J4: ='Weekly Progress Report'!#REF! -> #REF! | K4: ='Weekly Progress Report'!#REF! -> #REF! | L4: ='Weekly Progress Report'!#REF! -> #REF! | M4: ='Weekly Progress Report'!#REF! -> #REF! | N4: ='Weekly Progress Report'!$I$3 -> 46107 | O4: ='Weekly Progress Report'!$I$4 -> 46107 | P4: ='Weekly Progress Report'!$I$5 -> 46148 | Q4: ='Weekly Progress Report'!$I$6 -> 46300 | R4: ='Weekly Progress Report'!$K$3 -> 46300 | S4: ='Weekly Progress Report'!$K$4 -> 46300 | T4: ='Weekly Progress Report'!$K$5 -> 46300 | U4: ='Weekly Progress Report'!$N$3 -> 15898659 | V4: ='Weekly Progress Report'!$N$4 -> 15898659 | W4: ='Weekly Progress Report'!$N$5 -> 15898659 | X4: ='Weekly Progress Report'!$N$6 -> 0 | Y4: ='Weekly Progress Report'!$R$3 -> 0 | Z4: ='Weekly Progress Report'!$R$4 -> 0 | AA4: ='Weekly Progress Report'!$R$5 -> 0 | AB4: ='Weekly Progress Report'!$R$6 -> 0 | AC4: ='Weekly Progress Report'!$I$23 -> 12162388 | AD4: ='Weekly Progress Report'!$U$3 -> 0.76499456 | AE4: ='Weekly Progress Report'!$U$4 -> 0.39339486 | AF4: ='Weekly Progress Report'!$W$3 -> 0.63904558 | AG4: ='Weekly Progress Report'!$W$4 -> 0.20345145 | AH4: ='Weekly Progress Report'!$Y$3 -> 0.86206897 | AI4: ='Weekly Progress Report'!$Y$5 -> 0.85 | AJ4: ='Weekly Progress Report'!$E$23 -> 1952900.5 | AK4: ='Weekly Progress Report'!$F$23 -> 0 | AL4: =AJ4/V4 -> 0.12283429 | AM4: =AK4/V4 -> 0 | AN4: ='Weekly Progress Report'!R23 -> 2373 | AO4: ='Weekly Progress Report'!S23 -> 0 | AP4: ='Weekly Progress Report'!C62 -> 35 | AQ4: ='Weekly Progress Report'!H62 -> 0 | AR4: ='Weekly Progress Report'!I62 -> 1 | AS4: ='Weekly Progress Report'!J62 -> 35 | AT4: ='Weekly Progress Report'!C71 -> 90 | AU4: ='Weekly Progress Report'!I71 -> 0 | AV4: ='Weekly Progress Report'!J71 -> 90 | AW4: ='Weekly Progress Report'!C80 | AX4: ='Weekly Progress Report'!D80 | AY4: ='Weekly Progress Report'!E80 | AZ4: ='Weekly Progress Report'!F80 | BA4: ='Weekly Progress Report'!G80 | BB4: ='Weekly Progress Report'!#REF! -> #REF! | BC4: ='Weekly Progress Report'!H80 -> 0 | BD4: ='Weekly Progress Report'!M58 -> 0 | BE4: ='Weekly Progress Report'!N58 -> 0 | BF4: ='Weekly Progress Report'!O58 -> 0 | BG4: ='Weekly Progress Report'!P58 -> 0 | BH4: ='Weekly Progress Report'!M59 -> 0 | BI4: ='Weekly Progress Report'!N59 -> 0 | BJ4: ='Weekly Progress Report'!O59 -> 0 | BK4: ='Weekly Progress Report'!P59 -> 0 | BL4: ='Weekly Progress Report'!M60 -> 24 | BM4: ='Weekly Progress Report'!N60 -> 5 | BN4: ='Weekly Progress Report'!O60 -> 0 | BO4: ='Weekly Progress Report'!P60 -> 0 | BP4: ='Weekly Progress Report'!M61 -> 229 | BQ4: ='Weekly Progress Report'!N61 -> 36 | BR4: ='Weekly Progress Report'!O61 -> 0 | BS4: ='Weekly Progress Report'!P61 -> 0 | BT4: ='Weekly Progress Report'!N63 -> 46159 | BU4: ='Weekly Progress Report'!N64 -> 46159 | BV4: ='Weekly Progress Report'!N65 -> 46161 | BW4: ='Weekly Progress Report'!N66 -> 46161 | BX4: ='Weekly Progress Report'!N67 -> 46167 | BY4: ='Weekly Progress Report'!T63 -> 46162 | BZ4: ='Weekly Progress Report'!T64 -> 46162 | CA4: ='Weekly Progress Report'!T65 -> 46162 | CB4: ='Weekly Progress Report'!T66 -> 46148 | CC4: ='Weekly Progress Report'!T67 -> 46148 | CD4: ='Weekly Progress Report'!M69 -> 0 | CE4: ='Weekly Progress Report'!M70 -> 0 | CF4: ='Weekly Progress Report'!M71 -> 0 | CG4: ='Weekly Progress Report'!M72 -> 0 | CH4: ='Weekly Progress Report'!M73 -> 0 | CI4: ='Weekly Progress Report'!M74 -> 0 | CJ4: ='Weekly Progress Report'!M75 -> 0 | CK4: ='Weekly Progress Report'!Q69 -> 3502841.3 | CL4: ='Weekly Progress Report'!Q70 -> 0 | CM4: ='Weekly Progress Report'!Q71 -> 0 | CN4: ='Weekly Progress Report'!Q72 -> 46275 | CO4: ='Weekly Progress Report'!Q73 -> 0 | CP4: ='Weekly Progress Report'!Q74 -> 0 | CQ4: ='Weekly Progress Report'!Q75 -> 0 | CR4: ='Weekly Progress Report'!K79 -> 8 | CS4: ='Weekly Progress Report'!L79 -> 11 | CT4: ='Weekly Progress Report'!N79 -> 2 | CU4: ='Weekly Progress Report'!O79 -> 15 | CV4: ='Weekly Progress Report'!P79 -> 108 | CW4: ='Weekly Progress Report'!S89 -> 3 | CX4: ='Weekly Progress Report'!T89 -> 8 | CY4: ='Weekly Progress Report'!Y57 -> 5562 | CZ4: ='Weekly Progress Report'!Y58 -> 5562 | DA4: ='Weekly Progress Report'!Y59 -> 0 | DB4: ='Weekly Progress Report'!Y60 -> 0 | DC4: ='Weekly Progress Report'!Y61 -> 0 | DD4: ='Weekly Progress Report'!Y62 -> 0 | DE4: ='Weekly Progress Report'!Y63 -> 0 | DF4: ='Weekly Progress Report'!Y64 -> 0 | DG4: ='Weekly Progress Report'!Y65 -> 0 | DH4: ='Weekly Progress Report'!Y66 -> 0 | DI4: ='Weekly Progress Report'!Y67 -> 0 | DJ4: ='Weekly Progress Report'!Y68 -> 3(6) | DK4: ='Weekly Progress Report'!Y69 -> 0 | DL4: ='Weekly Progress Report'!Y70 -> 0 | DM4: ='Weekly Progress Report'!Y71 -> 1(8) | DN4: ='Weekly Progress Report'!Y72 -> 0 | DO4: ='Weekly Progress Report'!AA57 -> 16470 | DP4: ='Weekly Progress Report'!AA58 -> 16470 | DQ4: ='Weekly Progress Report'!AA59 -> 0 | DR4: ='Weekly Progress Report'!AA60 -> 0 | DS4: ='Weekly Progress Report'!AA61 -> 0 | DT4: ='Weekly Progress Report'!AA62 -> 0 | DU4: ='Weekly Progress Report'!AA63 -> 0 | DV4: ='Weekly Progress Report'!AA64 -> 0 | DW4: ='Weekly Progress Report'!AA65 -> 0 | DX4: ='Weekly Progress Report'!AA66 -> 0 | DY4: ='Weekly Progress Report'!AA67 -> 0 | DZ4: ='Weekly Progress Report'!AA68 -> 9(21) | EA4: ='Weekly Progress Report'!AA69 -> 0 | EB4: ='Weekly Progress Report'!AA70 -> 0 | EC4: ='Weekly Progress Report'!AA71 -> 3(27) | ED4: ='Weekly Progress Report'!AA72 -> 0 | EE4: ='Weekly Progress Report'!AB57 -> 30524 | EF4: ='Weekly Progress Report'!AB58 -> 30524 | EG4: ='Weekly Progress Report'!AB59 -> 0 | EH4: ='Weekly Progress Report'!AB60 -> 0 | EI4: ='Weekly Progress Report'!AB61 -> 0 | EJ4: ='Weekly Progress Report'!AB62 -> 0 | EK4: ='Weekly Progress Report'!AB63 -> 0 | EL4: ='Weekly Progress Report'!AB64 -> 0 | EM4: ='Weekly Progress Report'!AB65 -> 0 | EN4: ='Weekly Progress Report'!AB66 -> 0 | EO4: ='Weekly Progress Report'!AB67 -> 0 | EP4: ='Weekly Progress Report'!AB68 -> 23(137) | EQ4: ='Weekly Progress Report'!AB69 -> 2(14) | ER4: ='Weekly Progress Report'!AB70 -> 3 | ES4: ='Weekly Progress Report'!AB71 -> 17(230) | ET4: ='Weekly Progress Report'!AB72 -> 0 | EU4: ='Weekly Progress Report'!AC57 -> 30524 | EV4: ='Weekly Progress Report'!AC58 -> 30524 | EW4: ='Weekly Progress Report'!AC59 -> 0 | EX4: ='Weekly Progress Report'!AC60 -> 0 | EY4: ='Weekly Progress Report'!AC61 -> 0 | EZ4: ='Weekly Progress Report'!AC62 -> 0 | FA4: ='Weekly Progress Report'!AC63 -> 0 | FB4: ='Weekly Progress Report'!AC64 -> 0 | FC4: ='Weekly Progress Report'!AC65 -> 0 | FD4: ='Weekly Progress Report'!AC66 -> 0 | FE4: ='Weekly Progress Report'!AC67 -> 0 | FF4: ='Weekly Progress Report'!AC68 -> 23(137) | FG4: ='Weekly Progress Report'!AC69 -> 2(14) | FH4: ='Weekly Progress Report'!AC70 -> 3 | FI4: ='Weekly Progress Report'!AC71 -> 17(230) | FJ4: ='Weekly Progress Report'!AC72 | FK4: ='Weekly Progress Report'!A85 -> 554 | FL4: ='Weekly Progress Report'!B85 -> 390 | FM4: ='Weekly Progress Report'!C85 -> 63 | FN4: ='Weekly Progress Report'!D85 -> 101 | FO4: ='Weekly Progress Report'!A89 -> 0 | FP4: ='Weekly Progress Report'!B89 -> 0 | FQ4: ='Weekly Progress Report'!#REF! -> #REF! | FR4: ='Weekly Progress Report'!H89 -> 28 | FS4: ='Weekly Progress Report'!B97 -> 0 | FT4: ='Weekly Progress Report'!D97 -> 0 | FU4: ='Weekly Progress Report'!F97 -> 0 | FV4: ='Weekly Progress Report'!#REF! -> #REF! | FW4: ='Weekly Progress Report'!I97 -> 0 | FX4: ='Weekly Progress Report'!K97 -> 0 | FY4: ='Weekly Progress Report'!M97 -> 0 | FZ4: ='Weekly Progress Report'!N97 -> 0 | GA4: ='Weekly Progress Report'!O97 -> 0

Sheet General Information
A1: Weekly Progress Report - Construction Projects | K1: Data Date | L1: 46286
A2: Contract General Information
A3: Project Name | C3: Improvement of Waad Al Shamal Industrial City Fence & Gates
A4: Project ID | C4: WAS1-05-006
A5: Contractor | C5: Hamza Mohammad Alderi Construction Co.
A6: Consultant | C6: Consolidated Consultants Group
A7: Stage | C7: Construction
A8: Status | C8: Active
A9: Modon PM | C9: Muhammed H. Al-Essa
A11: Key Dates
A12: Contract Award Date | C12: 46107
A13: Contract Sign Date | C13: 46107
A14: Site Handover Date | C14: 46148
A15: Original Completion | C15: 46300
A16: Contract Award Date (Hijri) | C16: =C12 -> 46107
A17: Contract Sign Date (Hijri) | C17: =C13 -> 46107
A18: Site Handover Date (Hijri) | C18: =C14 -> 46148
A19: Original Completion (Hijri) | C19: =C15 -> 46300
A20: Revised Completion Date | C20: 46300
A21: Committed Completion Date | C21: 46300
A22: Forecast Completion | C22: 46300 | K22: =C15-C14 -> 152
A23: Variance | C23: =C20-C22 -> 0 | K23: =L1-C14 -> 138 | L23: =K23/K22 -> 0.90789474
A25: Key Project Submittals | C25: Submission Date | D25: Days taken to approve orginal plan from site handover date
A26: Quality Plan submission | C26: 46159 | D26: =C26-C14 -> 11
A27: Quality Plan approval | C27: 46159
A28: Quality Plan Last Update | C28: 46159
A30: Safety Plan submission | C30: 46161 | D30: =C30-C14 -> 13
A31: Safety Plan approval | C31: 46161
A32: Safety Plan Last Update | C32: 46161
A34: Risk Management Plan submission | D34: =C34-C14 -> -46148
A35: Risk Management Plan approval
A36: Risk Management Plan Last Update
A38: Baseline Schedule submission | C38: 46162 | D38: =C38-C14 -> 14
A39: Baseline Schedule approval | C39: 46162
A40: No of Schedule Versions | C40: 46162
A41: Last Recovery Schedule Approval Date | C41: 46162
A43: BOQ submission | C43: 46148 | D43: =C43-C19 -> -152
A44: BOQ approval | C44: 46148
A45: No of Approved Version of BOQ | C45: 46148
A47: Construction Plan submission | C47: 46162 | D47: =C47-C14 -> 14
A48: Construction Plan Approval | C48: 46167

Sheet Weekly Progress Report
A1: MODON - Weekly Progress Report - Construction Projects | AE1: Data Date | AF1: ='General Information'!L1 -> 46286
A2: Contract General Information | G2: Key Dates | L2: Cost Summary (SR) | T2: Performance Summary | Z2: Project Scope
A3: Project Name | B3: ='General Information'!C3 -> Improvement of Waad Al Shamal Industrial City Fence & Gates | G3: Contract Award | H3: Contract Award (Hijri) | I3: ='General Information'!C16 -> 46107 | J3: Revised Completion | K3: ='General Information'!C20 -> 46300 | L3: Original Contract Value | N3: ='Invoice Log'!E3 -> 15898659 | P3: O&M Value (if any) | R3: ='Invoice Log'!I3 -> 0 | S3: EAC | T3: Plan Value | U3: =J24 -> 0.76499456 | V3: Phys. Plan Value | W3: =T24 -> 0.63904558 | X3: Quality Score | Y3: =Quality!AC10 -> 0.86206897 | Z3: =+Progress!#REF! -> #REF!
A4: Project ID | B4: ='General Information'!C4 -> WAS1-05-006 | D4: Stage | E4: ='General Information'!C7 -> Construction | G4: Contract Sign | H4: Contract Sign (Hijri) | I4: ='General Information'!C17 -> 46107 | J4: Committed Completion | K4: ='General Information'!C21 -> 46300 | L4: Revised Contract Value | N4: ='Invoice Log'!E4 -> 15898659 | O4: EAC | P4: Submitted Invoices (Gross Value) | R4: 0 | T4: Earn Value | U4: =L24 -> 0.39339486 | V4: Phys. Earn Value | W4: =V24 -> 0.20345145 | Y4: =REPT("¢",IF(INT(+Y3*10)>5,5,INT(+Y3*10)))&REPT("£",IF(INT(+Y3*10)>5,0,5-INT(+Y3*10)))&CHAR(10)&REPT("¢",+IF(INT(+Y3*10)>5,-5+INT(+Y3*10),0))&REPT("£",IF(INT(+Y3*10)>5,10-INT(+Y3*10),5)) -> ¢¢¢¢¢ ¢¢¢££
A5: Contractor | B5: ='General Information'!C5 -> Hamza Mohammad Alderi Construction Co. | D5: Status | E5: ='General Information'!C8 -> Active | G5: Site Handover | H5: Site Handover (Hijri) | I5: ='General Information'!C18 -> 46148 | J5: Forecast Completion | K5: ='General Information'!C22 -> 46300 | L5: Estimate At Completion Value | N5: ='Invoice Log'!E5 -> 15898659 | O5: =+#REF!+#REF!+N5 -> #REF! | P5: Penalities | R5: 0 | T5: Variance | U5: =U4-U3 -> -0.3715997 | V5: Variance | W5: =W4-W3 -> -0.43559413 | X5: Safety Score | Y5: ='HSE-Stat'!J23 -> 0.85
A6: Consultant | B6: ='General Information'!C6 -> Consolidated Consultants Group | D6: Modon PM | E6: ='General Information'!C9 -> Muhammed H. Al-Essa | G6: Original Completion | H6: Original Completion (Hijri) | I6: ='General Information'!C19 -> 46300 | J6: Variance | K6: ='General Information'!C23 -> 0 | L6: Potential Changes | N6: =N4-N5 -> 0 | P6: FIR Value (Todate) | R6: 0 | T6: FIR % | U6: 0 | V6: Invoiced % | W6: 0 | Y6: =REPT("¢",IF(INT(+Y5*10)>5,5,INT(+Y5*10)))&REPT("£",IF(INT(+Y5*10)>5,0,5-INT(+Y5*10)))&CHAR(10)&REPT("¢",+IF(INT(+Y5*10)>5,-5+INT(+Y5*10),0))&REPT("£",IF(INT(+Y5*10)>5,10-INT(+Y5*10),5)) -> ¢¢¢¢¢ ¢¢¢££ | AI6: A
A8: Progress Overview
A9: Earned Value Progress (SAR) | N9: Physical Progress (Effort) | Z9: Earned Value Progress (%)
A10: WBS | C10: BOQ Value (SAR) | D10: % Wt. | E10: Weekly (SAR) | J10: To Date (SAR) | N10: Budgeted | O10: % Wt. | P10: Weekly Physical Progress | T10: To Date Physical Progress
E11: Planned | G11: Earned | I11: Original Plan % | J11: Planned | L11: Earned | N11: (Manhours) | P11: Planned | R11: Earned | T11: Planned | V11: Earned
A12: =Progress!A7 -> WAS1-05-006 - B1 - B1 - B1 - B1.2 Mobilization | C12: =Progress!B7 -> 0 | D12: =Progress!C7 -> 0 | E12: =Progress!D7 -> 0 | G12: =Progress!E7 -> 0 | I12: =Progress!F7 -> 0 | J12: =Progress!G7 -> 0 | L12: =Progress!H7 -> 0 | N12: =Progress!J7 -> 2956 | O12: =Progress!K7 -> 0.029936906 | P12: =Progress!L7 -> 0 | R12: =Progress!M7 -> 0 | T12: =Progress!N7 -> 2956 | V12: =Progress!O7 -> 2956
A13: =Progress!A8 -> WAS1-05-006 - B1 - B1 - B1 - B1.3 Preliminary Submittals | C13: =Progress!B8 -> 0 | D13: =Progress!C8 -> 0 | E13: =Progress!D8 -> 0 | G13: =Progress!E8 -> 0 | I13: =Progress!F8 -> 0 | J13: =Progress!G8 -> 0 | L13: =Progress!H8 -> 0 | N13: =Progress!J8 -> 0 | O13: =Progress!K8 -> 0 | P13: =Progress!L8 -> 0 | R13: =Progress!M8 -> 0 | T13: =Progress!N8 -> 0 | V13: =Progress!O8 -> 0
A14: =Progress!A9 -> WAS1-05-006 - B1 - B1 - B1 - B1.6 Engineering | C14: =Progress!B9 -> 476989.77 | D14: =Progress!C9 -> 0.030001887 | E14: =Progress!D9 -> 8112.07 | G14: =Progress!E9 -> 973.44 | I14: =Progress!F9 -> 473744.95 | J14: =Progress!G9 -> 473744.95 | L14: =Progress!H9 -> 181061.42 | N14: =Progress!J9 -> 4927 | O14: =Progress!K9 -> 0.049898219 | P14: =Progress!L9 -> 62 | R14: =Progress!M9 -> 154 | T14: =Progress!N9 -> 4911 | V14: =Progress!O9 -> 2854
A15: =Progress!A10 -> WAS1-05-006 - B1 - B1 - B1 - B1.7 Procurement | C15: =Progress!B10 -> 3179931.7 | D15: =Progress!C10 -> 0.20001257 | E15: =Progress!D10 -> 168485.46 | G15: =Progress!E10 -> 0 | I15: =Progress!F10 -> 3045396.1 | J15: =Progress!G10 -> 3045396.1 | L15: =Progress!H10 -> 1896470.1 | N15: =Progress!J10 -> 12811 | O15: =Progress!K10 -> 0.12974347 | P15: =Progress!L10 -> 3846 | R15: =Progress!M10 -> 0 | T15: =Progress!N10 -> 9740 | V15: =Progress!O10 -> 2301
A16: =Progress!A11 -> WAS1-05-006 - B1 - B1 - B1 - B1.8 Construction | C16: =Progress!B11 -> 10651772 | D16: =Progress!C11 -> 0.66997925 | E16: =Progress!D11 -> 1776303 | G16: =Progress!E11 -> 1557929 | I16: =Progress!F11 -> 8643246.6 | J16: =Progress!G11 -> 8643246.6 | L16: =Progress!H11 -> 4176919.2 | N16: =Progress!J11 -> 73908 | O16: =Progress!K11 -> 0.74850366 | P16: =Progress!L11 -> 8524 | R16: =Progress!M11 -> 2219 | T16: =Progress!N11 -> 45493 | V16: =Progress!O11 -> 11978
A17: =Progress!A12 -> WAS1-05-006 - B1 - B1 - B1 - B1.8.1 FENCES | C17: =Progress!B12 -> 9040220 | D17: =Progress!C12 -> 0.56861525 | E17: =Progress!D12 -> 1676971.3 | G17: =Progress!E12 -> 1536539.6 | I17: =Progress!F12 -> 7906683.8 | J17: =Progress!G12 -> 7906683.8 | L17: =Progress!H12 -> 4096091.3 | N17: =Progress!J12 -> 4885 | O17: =Progress!K12 -> 0.049472863 | P17: =Progress!L12 -> 750 | R17: =Progress!M12 -> 484 | T17: =Progress!N12 -> 4227 | V17: =Progress!O12 -> 2183
A18: =Progress!A13 -> WAS1-05-006 - B1 - B1 - B1 - B1.8.2 GUARD HOUSE 1 | C18: =Progress!B13 -> 438683.2 | D18: =Progress!C13 -> 0.027592465 | E18: =Progress!D13 -> 17202.44 | G18: =Progress!E13 -> 8065.64 | I18: =Progress!F13 -> 153069.53 | J18: =Progress!G13 -> 153069.53 | L18: =Progress!H13 -> 35100.37 | N18: =Progress!J13 -> 22300 | O18: =Progress!K13 -> 0.22584337 | P18: =Progress!L13 -> 2530 | R18: =Progress!M13 -> 483 | T18: =Progress!N13 -> 11323 | V18: =Progress!O13 -> 3732
A19: =Progress!A14 -> WAS1-05-006 - B1 - B1 - B1 - B1.8.3 GUARD HOUSE 2 | C19: =Progress!B14 -> 438683.2 | D19: =Progress!C14 -> 0.027592465 | E19: =Progress!D14 -> 15771.65 | G19: =Progress!E14 -> 5479.23 | I19: =Progress!F14 -> 197325.23 | J19: =Progress!G14 -> 197325.23 | L19: =Progress!H14 -> 10848.26 | N19: =Progress!J14 -> 22300 | O19: =Progress!K14 -> 0.22584337 | P19: =Progress!L14 -> 2410 | R19: =Progress!M14 -> 775 | T19: =Progress!N14 -> 14176 | V19: =Progress!O14 -> 2336
A20: =Progress!A15 -> WAS1-05-006 - B1 - B1 - B1 - B1.8.5 GUARD HOUSE 3 | C20: =Progress!B15 -> 438683.2 | D20: =Progress!C15 -> 0.027592465 | E20: =Progress!D15 -> 15771.65 | G20: =Progress!E15 -> 7844.51 | I20: =Progress!F15 -> 197325.23 | J20: =Progress!G15 -> 197325.23 | L20: =Progress!H15 -> 34879.24 | N20: =Progress!J15 -> 22300 | O20: =Progress!K15 -> 0.22584337 | P20: =Progress!L15 -> 2410 | R20: =Progress!M15 -> 478 | T20: =Progress!N15 -> 14176 | V20: =Progress!O15 -> 3727
A21: =Progress!A16 -> WAS1-05-006 - B1 - B1 - B1 - B1.8.4 EXT. WORKS | C21: =Progress!B16 -> 295502.16 | D21: =Progress!C16 -> 0.018586609 | E21: =Progress!D16 -> 50585.98 | G21: =Progress!E16 -> 0 | I21: =Progress!F16 -> 188842.83 | J21: =Progress!G16 -> 188842.83 | L21: =Progress!H16 -> 0 | N21: =Progress!J16 -> 2320 | O21: =Progress!K16 -> 0.023495812 | P21: =Progress!L16 -> 422 | R21: =Progress!M16 -> 0 | T21: =Progress!N16 -> 1590 | V21: =Progress!O16 -> 0
A22: =Progress!A17 -> WAS1-05-006 - B1 - B1 - B1 - B1.4 Testing & Commissioning | C22: =Progress!B17 -> 1589965.9 | D22: =Progress!C17 -> 0.10000629 | E22: =Progress!D17 -> 0 | G22: =Progress!E17 -> 0 | I22: =Progress!F17 -> 0 | J22: =Progress!G17 -> 0 | L22: =Progress!H17 -> 0 | N22: =Progress!J17 -> 3942 | O22: =Progress!K17 -> 0.039922626 | P22: =Progress!L17 -> 0 | R22: =Progress!M17 -> 0 | T22: =Progress!N17 -> 0 | V22: =Progress!O17 -> 0
A23: Total (SAR) | C23: =SUM(C12:C15,C17:C22) -> 15898659 | D23: =Progress!C18 -> 1 | E23: =Progress!D18 -> 1952900.5 | G23: =Progress!E18 -> 1558902.5 | I23: =Progress!F18 -> 12162388 | J23: =Progress!G18 -> 12162388 | L23: =Progress!H18 -> 6254450.7 | N23: =Progress!J18 -> 98741 | O23: =Progress!K18 -> 1 | P23: =Progress!L18 -> 12432 | R23: =Progress!M18 -> 2373 | T23: =Progress!N18 -> 63100 | V23: =Progress!O18 -> 20089
A24: Total (%) | E24: =E23/$C$23 -> 0.12283429 | G24: =G23/$C$23 -> 0.098052449 | J24: =J23/$C$23 -> 0.76499456 | L24: =L23/$C$23 -> 0.39339486 | P24: =P23/$N$23 -> 0.12590515 | R24: =R23/$N$23 -> 0.02403257 | T24: =T23/$N$23 -> 0.63904558 | V24: =V23/$N$23 -> 0.20345145
Z25: Construction Milestones
Z26: Item No. | AA26: Milestones | AC26: Original (Baseline) | AD26: Latest Plan | AE26: Forecast | AF26: Status | AG26: Days Change
Z27: =+Milestones!A4 -> 1 | AA27: =+Milestones!B4 -> Award Date | AC27: =+Milestones!C4 -> 46107 | AD27: =+Milestones!D4 -> 46107 | AE27: =+Milestones!E4 -> 46107 | AF27: =+Milestones!F4 -> 0 | AG27: =+Milestones!G4 -> 0
Z28: =+Milestones!A5 -> 2 | AA28: =+Milestones!B5 -> Contract Sign Date | AC28: =+Milestones!C5 -> 46107 | AD28: =+Milestones!D5 -> 46107 | AE28: =+Milestones!E5 -> 46107 | AF28: =+Milestones!F5 -> A | AG28: =+Milestones!G5 -> 0
Z29: =+Milestones!A6 -> 3 | AA29: =+Milestones!B6 -> Site Handover Date | AC29: =+Milestones!C6 -> 46148 | AD29: =+Milestones!D6 -> 46148 | AE29: =+Milestones!E6 -> 46148 | AF29: =+Milestones!F6 -> A | AG29: =+Milestones!G6 -> 0
Z30: =+Milestones!A7 -> 4 | AA30: =+Milestones!B7 -> Start Mobilization | AC30: =+Milestones!C7 -> 46148 | AD30: =+Milestones!D7 -> 46148 | AE30: =+Milestones!E7 -> 46148 | AF30: =+Milestones!F7 -> A | AG30: =+Milestones!G7 -> 0
Z31: =+Milestones!A10 -> 7 | AA31: =+Milestones!B10 -> Complete Procurement | AC31: =+Milestones!C10 -> 46293 | AD31: =+Milestones!D10 -> 46293 | AE31: =+Milestones!E10 -> 46293 | AF31: =+Milestones!F10 -> F | AG31: =+Milestones!G10 -> 0
Z32: =+Milestones!A11 -> 8 | AA32: =+Milestones!B11 -> Complete Construction Works | AC32: =+Milestones!C11 -> 46300 | AD32: =+Milestones!D11 -> 46300 | AE32: =+Milestones!E11 -> 46300 | AF32: =+Milestones!F11 -> F | AG32: =+Milestones!G11 -> 0
Z33: =+Milestones!#REF! -> #REF! | AA33: =+Milestones!#REF! -> #REF! | AC33: =+Milestones!#REF! -> #REF! | AD33: =+Milestones!#REF! -> #REF! | AE33: =+Milestones!#REF! -> #REF! | AF33: =+Milestones!#REF! -> #REF! | AG33: =+Milestones!#REF! -> #REF!
Z34: =+Milestones!A12 -> 10 | AA34: =+Milestones!B12 -> Complete Demobilization | AC34: =+Milestones!C12 -> 46300 | AD34: =+Milestones!D12 -> 46300 | AE34: =+Milestones!E12 -> 46300 | AF34: =+Milestones!F12 -> F | AG34: =+Milestones!G12 -> 0
Z35: =+Milestones!A13 -> 11 | AA35: =+Milestones!B13 -> Complete all Works including Testing & Commissioning, Cleanup, Closeout Documentation and Ready for Initial Handover | AC35: =+Milestones!C13 -> 46300 | AD35: =+Milestones!D13 -> 46300 | AE35: =+Milestones!E13 -> 46300 | AF35: =+Milestones!F13 -> F | AG35: =+Milestones!G13 -> 0
Z36: =+Milestones!A14 -> 12 | AA36: =+Milestones!B14 -> Project Completion Date | AC36: =+Milestones!C14 -> 46300 | AD36: =+Milestones!D14 -> 46300 | AE36: =+Milestones!E14 -> 46300 | AF36: =+Milestones!F14 -> F | AG36: =+Milestones!G14 -> 0
A52: Performance overview
A53: Submittals Status | K53: Quality | V53: Safety
A54: Shop Drawings | K54: Quality Reports | V54: Safety Statistics | AD54: Proactive Vs Reactive Actions Taken
A55: Item Per WBS | C55: Total | D55: Total Submitted Drawings | H55: Remaining | I55: Pending | J55: Total Submittals | K55: Quality Reports | M55: Issued | N55: Closed | O55: Pending | P55: Avg. Closing (Days) | Q55: Pending | V55: Category | W55: Item | Y55: This Week | AA55: This Month | AB55: Year to Date | AC55: Cumulative
D56: A | E56: B | F56: C | G56: D | Q56: 0-10 Days | R56: 11-20 Days | S56: 21-30 Days | T56: 31-60 Days | U56: > 60 Days
A57: ='Quality-Stat'!$A$13 -> Civil | C57: =IF('Quality-Stat'!D13="","",'Quality-Stat'!D13) -> 13 | D57: =IF('Quality-Stat'!E13="","",'Quality-Stat'!E13) -> 5 | E57: =IF('Quality-Stat'!F13="","",'Quality-Stat'!F13) -> 7 | F57: =IF('Quality-Stat'!G13="","",'Quality-Stat'!G13) -> 0 | G57: =IF('Quality-Stat'!H13="","",'Quality-Stat'!H13) -> 1 | H57: =IF('Quality-Stat'!J13="","",'Quality-Stat'!J13) -> 0 | I57: =IF('Quality-Stat'!K13="","",'Quality-Stat'!K13) -> 0 | J57: =IF('Quality-Stat'!L13="","",'Quality-Stat'!L13) -> 13 | V57: General | W57: ='HSE-Stat'!B4 -> Total Hours Worked | Y57: ='HSE-Stat'!D4 -> 5562 | AA57: ='HSE-Stat'!E4 -> 16470 | AB57: ='HSE-Stat'!F4 -> 30524 | AC57: ='HSE-Stat'!G4 -> 30524 | AF57: Proactive | AG57: =+SUM(AC68:AC72) -> 3
A58: ='Quality-Stat'!$A$14 -> Structural | C58: =IF('Quality-Stat'!D14="","",'Quality-Stat'!D14) | D58: =IF('Quality-Stat'!E14="","",'Quality-Stat'!E14) -> 0 | E58: =IF('Quality-Stat'!F14="","",'Quality-Stat'!F14) -> 0 | F58: =IF('Quality-Stat'!G14="","",'Quality-Stat'!G14) -> 0 | G58: =IF('Quality-Stat'!H14="","",'Quality-Stat'!H14) -> 0 | H58: =IF('Quality-Stat'!J14="","",'Quality-Stat'!J14) -> 0 | I58: =IF('Quality-Stat'!K14="","",'Quality-Stat'!K14) | J58: =IF('Quality-Stat'!L14="","",'Quality-Stat'!L14) -> 0 | K58: Non Conformance (NCR) | M58: ='Quality-Stat'!D5 -> 0 | N58: ='Quality-Stat'!E5 -> 0 | O58: ='Quality-Stat'!F5 -> 0 | P58: ='Quality-Stat'!G5 -> 0 | Q58: ='Quality-Stat'!H5 -> 0 | R58: ='Quality-Stat'!I5 -> 0 | S58: ='Quality-Stat'!J5 -> 0 | T58: ='Quality-Stat'!K5 -> 0 | U58: ='Quality-Stat'!L5 -> 0 | W58: ='HSE-Stat'!B5 -> Safe Hours Worked | Y58: ='HSE-Stat'!D5 -> 5562 | AA58: ='HSE-Stat'!E5 -> 16470 | AB58: ='HSE-Stat'!F5 -> 30524 | AC58: ='HSE-Stat'!G5 -> 30524 | AF58: Reactive | AG58: =SUM(AC59:AC67) -> 0
A59: ='Quality-Stat'!$A$15 -> Architectural | C59: =IF('Quality-Stat'!D15="","",'Quality-Stat'!D15) -> 10 | D59: =IF('Quality-Stat'!E15="","",'Quality-Stat'!E15) -> 3 | E59: =IF('Quality-Stat'!F15="","",'Quality-Stat'!F15) -> 7 | F59: =IF('Quality-Stat'!G15="","",'Quality-Stat'!G15) -> 0 | G59: =IF('Quality-Stat'!H15="","",'Quality-Stat'!H15) -> 0 | H59: =IF('Quality-Stat'!J15="","",'Quality-Stat'!J15) -> 0 | I59: =IF('Quality-Stat'!K15="","",'Quality-Stat'!K15) -> 0 | J59: =IF('Quality-Stat'!L15="","",'Quality-Stat'!L15) -> 10 | K59: Site Instruction (SIR) | M59: ='Quality-Stat'!D6 -> 0 | N59: ='Quality-Stat'!E6 -> 0 | O59: ='Quality-Stat'!F6 -> 0 | P59: ='Quality-Stat'!G6 -> 0 | Q59: ='Quality-Stat'!H6 -> 0 | R59: ='Quality-Stat'!I6 -> 0 | S59: ='Quality-Stat'!J6 -> 0 | T59: ='Quality-Stat'!K6 -> 0 | U59: ='Quality-Stat'!L6 -> 0 | V59: Reactive | W59: ='HSE-Stat'!B6 -> LTI | Y59: ='HSE-Stat'!D6 -> 0 | AA59: ='HSE-Stat'!E6 -> 0 | AB59: ='HSE-Stat'!F6 -> 0 | AC59: ='HSE-Stat'!G6 -> 0
A60: ='Quality-Stat'!$A$16 -> Mechanical | C60: =IF('Quality-Stat'!D16="","",'Quality-Stat'!D16) -> 4 | D60: =IF('Quality-Stat'!E16="","",'Quality-Stat'!E16) -> 0 | E60: =IF('Quality-Stat'!F16="","",'Quality-Stat'!F16) -> 4 | F60: =IF('Quality-Stat'!G16="","",'Quality-Stat'!G16) -> 0 | G60: =IF('Quality-Stat'!H16="","",'Quality-Stat'!H16) -> 0 | H60: =IF('Quality-Stat'!J16="","",'Quality-Stat'!J16) -> 0 | I60: =IF('Quality-Stat'!K16="","",'Quality-Stat'!K16) -> 0 | J60: =IF('Quality-Stat'!L16="","",'Quality-Stat'!L16) -> 4 | K60: Material Inspection (MIR) | M60: ='Quality-Stat'!D7 -> 24 | N60: ='Quality-Stat'!E7 -> 5 | O60: ='Quality-Stat'!F7 -> 0 | P60: ='Quality-Stat'!G7 -> 0 | Q60: ='Quality-Stat'!H7 -> 0 | R60: ='Quality-Stat'!I7 -> 0 | S60: ='Quality-Stat'!J7 -> 0 | T60: ='Quality-Stat'!K7 -> 0 | U60: ='Quality-Stat'!L7 -> 0 | W60: ='HSE-Stat'!B7 -> MTC (Healed w/o Disability) | Y60: ='HSE-Stat'!D7 -> 0 | AA60: ='HSE-Stat'!E7 -> 0 | AB60: ='HSE-Stat'!F7 -> 0 | AC60: ='HSE-Stat'!G7 -> 0
A61: ='Quality-Stat'!$A$17 -> Electrical | C61: =IF('Quality-Stat'!D17="","",'Quality-Stat'!D17) -> 8 | D61: =IF('Quality-Stat'!E17="","",'Quality-Stat'!E17) -> 0 | E61: =IF('Quality-Stat'!F17="","",'Quality-Stat'!F17) -> 7 | F61: =IF('Quality-Stat'!G17="","",'Quality-Stat'!G17) -> 0 | G61: =IF('Quality-Stat'!H17="","",'Quality-Stat'!H17) -> 0 | H61: =IF('Quality-Stat'!J17="","",'Quality-Stat'!J17) -> 0 | I61: =IF('Quality-Stat'!K17="","",'Quality-Stat'!K17) -> 1 | J61: =IF('Quality-Stat'!L17="","",'Quality-Stat'!L17) -> 8 | K61: Field Inspection (FIR) | M61: ='Quality-Stat'!D8 -> 229 | N61: ='Quality-Stat'!E8 -> 36 | O61: ='Quality-Stat'!F8 -> 0 | P61: ='Quality-Stat'!G8 -> 0 | Q61: ='Quality-Stat'!H8 -> 0 | R61: ='Quality-Stat'!I8 -> 0 | S61: ='Quality-Stat'!J8 -> 0 | T61: ='Quality-Stat'!K8 -> 0 | U61: ='Quality-Stat'!L8 -> 0 | W61: ='HSE-Stat'!B8 -> MTC (Healed w/ Disability) | Y61: ='HSE-Stat'!D8 -> 0 | AA61: ='HSE-Stat'!E8 -> 0 | AB61: ='HSE-Stat'!F8 -> 0 | AC61: ='HSE-Stat'!G8 -> 0
A62: TOTAL | C62: =SUM(C57:C61) -> 35 | D62: =SUM(D57:D61) -> 8 | E62: =SUM(E57:E61) -> 25 | F62: =SUM(F57:F61) -> 0 | G62: =SUM(G57:G61) -> 1 | H62: =SUM(H57:H61) -> 0 | I62: =SUM(I57:I61) -> 1 | J62: =SUM(J57:J61) -> 35 | K62: Key Submittals Approval Status | W62: ='HSE-Stat'!B9 -> Near Miss | Y62: ='HSE-Stat'!D9 -> 0 | AA62: ='HSE-Stat'!E9 -> 0 | AB62: ='HSE-Stat'!F9 -> 0 | AC62: ='HSE-Stat'!G9 -> 0
A63: Material Approval | K63: 1 Quality Plan Approval | N63: ='General Information'!C27 -> 46159 | P63: 6 Baseline Approval | T63: ='General Information'!C39 -> 46162 | W63: ='HSE-Stat'!B10 -> First Aid Cases | Y63: ='HSE-Stat'!D10 -> 0 | AA63: ='HSE-Stat'!E10 -> 0 | AB63: ='HSE-Stat'!F10 -> 0 | AC63: ='HSE-Stat'!G10 -> 0 | AD63: Total Hours Worked Vs Safe Hours Worked
A64: Item Per WBS | C64: Total | D64: Total Submitted Material | H64: Remaining to approve | I64: Pending | J64: Total Submittals | K64: 2 Quality Plan Last Up | N64: ='General Information'!C28 -> 46159 | P64: 7 No of Approved Version of Schedule | T64: ='General Information'!C40 -> 46162 | W64: ='HSE-Stat'!B11 -> Fatality | Y64: ='HSE-Stat'!D11 -> 0 | AA64: ='HSE-Stat'!E11 -> 0 | AB64: ='HSE-Stat'!F11 -> 0 | AC64: ='HSE-Stat'!G11 -> 0
D65: A | E65: B | F65: C | G65: D | H65: with Designer | K65: 3 Safety Plan Approval | N65: ='General Information'!C31 -> 46161 | P65: 8 Last Approved Schedule | T65: ='General Information'!C41 -> 46162 | W65: ='HSE-Stat'!B12 -> Fire Incident Cases | Y65: ='HSE-Stat'!D12 -> 0 | AA65: ='HSE-Stat'!E12 -> 0 | AB65: ='HSE-Stat'!F12 -> 0 | AC65: ='HSE-Stat'!G12 -> 0
A66: Civil | C66: 23 | D66: =IF('Quality-Stat'!E25="","",'Quality-Stat'!E25) | E66: 23 | F66: =IF('Quality-Stat'!G25="","",'Quality-Stat'!G25) | G66: =IF('Quality-Stat'!H25="","",'Quality-Stat'!H25) | H66: =IF('Quality-Stat'!J25="","",'Quality-Stat'!J25) -> 0 | I66: =IF('Quality-Stat'!K25="","",'Quality-Stat'!K25) | J66: 23 | K66: 4 Safety Plan Last Up | N66: ='General Information'!C32 -> 46161 | P66: 9 BOQ Approval Date | T66: ='General Information'!C44 -> 46148 | W66: ='HSE-Stat'!B13 -> Vehicle Incident | Y66: ='HSE-Stat'!D13 -> 0 | AA66: ='HSE-Stat'!E13 -> 0 | AB66: ='HSE-Stat'!F13 -> 0 | AC66: ='HSE-Stat'!G13 -> 0
A67: Structural | D67: =IF('Quality-Stat'!E26="","",'Quality-Stat'!E26) | G67: =IF('Quality-Stat'!H26="","",'Quality-Stat'!H26) | H67: =IF('Quality-Stat'!J26="","",'Quality-Stat'!J26) -> 0 | I67: =IF('Quality-Stat'!K26="","",'Quality-Stat'!K26) -> 0 | J67: 0 | K67: 5 Construction Plan Approval | N67: ='General Information'!C48 -> 46167 | P67: 10 No of Approved Version of BOQ | T67: ='General Information'!C45 -> 46148 | W67: ='HSE-Stat'!B14 -> Property Damages | Y67: ='HSE-Stat'!D14 -> 0 | AA67: ='HSE-Stat'!E14 -> 0 | AB67: ='HSE-Stat'!F14 -> 0 | AC67: ='HSE-Stat'!G14 -> 0
A68: Architectural | C68: 19 | D68: =IF('Quality-Stat'!E27="","",'Quality-Stat'!E27) | E68: 18 | F68: 1 | H68: =IF('Quality-Stat'!J27="","",'Quality-Stat'!J27) -> 0 | I68: =IF('Quality-Stat'!K27="","",'Quality-Stat'!K27) -> 0 | J68: 19 | K68: Invoices Summary | V68: Proactive | W68: ='HSE-Stat'!B15 -> Induction Training - Sessions(Headcount) | Y68: ='HSE-Stat'!D15 -> 3(6) | AA68: ='HSE-Stat'!E15 -> 9(21) | AB68: ='HSE-Stat'!F15 -> 23(137) | AC68: ='HSE-Stat'!G15 -> 23(137)
A69: Mechanical | C69: 27 | D69: =IF('Quality-Stat'!E28="","",'Quality-Stat'!E28) | E69: 26 | F69: =IF('Quality-Stat'!G28="","",'Quality-Stat'!G28) -> 1 | G69: =IF('Quality-Stat'!H28="","",'Quality-Stat'!H28) -> 1 | H69: =IF('Quality-Stat'!J28="","",'Quality-Stat'!J28) -> 0 | I69: 0 | J69: 27 | K69: Total Submitted Invoices | M69: ='Invoice Log'!U3 -> 0 | N69: Submitted Invoices (SAR) | Q69: ='Invoice Log'!Y3 -> 3502841.3 | S69: Contract Value (SR) | T69: =N4 -> 15898659 | W69: ='HSE-Stat'!B16 -> No.of Internal Training - Sessions(Headcount) | Y69: ='HSE-Stat'!D16 -> 0 | AA69: ='HSE-Stat'!E16 -> 0 | AB69: ='HSE-Stat'!F16 -> 2(14) | AC69: ='HSE-Stat'!G16 -> 2(14)
A70: Electrical | C70: 21 | D70: =IF('Quality-Stat'!E29="","",'Quality-Stat'!E29) -> 0 | E70: 19 | F70: 0 | G70: 1 | H70: =IF('Quality-Stat'!J29="","",'Quality-Stat'!J29) -> 0 | I70: =IF('Quality-Stat'!K29="","",'Quality-Stat'!K29) -> 0 | J70: 21 | K70: PM Approved Invoices | M70: ='Invoice Log'!U5 -> 0 | N70: PM Approved Invoices (SAR) | Q70: ='Invoice Log'!Y5 -> 0 | S70: Planned Value (SR) | T70: =#REF! -> #REF! | W70: ='HSE-Stat'!B17 -> No.of Internal Audit | Y70: ='HSE-Stat'!D17 -> 0 | AA70: ='HSE-Stat'!E17 -> 0 | AB70: ='HSE-Stat'!F17 -> 3 | AC70: ='HSE-Stat'!G17 -> 3
A71: TOTAL | C71: =SUM(C66:C70) -> 90 | D71: =SUM(D66:D70) -> 0 | E71: =SUM(E66:E70) -> 86 | F71: =SUM(F66:F70) -> 2 | G71: =SUM(G66:G70) -> 2 | H71: =SUM(H66:H70) -> 0 | I71: =SUM(I66:I70) -> 0 | J71: =SUM(J66:J70) -> 90 | K71: No of Paid Invoices | M71: ='Invoice Log'!U6 -> 0 | N71: Paid Invoices (SAR) | Q71: ='Invoice Log'!Y6 -> 0 | S71: Earned Value (SR) | T71: =H23 -> 0 | W71: ='HSE-Stat'!B18 -> No. of Toolbox Talks - Sessions(Headcount) | Y71: ='HSE-Stat'!D18 -> 1(8) | AA71: ='HSE-Stat'!E18 -> 3(27) | AB71: ='HSE-Stat'!F18 -> 17(230) | AC71: ='HSE-Stat'!G18 -> 17(230)
A72: Procurement Summary | K72: No of Pending Invoices | M72: =M70-M71 -> 0 | N72: Last Submitted Period | Q72: ='Invoice Log'!AB3 -> 46275 | S72: Submitted (SAR) | T72: =Q69 -> 3502841.3 | W72: ='HSE-Stat'!B19 -> Safety Awards/Incentives | Y72: ='HSE-Stat'!D19 -> 0 | AA72: ='HSE-Stat'!E19 -> 0 | AB72: ='HSE-Stat'!F19 -> 0 | AC72: ='HSE-Stat'!G19
A73: Item Per WBS | C73: Total Materials | D73: Total Number of P.O. | E73: Actual P.O. To Date | F73: Remaining P.O | G73: Material on Site | H73: Material Delivery Completion (Date) | K73: Advance Payment % | M73: ='Invoice Log'!M3 -> 0 | N73: Advance Payment (SAR) | Q73: ='Invoice Log'!Q3 -> 0 | S73: PM Approved (SAR) | T73: =Q70 -> 0 | V73: Latest Contract Change Order Log
D74: A | E74: B | F74: C | G74: D | K74: Retention % | M74: ='Invoice Log'!M4 -> 0 | N74: Retention (SAR) | Q74: ='Invoice Log'!Q4 -> 0 | S74: Total Paid (SAR) | T74: =Q71 -> 0
K75: Deduction / Penalties % | M75: ='Invoice Log'!M5 -> 0 | N75: Deduction / Penalties (SAR) | Q75: ='Invoice Log'!M6 -> 0 | V75: CCO No. | W75: Date Added | X75: Description of Change | AC75: Status | AD75: Cost | AE75: Sch Impact (Months) | AF75: Date Approved | AG75: Duration
K76: Resources at Site
K77: Head Count - Non Manual | O77: Head Count - Manual | S77: Total Head Count | V77: =CCO!A3 -> 0 | W77: =CCO!B3 -> 0 | X77: =CCO!C3 -> 0 | AC77: =CCO!D3 -> 0 | AD77: =CCO!E3 -> 0 | AE77: =CCO!F3 -> 0 | AF77: =CCO!G3 -> 0 | AG77: =CCO!H3 -> 0
K78: Planned | L78: Actual | M78: Next Month Forecast | N78: Saudi Staff | O78: Planned | P78: Actual | Q78: Next Month Forecast | R78: Saudi Staff | S78: Total Plan | T78: Total Actual | U78: Variance
K79: =Manpower!F3 -> 8 | L79: =Manpower!F5 -> 11 | M79: 11 | N79: 2 | O79: =Manpower!F11 -> 15 | P79: =Manpower!F13 -> 108 | Q79: =O79 -> 15 | R79: 0 | S79: =K79+O79 -> 23 | T79: =L79+P79 -> 119 | U79: =+T79-S79 -> 96 | V79: =CCO!A4 | W79: =CCO!B4 | X79: =CCO!C4 | AC79: =IF(CCO!D4="","",CCO!D4) | AD79: =CCO!E4 | AE79: =CCO!F4 | AF79: =CCO!G4 | AG79: =CCO!H4
A80: TOTAL | C80: =IF('Quality-Stat'!D41="","",'Quality-Stat'!D41) | D80: =IF('Quality-Stat'!E41="","",'Quality-Stat'!E41) | E80: =IF('Quality-Stat'!F41="","",'Quality-Stat'!F41) | F80: =IF('Quality-Stat'!G41="","",'Quality-Stat'!G41) | G80: =IF('Quality-Stat'!H41="","",'Quality-Stat'!H41) | K80: Manpower Breakdown by Trade | R80: Major Equipment
A81: =Schedule!A1 -> Primavera P6 Schedule Status | K81: Key Trade | L81: Planned | M81: Actual | R81: Type | S81: Planned | T81: Actual | U81: Idle | V81: =CCO!A5 | W81: =CCO!B5 | X81: =CCO!C5 | AC81: =IF(CCO!D5="","",CCO!D5) | AD81: =CCO!E5 | AE81: =CCO!F5 | AF81: =CCO!G5 | AG81: =CCO!H5
A82: =Schedule!A2 -> Project Activities Overview | K82: =+Manpower!N23 -> General Labor | L82: 8 | M82: 13 | R82: =+Manpower!$B$49 -> Excavator | S82: 2 | T82: 5 | U82: =+Manpower!B52 -> 0
A83: =Schedule!A3 -> Schedule Statistics | F83: =Schedule!F3 -> Active Schedule Activities | K83: =+Manpower!P23 -> Carpenter | L83: 0 | M83: 0 | R83: =+Manpower!$D$49 -> Loader | S83: 0 | T83: 0 | U83: =+Manpower!D52 -> 0 | V83: Major Quantity Trackers
A84: =Schedule!A4 -> Total Act. | B84: =Schedule!B4 -> Not Started | C84: =Schedule!C4 -> In Progress | D84: =Schedule!D4 -> Completed | E84: =Schedule!E4 -> % | F84: =Schedule!F4 -> Active | G84: =Schedule!G4 -> Ahead | H84: =Schedule!I4 -> Behind | I84: =Schedule!J4 -> Flag | J84: =Schedule!K4 -> 0 | K84: =+Manpower!R23 -> Plumber | L84: 0 | M84: 0 | R84: =+Manpower!$F$49 -> Dozer | S84: =+Manpower!F50 -> 0 | T84: =+Manpower!F51 -> 0 | U84: =+Manpower!F52 -> 0 | V84: BOQ N0. | W84: Item Description | AB84: Total Qty | AC84: Measu Unit | AD84: Plan to Date | AE84: Act to Date | AF84: Remaining | AG84: Variance
A85: =Schedule!A5 -> 554 | B85: =Schedule!B5 -> 390 | C85: =Schedule!C5 -> 63 | D85: =Schedule!D5 -> 101 | E85: =Schedule!E5 -> 0.18231047 | F85: =Schedule!F5 -> 63 | G85: =Schedule!G5 -> 101 | H85: =Schedule!I5 -> 0 | I85: =Schedule!J5 -> 126 | K85: =+Manpower!T23 -> Operator | L85: 0 | M85: 0 | R85: =+Manpower!$H$49 -> Dumper | S85: =+Manpower!H50 -> 0 | T85: 0 | U85: =+Manpower!H52 -> 0 | V85: ='Major Quantities'!A2 -> 0 | W85: ='Major Quantities'!B2 -> 0 | AB85: ='Major Quantities'!C2 -> 0 | AC85: ='Major Quantities'!D2 -> 0 | AD85: ='Major Quantities'!E2 -> 0 | AE85: ='Major Quantities'!F2 -> 0 | AF85: ='Major Quantities'!G2 -> 0 | AG85: ='Major Quantities'!H2 -> 0
A86: =Schedule!A6 -> Critical Path Activities | D86: =Schedule!D6 -> Free Float Management (Total) | K86: =+Manpower!V23 -> Steel Fixer | L86: 10 | M86: 35 | R86: =+Manpower!$J$49 -> Crane | S86: 0 | T86: 0 | U86: =+Manpower!J52 -> 0 | V86: ='Major Quantities'!A3 -> 0 | W86: ='Major Quantities'!B3 -> 0 | AB86: ='Major Quantities'!C3 -> 0 | AC86: ='Major Quantities'!D3 -> 0 | AD86: ='Major Quantities'!E3 -> 0 | AE86: ='Major Quantities'!F3 -> 0 | AF86: ='Major Quantities'!G3 -> 0 | AG86: ='Major Quantities'!H3 -> 0
D87: =Schedule!D7 -> Greater Than 14 Days | F87: =Schedule!F7 -> Less Than 14 Days | K87: =+Manpower!X23 -> Mason | L87: 0 | M87: 0 | R87: =+Manpower!$L$49 -> Grader | S87: =+Manpower!L50 -> 0 | T87: 0 | U87: =+Manpower!L52 -> 0 | V87: ='Major Quantities'!A4 -> 0 | W87: ='Major Quantities'!B4 -> 0 | AB87: ='Major Quantities'!C4 -> 0 | AC87: ='Major Quantities'!D4 -> 0 | AD87: ='Major Quantities'!E4 -> 0 | AE87: ='Major Quantities'!F4 -> 0 | AF87: ='Major Quantities'!G4 -> 0 | AG87: ='Major Quantities'!H4 -> 0
A88: =Schedule!A8 -> Last Week | B88: =Schedule!B8 -> This Week | C88: =Schedule!C8 -> Diff | D88: =Schedule!D8 -> Last Week | E88: =Schedule!E8 -> This Week | F88: =Schedule!F8 -> Last Week | G88: =Schedule!G8 -> This Week | H88: =Schedule!I8 -> This Week | I88: =Schedule!J8 -> Flag | J88: =Schedule!K8 -> 0 | K88: =+Manpower!Z23 -> Others | L88: 5 | M88: 60 | R88: =+Manpower!$N$49 -> Other | S88: 1 | T88: 3 | U88: =+Manpower!N52 -> 0 | V88: ='Major Quantities'!A5 -> 0 | W88: ='Major Quantities'!B5 -> 0 | AB88: ='Major Quantities'!C5 -> 0 | AC88: ='Major Quantities'!D5 -> 0 | AD88: ='Major Quantities'!E5 -> 0 | AE88: ='Major Quantities'!F5 -> 0 | AF88: ='Major Quantities'!G5 -> 0 | AG88: ='Major Quantities'!H5 -> 0
A89: =Schedule!A9 -> 0 | B89: =Schedule!B9 -> 0 | C89: =Schedule!C9 -> 0 | D89: =Schedule!D9 -> 33 | E89: =Schedule!E9 -> 33 | F89: =Schedule!F9 -> 225 | G89: =Schedule!G9 -> 225 | H89: =Schedule!I9 -> 28 | I89: =Schedule!J9 -> 1 | K89: Total | L89: =SUM(L82:L88) -> 23 | M89: =SUM(M82:M88) -> 108 | R89: Total | S89: =SUM(S82:S88) -> 3 | T89: =SUM(T82:T88) -> 8 | U89: =SUM(U82:U88) -> 0 | V89: ='Major Quantities'!A6 -> 0 | W89: ='Major Quantities'!B6 -> 0 | AB89: ='Major Quantities'!C6 -> 0 | AC89: ='Major Quantities'!D6 -> 0 | AD89: ='Major Quantities'!E6 -> 0 | AE89: ='Major Quantities'!F6 -> 0 | AF89: ='Major Quantities'!G6 -> 0 | AG89: ='Major Quantities'!H6 -> 0
A90: Weekly Prgoress Photos | P90: Top Issues and Risks
A91: ='Weekly Photos'!B23 -> Fence Works | F91: ='Weekly Photos'!L23 -> Fence Works | K91: ='Weekly Photos'!B4 -> S.O.G Works | P91: Top 5 Issues
P92: Issue No | Q92: Date Identified | R92: Issue Description | V92: Responsible | W92: Action Taken | Z92: Mitigation | AE92: Current Status | AF92: Expected/Actual Closure | AG92: Duration Elapsed
P93: =IF(+Issues!B11="","",+Issues!B11) -> 1 | Q93: =IF(+Issues!C11="","",+Issues!C11) | R93: =IF(+Issues!D11="","",+Issues!D11) | V93: =IF(+Issues!E11="","",+Issues!E11) | W93: =IF(+Issues!F11="","",+Issues!F11) | AE93: =IF(+Issues!H11="","",+Issues!H11) | AF93: =IF(+Issues!I11="","",+Issues!I11) | AG93: =IF(+Issues!J11="","",+Issues!J11)
P94: =IF(+Issues!B12="","",+Issues!B12) -> 2 | Q94: =IF(+Issues!C12="","",+Issues!C12) | R94: =IF(+Issues!D12="","",+Issues!D12) | V94: =IF(+Issues!E12="","",+Issues!E12) | W94: =IF(+Issues!F12="","",+Issues!F12) | AE94: =IF(+Issues!H12="","",+Issues!H12) | AF94: =IF(+Issues!I12="","",+Issues!I12) | AG94: =IF(+Issues!J12="","",+Issues!J12)
P95: =IF(+Issues!B13="","",+Issues!B13) -> 3 | Q95: =IF(+Issues!C13="","",+Issues!C13) | R95: =IF(+Issues!D13="","",+Issues!D13) | V95: =IF(+Issues!E13="","",+Issues!E13) | W95: =IF(+Issues!F13="","",+Issues!F13) | AE95: =IF(+Issues!H13="","",+Issues!H13) | AF95: =IF(+Issues!I13="","",+Issues!I13) | AG95: =IF(+Issues!J13="","",+Issues!J13)
P96: =IF(+Issues!B14="","",+Issues!B14) -> 4 | Q96: =IF(+Issues!C14="","",+Issues!C14) | R96: =IF(+Issues!D14="","",+Issues!D14) | V96: =IF(+Issues!E14="","",+Issues!E14) | W96: =IF(+Issues!F14="","",+Issues!F14) | AE96: =IF(+Issues!H14="","",+Issues!H14) | AF96: =IF(+Issues!I14="","",+Issues!I14) | AG96: =IF(+Issues!J14="","",+Issues!J14)
P97: =IF(+Issues!B15="","",+Issues!B15) -> 5 | Q97: =IF(+Issues!C15="","",+Issues!C15) | R97: =IF(+Issues!D15="","",+Issues!D15) | V97: =IF(+Issues!E15="","",+Issues!E15) | W97: =IF(+Issues!F15="","",+Issues!F15) | AE97: =IF(+Issues!H15="","",+Issues!H15) | AF97: =IF(+Issues!I15="","",+Issues!I15) | AG97: =IF(+Issues!J15="","",+Issues!J15)

Sheet Sheet1
B2: Planned (%) | C2: Earned (%)
A3: KUMT-05-001.6 Engineering | B3: =Progress!G8 -> 0 | C3: =Progress!H8 -> 0
A4: KUMT-05-001.7 Procurement | B4: =Progress!G10 -> 3045396.1 | C4: =Progress!H10 -> 1896470.1
A5: KUMT-05-001.3 Construction | B5: =Progress!G11 -> 8643246.6 | C5: =Progress!H11 -> 4176919.2

Sheet Progress
A1: Project Scope Statement | R1: ='General Information'!$K$1 -> Data Date | S1: ='General Information'!L1 -> 46286
A4: Earned Value Progress (SAR) | J4: Physical Progress (Effort) | Q4: Previous week EV | T4: Previous week Effort
A5: WBS | B5: BOQ Value (SAR) | C5: % Wt. | D5: Weekly (SAR) | G5: To Date (SAR) | J5: Budgeted | K5: % Wt. | L5: Weekly Physical Progress | N5: To Date Physical Progress
D6: Planned | E6: Earned | F6: Original Plan | G6: Planned | H6: Earned | J6: (Manhours) | L6: Planned | M6: Earned | N6: Planned | O6: Earned | Q6: Planned | R6: Earned | T6: Planned | U6: Earned
A7: WAS1-05-006 - B1 - B1 - B1 - B1.2 Mobilization | B7: 0 | C7: =IF(ISBLANK(B7),"",B7/$B$18) -> 0 | D7: =G7-Q7 -> 0 | E7: =H7-R7 -> 0 | F7: 0 | G7: 0 | H7: 0 | J7: 2956 | K7: =J7/$J$18 -> 0.029936906 | L7: =N7-T7 -> 0 | M7: =O7-U7 -> 0 | N7: 2956 | O7: 2956 | Q7: 0 | R7: 0 | T7: 2956 | U7: 2956
A8: WAS1-05-006 - B1 - B1 - B1 - B1.3 Preliminary Submittals | B8: 0 | C8: =IF(ISBLANK(B8),"",B8/$B$18) -> 0 | D8: =G8-Q8 -> 0 | E8: =H8-R8 -> 0 | F8: 0 | G8: 0 | H8: 0 | J8: 0 | K8: =J8/$J$18 -> 0 | L8: =N8-T8 -> 0 | M8: =O8-U8 -> 0 | N8: 0 | O8: 0 | Q8: 0 | R8: 0 | T8: 0 | U8: 0
A9: WAS1-05-006 - B1 - B1 - B1 - B1.6 Engineering | B9: 476989.77 | C9: =IF(ISBLANK(B9),"",B9/$B$18) -> 0.030001887 | D9: =G9-Q9 -> 8112.07 | E9: =H9-R9 -> 973.44 | F9: 473744.95 | G9: 473744.95 | H9: 181061.42 | J9: 4927 | K9: =J9/$J$18 -> 0.049898219 | L9: =N9-T9 -> 62 | M9: =O9-U9 -> 154 | N9: 4911 | O9: 2854 | Q9: 465632.88 | R9: 180087.98 | T9: 4849 | U9: 2700
A10: WAS1-05-006 - B1 - B1 - B1 - B1.7 Procurement | B10: 3179931.7 | C10: =IF(ISBLANK(B10),"",B10/$B$18) -> 0.20001257 | D10: =G10-Q10 -> 168485.46 | E10: =H10-R10 -> 0 | F10: 3045396.1 | G10: 3045396.1 | H10: 1896470.1 | J10: 12811 | K10: =J10/$J$18 -> 0.12974347 | L10: =N10-T10 -> 3846 | M10: =O10-U10 -> 0 | N10: 9740 | O10: 2301 | Q10: 2876910.7 | R10: 1896470.1 | T10: 5894 | U10: 2301
A11: WAS1-05-006 - B1 - B1 - B1 - B1.8 Construction | B11: 10651772 | C11: =IF(ISBLANK(B11),"",B11/$B$18) -> 0.66997925 | D11: =G11-Q11 -> 1776303 | E11: =H11-R11 -> 1557929 | F11: 8643246.6 | G11: 8643246.6 | H11: 4176919.2 | J11: 73908 | K11: =J11/$J$18 -> 0.74850366 | L11: =N11-T11 -> 8524 | M11: =O11-U11 -> 2219 | N11: 45493 | O11: 11978 | Q11: 6866943.6 | R11: 2618990.1 | T11: 36969 | U11: 9759
A12: WAS1-05-006 - B1 - B1 - B1 - B1.8.1 FENCES | B12: 9040220 | C12: =IF(ISBLANK(B12),"",B12/$B$18) -> 0.56861525 | D12: =F12-Q12 -> 1676971.3 | E12: =H12-R12 -> 1536539.6 | F12: 7906683.8 | G12: 7906683.8 | H12: 4096091.3 | J12: 4885 | K12: =J12/$J$18 -> 0.049472863 | L12: =N12-T12 -> 750 | M12: =O12-U12 -> 484 | N12: 4227 | O12: 2183 | Q12: 6229712.5 | R12: 2559551.7 | T12: 3477 | U12: 1699
A13: WAS1-05-006 - B1 - B1 - B1 - B1.8.2 GUARD HOUSE 1 | B13: 438683.2 | C13: =IF(ISBLANK(B13),"",B13/$B$18) -> 0.027592465 | D13: =F13-Q13 -> 17202.44 | E13: =H13-R13 -> 8065.64 | F13: 153069.53 | G13: 153069.53 | H13: 35100.37 | J13: 22300 | K13: =J13/$J$18 -> 0.22584337 | L13: =N13-T13 -> 2530 | M13: =O13-U13 -> 483 | N13: 11323 | O13: 3732 | Q13: 135867.09 | R13: 27034.73 | T13: 8793 | U13: 3249
A14: WAS1-05-006 - B1 - B1 - B1 - B1.8.3 GUARD HOUSE 2 | B14: 438683.2 | C14: =IF(ISBLANK(B14),"",B14/$B$18) -> 0.027592465 | D14: =F14-Q14 -> 15771.65 | E14: =H14-R14 -> 5479.23 | F14: 197325.23 | G14: 197325.23 | H14: 10848.26 | J14: 22300 | K14: =J14/$J$18 -> 0.22584337 | L14: =N14-T14 -> 2410 | M14: =O14-U14 -> 775 | N14: 14176 | O14: 2336 | Q14: 181553.58 | R14: 5369.03 | T14: 11766 | U14: 1561
A15: WAS1-05-006 - B1 - B1 - B1 - B1.8.5 GUARD HOUSE 3 | B15: 438683.2 | C15: =IF(ISBLANK(B15),"",B15/$B$18) -> 0.027592465 | D15: =F15-Q15 -> 15771.65 | E15: =H15-R15 -> 7844.51 | F15: 197325.23 | G15: 197325.23 | H15: 34879.24 | J15: 22300 | K15: =J15/$J$18 -> 0.22584337 | L15: =N15-T15 -> 2410 | M15: =O15-U15 -> 478 | N15: 14176 | O15: 3727 | Q15: 181553.58 | R15: 27034.73 | T15: 11766 | U15: 3249
A16: WAS1-05-006 - B1 - B1 - B1 - B1.8.4 EXT. WORKS | B16: 295502.16 | C16: =IF(ISBLANK(B16),"",B16/$B$18) -> 0.018586609 | D16: =F16-Q16 -> 50585.98 | E16: =H16-R16 -> 0 | F16: 188842.83 | G16: 188842.83 | H16: 0 | J16: 2320 | K16: =J16/$J$18 -> 0.023495812 | L16: =N16-T16 -> 422 | M16: =O16-U16 -> 0 | N16: 1590 | O16: 0 | Q16: 138256.85 | R16: 0 | T16: 1168 | U16: 0
A17: WAS1-05-006 - B1 - B1 - B1 - B1.4 Testing & Commissioning | B17: 1589965.9 | C17: =IF(ISBLANK(B17),"",B17/$B$18) -> 0.10000629 | D17: =F17-Q17 -> 0 | E17: =H17-R17 -> 0 | F17: 0 | G17: 0 | H17: 0 | J17: 3942 | K17: =J17/$J$18 -> 0.039922626 | L17: =N17-T17 -> 0 | M17: =O17-U17 -> 0 | N17: 0 | O17: 0 | Q17: 0 | R17: 0 | T17: 0 | U17: 0
B18: =SUM(B9:B10,B12:B17) -> 15898659 | C18: =SUM(C7:C10,C12:C17) -> 1 | D18: =SUM(D7:D11) -> 1952900.5 | E18: =SUM(E7:E11) -> 1558902.5 | F18: =SUM(F7:F11) -> 12162388 | G18: =SUM(G7:G11) -> 12162388 | H18: =SUM(H7:H11) -> 6254450.7 | J18: =SUM(J7:J10,J12:J17) -> 98741 | K18: =SUM(K7:K10,K12:K17) -> 1 | L18: =SUM(L7:L11) -> 12432 | M18: =SUM(M7:M11) -> 2373 | N18: =SUM(N7:N11) -> 63100 | O18: =SUM(O7:O11) -> 20089 | Q18: 10209487 | R18: 4695548.2 | T18: 50668 | U18: 17716
D19: =D18/$B$18 -> 0.12283429 | E19: =E18/$B$18 -> 0.098052449 | F19: =F18/$B$18 -> 0.76499456 | G19: =G18/$B$18 -> 0.76499456 | H19: =H18/$B$18 -> 0.39339486 | L19: =L18/$J$18 -> 0.12590515 | M19: =M18/$J$18 -> 0.02403257 | N19: =N18/$J$18 -> 0.63904558 | O19: =O18/$J$18 -> 0.20345145 | Q19: 0.64216026 | R19: 0.29534241 | T19: 0.51416104 | U19: 0.17977574
H21: =H19-G19 -> -0.3715997
O24: =O19-N19 -> -0.43559413

Sheet Weekly Photos
B1: Date | C1: ='Weekly Progress Report'!AF1 -> 46286
B4: S.O.G Works | L4: Fence Works
B23: Fence Works | L23: Fence Works

Sheet FIR Summary
A2: Project Name | C2: ='General Information'!C3 -> Improvement of Waad Al Shamal Industrial City Fence & Gates | I2: Total FIR Amount
A3: Project ID | C3: ='General Information'!C4 -> WAS1-05-006 | E3: Project Budget | F3: =Progress!B18 -> 15898659 | I3: 0
A4: Date Pariod | C4: Start Date | D4: =G4-6 -> 46280 | E4: To | F4: Data Date | G4: ='General Information'!L1 -> 46286 | I4: =Total -> 0
A6: BOQ Item # | B6: BOQ Description | C6: FIR # | D6: Date | E6: FIR Description | F6: Unit Rate | G6: Current Pariod Quantity | H6: Total (SR) | I6: Comments
H7: =F7*G7 -> 0
H8: =F8*G8 -> 0
A9: BILL NO.1 B1.02 00 00 | B9: BILL NO.3 STRUCTURAL WORKS | H9: =Total -> 0

Sheet Quality
B2: QC OBSERVATIONS CHECKLIST
BB4: ='General Information'!C14 -> 46148
B6: Project No. | E6: ='[47]General Information'!C4 -> WAS1-05-006 | K6: OBS No. | O6: 12 | U6: Inspection Day: | X6: 46284
B8: Project | E8: ='[47]General Information'!C3 -> Improvement of Waad Al Shamal Industrial City Fence & Gates | O8: Contractor: Consultant: | U8: ='[47]General Information'!C5&" "&'[47]General Information'!C6 -> Hamza Mohammad Alderi Construction Co. Consolidated Consultants Group
B10: 4 | D10: Excellent | G10: Quality Management System is being practiced and applies to MODON System | Z10: 90 - 100 | AB10: QC Overall Score | AC10: =Q49 -> 0.86206897 | AN10: =SUM(Z10:Z13) -> 0 | AO10: 100 | AP10: 0.22883295
B11: 3 | D11: Good | G11: Evidence of compliance with plans and procedures. | Z11: 80 - 89 | AN11: =SUM(Y10:Y14) -> 0 | AO11: 89 | AP11: 0.20366133
B12: 2 | D12: Average | G12: Indication level of compliance with standards but there is room for improvement | Z12: 70 - 79 | AO12: 79 | AP12: 0.18077803
B13: 1 | D13: Improve | G13: Quality and Control is NOT being managed effectively. Needs Improvement | Z13: ≤ 69 | AO13: 69 | AP13: 0.15789474
B14: 0 | D14: N/A | G14: Item was not applicable or this item was not reviewed during the inspection. | Z14: Zero | AO14: 100 | AP14: 0.22883295
B16: No. | C16: Topic | K16: E (4) | L16: G (3) | M16: A (2) | N16: I (1) | O16: N/A (0) | Q16: No. | R16: Topic | Z16: E (4) | AA16: G (3) | AB16: A (2) | AC16: I (1) | AD16: N/A (0) | AO16: =SUM(AO10:AO15) -> 437
K17: 1 | L17: 0.89 | M17: 0.79 | N17: 0.69 | O17: 1 | Z17: 1 | AA17: 0.89 | AB17: 0.79 | AC17: 0.69 | AD17: 1 | AF17: =SUM(AF18:AG46)/COUNT(AF18:AG46) -> 0.86206897
B18: 1 | C18: Control of Access to Site/Office | K18: 0 | L18: 1 | Q18: 30 | R18: QC of Excavation | Z18: 0 | AA18: 1 | AD18: 0 | AF18: =SUMPRODUCT($K$17:$O$17,K18:O18) -> 0.89 | AG18: =SUMPRODUCT($Z$17:$AD$17,Z18:AD18) -> 0.89 | AV18: Item Count | AW18: Score | AX18: Distributtion
B19: 2 | C19: Document Control Administration | K19: 0 | L19: 1 | M19: 0 | Q19: 31 | R19: QC of Roads/Round about | AA19: 0 | AD19: 1 | AF19: =SUMPRODUCT($K$17:$O$17,K19:O19) -> 0.89 | AG19: =SUMPRODUCT($Z$17:$AD$17,Z19:AD19) -> 1 | AX19: Overall | AY19: Relevant
B20: 3 | C20: Project Documents and Progress | L20: 1 | Q20: 32 | R20: QC of Interlock & Curbstone | Z20: 0 | AA20: 1 | AF20: =SUMPRODUCT($K$17:$O$17,K20:O20) -> 0.89 | AG20: =SUMPRODUCT($Z$17:$AD$17,Z20:AD20) -> 0.89 | AM20: 4 | AN20: =58 -> 58 | AO20: counts | AQ20: 4 | AR20: Excellent | AV20: =SUM(Z18:Z46,K18:K46) -> 2 | AW20: =AQ20*AV20 -> 8 | AX20: =AV20/$AV$25 -> 0.034482759 | AY20: =AV20/SUM($AV$20:$AV$23) -> 0.047619048
B21: 4 | C21: Contractor's Quality Plan/CM (Updated and Reviewed) | K21: 1 | M21: 0 | Q21: 33 | R21: Layers/Backfilling Sampling | Z21: 0 | AA21: 1 | AD21: 0 | AF21: =SUMPRODUCT($K$17:$O$17,K21:O21) -> 1 | AG21: =SUMPRODUCT($Z$17:$AD$17,Z21:AD21) -> 0.89 | AM21: 3 | AN21: =58 -> 58 | AO21: counts | AQ21: 3 | AR21: Good | AV21: =SUM(L18:L46,AA18:AA46) -> 14 | AW21: =AQ21*AV21 -> 42 | AX21: =AV21/$AV$25 -> 0.24137931 | AY21: =AV21/SUM($AV$20:$AV$23) -> 0.33333333
B22: 5 | C22: MS Log and Paperwork | K22: 0 | L22: 0 | M22: 1 | Q22: 34 | R22: Pump Stations Units | Z22: 0 | AA22: 0 | AB22: 0 | AD22: 1 | AF22: =SUMPRODUCT($K$17:$O$17,K22:O22) -> 0.79 | AG22: =SUMPRODUCT($Z$17:$AD$17,Z22:AD22) -> 1 | AM22: 2 | AN22: =58 -> 58 | AO22: counts | AQ22: 2 | AR22: Average | AV22: =SUM(M18:M46,AB18:AB46) -> 16 | AW22: =AQ22*AV22 -> 32 | AX22: =AV22/$AV$25 -> 0.27586207 | AY22: =AV22/SUM($AV$20:$AV$23) -> 0.38095238 | BC22: NB: Insert 1, or 0 in the required cell only.
B23: 6 | C23: RFI, FIR, & MIR Procedure | K23: 0 | L23: 1 | Q23: 35 | R23: Quality of Form Work | Z23: 1 | AA23: 0 | AD23: 0 | AF23: =SUMPRODUCT($K$17:$O$17,K23:O23) -> 0.89 | AG23: =SUMPRODUCT($Z$17:$AD$17,Z23:AD23) -> 1 | AM23: 1 | AN23: =58 -> 58 | AO23: counts | AQ23: 1 | AR23: Improve | AV23: =SUM(N18:N46,AC18:AC46) -> 10 | AW23: =AQ23*AV23 -> 10 | AX23: =AV23/$AV$25 -> 0.17241379 | AY23: =AV23/SUM($AV$20:$AV$23) -> 0.23809524
B24: 7 | C24: RFI, FIR, & MIR Inventory system | K24: 0 | L24: 1 | Q24: 36 | R24: Design Change List | AC24: 0 | AD24: 1 | AF24: =SUMPRODUCT($K$17:$O$17,K24:O24) -> 0.89 | AG24: =SUMPRODUCT($Z$17:$AD$17,Z24:AD24) -> 1 | AM24: 0 | AN24: =58 -> 58 | AO24: counts | AQ24: 0 | AR24: N/A | AV24: =SUM(O18:O46,AD18:AD46) -> 16 | AW24: =AQ24*AV24 -> 0 | AX24: =AV24/$AV$25 -> 0.27586207 | AY24: -
B25: 8 | C25: NCRs Control & Procedure | K25: 0 | L25: 0 | M25: 1 | O25: 0 | Q25: 37 | R25: Quality of Concrete Placing | Z25: 0 | AA25: 0 | AB25: 1 | AF25: =SUMPRODUCT($K$17:$O$17,K25:O25) -> 0.79 | AG25: =SUMPRODUCT($Z$17:$AD$17,Z25:AD25) -> 0.79 | AR25: Total | AV25: =SUM(AV20:AV24) -> 58 | AW25: =SUM(AW20:AW24) -> 92 | AX25: =SUM(AX20:AX24) -> 1 | AY25: =SUM(AY20:AY24) -> 1
B26: 9 | C26: NCR Log | K26: 0 | M26: 1 | O26: 0 | Q26: 38 | R26: Concrete Surface Finishing | Z26: 0 | AA26: 0 | AB26: 1 | AF26: =SUMPRODUCT($K$17:$O$17,K26:O26) -> 0.79 | AG26: =SUMPRODUCT($Z$17:$AD$17,Z26:AD26) -> 0.79
B27: 10 | C27: MODON Standard* | K27: 0 | L27: 1 | Q27: 39 | R27: Pedestals/Columns/Beams Alignment | Z27: 0 | AA27: 0 | AB27: 1 | AF27: =SUMPRODUCT($K$17:$O$17,K27:O27) -> 0.89 | AG27: =SUMPRODUCT($Z$17:$AD$17,Z27:AD27) -> 0.79 | AV27: Maz Score Available: | AW27: =SUM(AV20:AV23)*AQ20 -> 168 | AX27: <- Excludes N/A items
B28: 11 | C28: Project Risk Plan/Management* | K28: 0 | L28: 0 | M28: 1 | Q28: 40 | R28: Siporex Lifting & Unloading | AA28: 0 | AB28: 0 | AD28: 1 | AF28: =SUMPRODUCT($K$17:$O$17,K28:O28) -> 0.79 | AG28: =SUMPRODUCT($Z$17:$AD$17,Z28:AD28) -> 1
B29: 12 | C29: Monthly Quality Reports* | K29: 0 | L29: 0 | M29: 1 | Q29: 41 | R29: Siporex Quality Pre-installation | AA29: 0 | AD29: 1 | AF29: =SUMPRODUCT($K$17:$O$17,K29:O29) -> 0.79 | AG29: =SUMPRODUCT($Z$17:$AD$17,Z29:AD29) -> 1
B30: 13 | C30: ITP | K30: 0 | L30: 1 | Q30: 42 | R30: Siporex Finishing Quality | Z30: 0 | AA30: 0 | AD30: 1 | AF30: =SUMPRODUCT($K$17:$O$17,K30:O30) -> 0.89 | AG30: =SUMPRODUCT($Z$17:$AD$17,Z30:AD30) -> 1 | AR30: Total Score | AW30: Percentage (%)
B31: 14 | C31: MODON Weekly Report | K31: 0 | L31: 1 | Q31: 43 | R31: Roads / Parking Markings | AA31: 0 | AD31: 1 | AF31: =SUMPRODUCT($K$17:$O$17,K31:O31) -> 0.89 | AG31: =SUMPRODUCT($Z$17:$AD$17,Z31:AD31) -> 1 | AN31: =MAX(AN20:AN24) -> 58 | AR31: =AW25 -> 92 | AW31: =SUM(100/AR33*AR31) -> 54.761905 | AY31: %
B32: 15 | C32: Design Change Official Paperwork* | K32: 0 | L32: 0 | O32: 1 | Q32: 44 | R32: QC of Finishing Outdoors | Z32: 0 | AA32: 0 | AD32: 1 | AF32: =SUMPRODUCT($K$17:$O$17,K32:O32) -> 1 | AG32: =SUMPRODUCT($Z$17:$AD$17,Z32:AD32) -> 1 | AR32: Max Score Available | BP32: 31
B33: 16 | C33: Design Change was Applied* | K33: 0 | L33: 0 | O33: 1 | Q33: 45 | R33: Quality of Finishing Indoors | Z33: 0 | AA33: 0 | AD33: 1 | AF33: =SUMPRODUCT($K$17:$O$17,K33:O33) -> 1 | AG33: =SUMPRODUCT($Z$17:$AD$17,Z33:AD33) -> 1 | AR33: =AW27 -> 168 | BP33: 32
B34: 17 | C34: Material List | K34: 0 | L34: 0 | N34: 1 | Q34: 46 | R34: Stairs Quality | Z34: 0 | AB34: 0 | AD34: 1 | AF34: =SUMPRODUCT($K$17:$O$17,K34:O34) -> 0.69 | AG34: =SUMPRODUCT($Z$17:$AD$17,Z34:AD34) -> 1 | BP34: 33
B35: 18 | C35: Pending Material Status | K35: 0 | N35: 1 | O35: 0 | Q35: 47 | R35: Tanks Method Statement Work | AC35: 1 | AD35: 0 | AF35: =SUMPRODUCT($K$17:$O$17,K35:O35) -> 0.69 | AG35: =SUMPRODUCT($Z$17:$AD$17,Z35:AD35) -> 0.69 | BP35: 34
B36: 19 | C36: Lifting Plan* | M36: 0 | N36: 1 | O36: 0 | Q36: 48 | R36: Electric Rooms | Z36: 0 | AC36: 1 | AD36: 0 | AF36: =SUMPRODUCT($K$17:$O$17,K36:O36) -> 0.69 | AG36: =SUMPRODUCT($Z$17:$AD$17,Z36:AD36) -> 0.69 | BP36: 35
B37: 20 | C37: DWG Log | K37: 0 | M37: 1 | Q37: 49 | R37: QC of MCC/ATS Plant Units | Z37: 0 | AD37: 1 | AF37: =SUMPRODUCT($K$17:$O$17,K37:O37) -> 0.79 | AG37: =SUMPRODUCT($Z$17:$AD$17,Z37:AD37) -> 1 | BP37: 36
B38: 21 | C38: Invoice Status | K38: 0 | L38: 0 | M38: 1 | N38: 0 | O38: 0 | Q38: 50 | R38: Qualified Subcontractor | Z38: 0 | AA38: 1 | AD38: 0 | AF38: =SUMPRODUCT($K$17:$O$17,K38:O38) -> 0.79 | AG38: =SUMPRODUCT($Z$17:$AD$17,Z38:AD38) -> 0.89 | BP38: 37
B39: 22 | C39: Site Handover Letter | K39: 0 | L39: 0 | O39: 1 | Q39: 51 | R39: Scaffold/Ladders/Slope/Bridge Compliance | Z39: 0 | AC39: 1 | AD39: 0 | AF39: =SUMPRODUCT($K$17:$O$17,K39:O39) -> 1 | AG39: =SUMPRODUCT($Z$17:$AD$17,Z39:AD39) -> 0.69 | BP39: 38
B40: 23 | C40: Material Testing Results & Certification | K40: 0 | L40: 1 | Q40: 52 | R40: Protection Applied to Completed Work | AC40: 1 | AD40: 0 | AF40: =SUMPRODUCT($K$17:$O$17,K40:O40) -> 0.89 | AG40: =SUMPRODUCT($Z$17:$AD$17,Z40:AD40) -> 0.69
B41: 24 | C41: As Build Drawings Status* | L41: 0 | O41: 1 | Q41: 53 | R41: Storage Management in/out Control | Z41: 0 | AA41: 0 | AB41: 1 | AC41: 0 | AF41: =SUMPRODUCT($K$17:$O$17,K41:O41) -> 1 | AG41: =SUMPRODUCT($Z$17:$AD$17,Z41:AD41) -> 0.79
B42: 25 | C42: Calibrated Lab Tools & Equipment | K42: 0 | M42: 1 | Q42: 54 | R42: Material Control | Z42: 0 | AA42: 0 | AB42: 1 | AC42: 0 | AF42: =SUMPRODUCT($K$17:$O$17,K42:O42) -> 0.79 | AG42: =SUMPRODUCT($Z$17:$AD$17,Z42:AD42) -> 0.79
B43: 26 | C43: Storage Inventory System | M43: 0 | N43: 1 | Q43: 55 | R43: Manholes Storing and Quality | AA43: 0 | AD43: 1 | AF43: =SUMPRODUCT($K$17:$O$17,K43:O43) -> 0.69 | AG43: =SUMPRODUCT($Z$17:$AD$17,Z43:AD43) -> 1
B44: 27 | C44: Logistics Plan | N44: 1 | Q44: 56 | R44: Reinforced Steel Quality | Z44: 0 | AA44: 1 | AF44: =SUMPRODUCT($K$17:$O$17,K44:O44) -> 0.69 | AG44: =SUMPRODUCT($Z$17:$AD$17,Z44:AD44) -> 0.89
B45: 28 | C45: Project Progress Planview | L45: 0 | M45: 0 | N45: 1 | Q45: 57 | R45: Safety Overview | Z45: 0 | AA45: 0 | AB45: 1 | AC45: 0 | AF45: =SUMPRODUCT($K$17:$O$17,K45:O45) -> 0.69 | AG45: =SUMPRODUCT($Z$17:$AD$17,Z45:AD45) -> 0.79
B46: 29 | C46: Sufficient Number of QC Inspectors | K46: 0 | M46: 1 | N46: 0 | O46: 0 | Q46: 58 | R46: Waste Management Control | Z46: 0 | AA46: 0 | AB46: 1 | AF46: =SUMPRODUCT($K$17:$O$17,K46:O46) -> 0.79 | AG46: =SUMPRODUCT($Z$17:$AD$17,Z46:AD46) -> 0.79
O47: 0
I48: Score
M49: *QC % | Q49: =AF17 -> 0.86206897
B51: Prepared by: | G51: Engr Imad Ali | Q51: Issued to PM: | V51: Eng. Mohammed Essa
B53: *QC Observations refer only to the practices and documentation observed at time of inspection. The responsibility of the CM and Contractor is to ensure that aspects of Quality are suitably managed. *Scores are a reflection of the general site conditions based upon the findings at the time of the walk through *If Applicable

Sheet Quality-Stat
A1: Quality Reports
A2: Item | C2: Issued | D2: Closed | E2: Pending | F2: Avg. Closing (Days) | G2: Pending
G3: 0-10 Days | H3: 11-20 Days | I3: 21-30 Days | J3: 31-60 Days | K3: > 60 Days
A5: Non Conforomance Report (NCR) | C5: 0 | D5: 0 | E5: =+C5-D5 -> 0 | F5: 0 | G5: 0 | H5: 0 | I5: 0 | J5: 0 | K5: 0
A6: Site Instruction (SI) | C6: 0 | D6: 0 | E6: 0 | F6: 0 | G6: 0 | H6: 0 | I6: 0 | J6: 0 | K6: 0
A7: Material Inspection Report (MIR) | C7: 29 | D7: 24 | E7: 5 | F7: 0 | G7: 0 | H7: 0 | I7: 0 | J7: 0 | K7: 0
A8: Field Inspection Report (FIR) | C8: 265 | D8: 229 | E8: 36 | F8: 0 | G8: 0 | H8: 0 | I8: 0 | J8: 0 | K8: 0
A10: Shop Drawings
A11: Item Per WBS | D11: Total | E11: Total Drawings Submitted | J11: Remaining Drawings | K11: Pending | L11: Total Submittals
E12: A | F12: B | G12: C | H12: D | I12: Processed | J12: with Designer | K12: Submittals With Consultant
A13: Civil | D13: 13 | E13: 5 | F13: 7 | G13: 0 | H13: 1 | I13: =SUM(E13:H13) -> 13 | J13: =D13-L13 -> 0 | K13: 0 | L13: =I13+K13 -> 13
A14: Structural | C14: Structural | E14: 0 | F14: 0 | G14: 0 | H14: 0 | I14: =SUM(E14:H14) -> 0 | J14: =D14-L14 -> 0 | L14: =I14+K14 -> 0
A15: Architectural | C15: Architectural | D15: 10 | E15: 3 | F15: 7 | G15: 0 | H15: 0 | I15: =SUM(E15:H15) -> 10 | J15: =D15-L15 -> 0 | K15: 0 | L15: =I15+K15 -> 10
A16: Mechanical | C16: Mechanical | D16: 4 | E16: 0 | F16: 4 | G16: 0 | H16: 0 | I16: =SUM(E16:H16) -> 4 | J16: =D16-L16 -> 0 | K16: 0 | L16: =I16+K16 -> 4
A17: Electrical | C17: Electrical | D17: 8 | E17: 0 | F17: 7 | G17: 0 | H17: 0 | I17: =SUM(E17:H17) -> 7 | J17: =D17-L17 -> 0 | K17: 1 | L17: =I17+K17 -> 8
A18: TOTAL | D18: =SUM(D13:D17) -> 35 | E18: =SUM(E13:E17) -> 8 | F18: =SUM(F13:F17) -> 25 | G18: =SUM(G13:G17) -> 0 | H18: =SUM(H13:H17) -> 1 | I18: =SUM(I13:I17) -> 34 | J18: =SUM(J13:J17) -> 0 | K18: =SUM(K13:K17) -> 1 | L18: =SUM(L13:L17) -> 35
A21: Material Approval
A22: Item Per WBS | D22: Total | E22: Total Materials Submitted | J22: Remaining to approve | K22: Pending | L22: Total Submittals
E23: A | F23: B | G23: C | H23: D | I23: Processed | J23: with Designer | K23: Submittals With Consultant
A24: Civil | D24: 23 | F24: 23 | I24: =SUM(E24:H24) -> 23 | J24: =D24-L24 -> 0 | K24: 0 | L24: =I24+K24 -> 23
A25: Structural | C25: Structural | I25: =SUM(E25:H25) -> 0 | J25: =D25-L25 -> 0 | L25: =I25+K25 -> 0
A26: Architectural | C26: Architectural | D26: 19 | F26: 18 | G26: 1 | I26: =SUM(E26:H26) -> 19 | J26: =D26-L26 -> 0 | K26: 0 | L26: =I26+K26 -> 19
A27: Mechanical | C27: Mechanical | D27: 27 | F27: 26 | G27: 0 | H27: 1 | I27: =SUM(E27:H27) -> 27 | J27: =D27-L27 -> 0 | K27: 0 | L27: =I27+K27 -> 27
A28: Electrical | C28: Electrical | D28: 21 | F28: 19 | G28: 1 | H28: 1 | I28: =SUM(E28:H28) -> 21 | J28: =D28-L28 -> 0 | K28: 0 | L28: =I28+K28 -> 21
A29: TOTAL | D29: =SUM(D24:D28) -> 90 | E29: =SUM(E24:E28) -> 0 | F29: =SUM(F24:F28) -> 86 | G29: =SUM(G24:G28) -> 2 | H29: =SUM(H24:H28) -> 2 | I29: =SUM(I24:I28) -> 90 | J29: =SUM(J24:J28) -> 0 | K29: =SUM(K24:K28) -> 0 | L29: =SUM(L24:L28) -> 90
A31: Procurement Summary
A32: Item Per WBS | D32: Total Materials | E32: Total Number of P.O. | F32: Actual P.O. To Date | G32: Remaining P.O | H32: Actual Material on Site | I32: Remaining Materials | J32: Material Delivery Completion (Date)
E33: A | F33: B | G33: C | H33: D | I33: Processed
A34: Civil
A35: Structural | C35: Structural
A36: Architectural | C36: Architectural
A37: Mechanical | C37: Mechanical
A38: Electrical | C38: Electrical
A39: TOTAL | D39: =SUM(D34:D38) -> 0 | E39: =SUM(E34:E38) -> 0 | F39: =SUM(F34:F38) -> 0 | G39: =SUM(G34:G38) -> 0 | H39: =SUM(H34:H38) -> 0 | I39: =SUM(I34:I38) -> 0 | J39: =MAX(J34:J38) -> 0
A41: Contractor Quality Inspections / Observations (Weekly Basis) | I41: Overall Average | J41: =AVERAGE(E43:E210) -> 0.89483333 | L41: Average Closing | M41: =AVERAGE(G43:G115) -> 1.0833333
A42: Week Number | B42: Date of Audit | C42: Date Issued | D42: Numbers Of Comments | E42: Quality Score | F42: Date Closed | G42: Closure Duration | I42: This Week Score | J42: =[48]Quality!AC10 -> 0.915 | L42: Average Number of Comments Per Audit | M42: =AVERAGE(D43:D115) -> 1.25
A43: Week-1 | B43: 46209 | C43: 46209 | D43: 2 | E43: 0.918 | F43: 46210 | G43: 1
A44: Week-2 | B44: 46216 | C44: 46216 | D44: 2 | E44: 0.91 | F44: 46218 | G44: 2
A45: Week-3 | B45: 46219 | C45: 46221 | D45: 2 | E45: 0.908 | F45: 46222 | G45: 1
A46: Week-4 | B46: 46226 | C46: 46228 | D46: 1 | E46: 0.9 | F46: 46229 | G46: 1
A47: Week-5 | B47: 46233 | C47: 46235 | D47: 1 | E47: 0.889 | F47: 46236 | G47: 1
A48: Week-6 | B48: 46240 | C48: 46242 | D48: 1 | E48: 0.9 | F48: 46243 | G48: 1
A49: Week-7 | B49: 46247 | C49: 46249 | D49: 1 | E49: 0.907 | F49: 46250 | G49: 1
A50: Week-8 | B50: 46254 | C50: 46256 | D50: 1 | E50: 0.907 | F50: 46257 | G50: 1
A51: Week-9 | B51: 46261 | C51: 46263 | D51: 1 | E51: 0.907 | F51: 46264 | G51: 1
A52: Week-10 | B52: 46268 | C52: 46270 | D52: 1 | E52: 0.864 | F52: 46271 | G52: 1
A53: Week-11 | B53: 46275 | C53: 46277 | D53: 1 | E53: 0.866 | F53: 46278 | G53: 1
A54: Week-12 | B54: 46282 | C54: 46284 | D54: 1 | E54: 0.862 | F54: 46285 | G54: 1
A55: Week-13
A56: Week-14
A57: Week-15
A58: Week-16
A59: Week-17
B208: =COUNTIF($C$131:$C$205,"C") -> 0
B209: =COUNTIF($C$131:$C$205,"S") -> 0
B210: =COUNTIF($C$131:$C$205,"A") -> 0
B211: =COUNTIF($C$131:$C$205,"M") -> 0
B212: =COUNTIF($C$131:$C$205,"E") -> 0

Sheet HSE
B1: MODON HSE Site Inspection Report
B2: Date | E2: 46284 | L2: Inspected By: | U2: Mr. Noaman Shah
B4: Project ID. | E4: WAS1-05-006 | L4: Report No. | P4: 12 | W4: MODON PM Name | Y4: Eng. Mohammad Eisa
B6: Project Name: | E6: Improvement of WAS Fence and Gate Project | L6: Contractor: | R6: Hamza Mohammad Alderi Contracting Co. | X6: Safety Performance | AA6: =IF(W29>0,3,IF(L29>6,2,IF(D29>0,2,1)*1)*1) -> 2 | AE6: =(((COUNTIF(L13:Q25,"1")+COUNTIF(AC13:AH25,"1"))*AR13)+(COUNTIF(L13:Q25,"2")+COUNTIF(AC13:AH25,"2"))*AR14+(COUNTIF(L13:Q25,"3")+COUNTIF(AC13:AH25,"3"))*AR15)/((COUNT(L13:Q25)+COUNT(AC13:AH25))*100) -> 0.8452381
B8: Inspections are a snapshot in time and refer only to the practices and documentation observed at the time of the Inspection. It remains the responsibility of the Consultant and Contractor to ensure that all aspects of Health & Safety are suitably managed.
B9: 1 | D9: Good Practice | H9: 2 | I9: Need Improvement | T9: 3 | U9: Fail (Life Threatening Activity) / Compliance with Plan & Procedures | X9: N/A | Y9: Atcitty Not Applicable for this Site Inspection Report
B11: No. | C11: Topic | K11: Wt. | L11: HSE Compliance | S11: No. | T11: Topic | AB11: Wt. | AC11: HSE Compliance
B13: 1 | C13: Access and Egress - (General access to site, segregated from vehicles, / Overhead protection, while entering into the building /Adequate lighting provided when dark or overnight work) | K13: 0.05 | L13: 2 | S13: 14 | T13: Work at Height - (PPE/Fall Protection(Same level, above and blow) / Training / Fall restraint / competency /Safe access & egress to and from work at height / Ladders / Openings (floor/shafts/Provision of emergency rescue) | AB13: 0.05 | AC13: 2 | AP13: 1 | AR13: 100 | AU13: 1
B14: 2 | C14: Traffic Management - (Loading/unloading/sheeting/temp. routes/speed/parking/competence) | K14: 0.03 | L14: 2 | S14: 15 | T14: Scaffolding - (Temp. Scaffolding Work-platform (All types) - qualified scaffolder / Inspection / Tagged / Safe Access/egress / PTW/Falsework & Formwork) | AB14: 0.04 | AC14: N/A | AP14: 2 | AR14: 75 | AU14: 2
B15: 3 | C15: Site Signage - (Project Notice Board & General Signage) | K15: 0.02 | L15: 2 | S15: 16 | T15: Mobile Elevated Work platform (MEWP) - (PTW/competence requirements/conditions/inspections/tagged/training/Full-body harness) | AB15: 0.04 | AC15: N/A | AP15: 3 | AR15: 0 | AU15: 3
B16: 4 | C16: PPE Compliance - (Use, storage, stock, handling & checks - Head, Foot, Eye, Hearing) | K16: 0.05 | L16: 2 | S16: 17 | T16: Excavation & Trenches - (PTW/Edge protection/buffer zone/Slope/Benching/Shoring/Geo-tech report/Atmospheric hazards/Acess&egress/Emergency management / MS&RA/H.E) | AB16: 0.03 | AC16: N/A | AU16: N/A
B17: 5 | C17: Housekeeping - (Material correctly stored/Rubbish cleaned & removed daily/slips & trips hazards) | K17: 0.03 | L17: 1 | S17: 18 | T17: Confined Space - (PTW/Training/competence/Emergency Management/MS & RA/Safe access/egress) | AB17: 0.05 | AC17: N/A
B18: 6 | C18: Storage of Materials - (Transporting, storage, training and use - Combustible / Flammable / Hazardous substances (COSHH) | L18: 2 | S18: 19 | T18: Fire Protection - (Flammable/Oxy. LPG /Combustible separated/FE's/Flashback arrestor/Sparks & slags/Smoking area/PTW/Generators/MS & RA/Emergency Management) | AC18: 2 | AL18: Red | AM18: Serious injury or death (immediately)
B19: 7 | C19: Site Waste Management - (Hazardous waste /Combustible waste / Human waste / Construction waste - asphalt, cable, timber, paving roof sheeting tiles, plastic & bricks) | L19: 1 | S19: 20 | T19: Health & Welfare - (Adequate drinking water/shaded - eating & rest area/washing & sanitary facilities/Certified FA/FA Box & Stock/adequate toilets/Ambulance) | AC19: 2 | AL19: Yellow | AM19: Minor or near miss (3 days to comply)
B20: 8 | C20: Health Surveillance - (Expose to excessive noise/vibration/dust/silica/CO/cement/radiation/extreme weather condition) | K20: 0.03 | L20: 1 | S20: 21 | T20: Environmental Incident Measures - (Spill/ Leakage / Concrete wash / vehicle & eqpts. wash / waste disposal/Sewers and drains/emissions/Emergency Management/Training/site run-off water) | AB20: 0.05 | AC20: 1 | AL20: Green | AM20: No issues
B21: 9 | C21: Electrical Safety - (Electrical qualified /RCD/GFCI/Industrial Cocket/LOTO/Cable-overhung or buried/Cords in good condition/current inspection tag) | K21: 0.05 | L21: 2 | S21: 22 | T21: HSE Communications & Meetings - (Schedule HSE Meetings/Safety Committee meetings/Alerts / Lesson learned/Safety Bulletin contains latest HSE KPI) | AB21: 0.05 | AC21: 1
B22: 10 | C22: Tools & Equipment - (Includes, powered, hydraulic & pneumatic/Guards in place/Properly stored/RCD Protection/Earthed/Good condition & tagged) | K22: 0.03 | L22: 2 | S22: 23 | T22: HSE Plan & Associated Procedures - (Approved updated HSE Plan/ CEMP/HAZComm/Procedures/Standards/Project Safety Risk Register) | AB22: 0.03 | AC22: 1 | AL22: 26 points > 4 minors then is it’s a serious issue
B23: 11 | C23: Manual Handling - (Lifting/loading/pulling/pushing/twisting/awkward posture/repetitive task/frequent and prolong physical effort/Reasonable practicable use of mechanical aid) | K23: 0.03 | L23: 2 | S23: 24 | T23: Health, Safety & Environment Incident reporting - (Review of HSE Statistics, Reporting of Unsafe Act & Conditions/ Reporting of Near Miss incident/Reporting of FA cases/Record MT cases) | AB23: 0.03 | AC23: 1
B24: 12 | C24: Vehicle and mobile equipment / Plant - (dumpers; excavators, cranes, piling rigs, grader, roller, loaders/condition/KSA License/certification) | K24: 0.05 | L24: 1 | S24: 25 | T24: HSE Awareness, Training & Competence - (Policy /Objective & targets/Information, training/Climatic condition awareness/Reponses in emergency situation/ Safety Behavior Observation) | AB24: 0.04 | AC24: 2
B25: 13 | C25: Lifting Operations & Rigging - (Lifting Plan/Lifting devices & gears/PTW/Condition/3rd party certification/bank-man/rigger/slingers/man-basket/inspection record/tagged) | L25: N/A | S25: 26 | T25: Project Leadership Site Tours - (Provide evidence of proactive safety performance/Deficient discovered discussed/Positive feedback/Workers resolving safety issues) | AC25: 2
B27: Prepared by: | G27: Mr. Noaman Shah | S27: Sent to MODON PM: | X27: Eng. Mohammad Eisa
B28: Safety Results
B29: 1 | D29: =COUNTIF(L13:Q26,"1")+COUNTIF(AB13:AG26,"1") -> 8 | I29: 2 | L29: =COUNTIF(L13:Q26,"2")+COUNTIF(AB13:AG26,"2") -> 13 | U29: 3 | W29: =COUNTIF(L13:Q26,"3")+COUNTIF(AB13:AG26,"3") -> 0

Sheet HSE-Stat
A1: Safety Statistics
A3: Category | B3: Item | D3: This Week | E3: This Month | F3: Year to Date | G3: Cumulative
A4: Category | B4: Total Hours Worked | D4: 5562 | E4: 16470 | F4: 30524 | G4: 30524
B5: Safe Hours Worked | D5: =D4 -> 5562 | E5: =E4 -> 16470 | F5: =F4 -> 30524 | G5: =G4 -> 30524
A6: Reactive | B6: LTI | D6: 0 | E6: 0 | F6: 0 | G6: 0
B7: MTC (Healed w/o Disability) | D7: 0 | E7: 0 | F7: 0 | G7: 0
B8: MTC (Healed w/ Disability) | D8: 0 | E8: 0 | F8: 0 | G8: 0
B9: Near Miss | D9: 0 | E9: 0 | F9: 0 | G9: 0
B10: First Aid Cases | D10: 0 | E10: 0 | F10: 0 | G10: 0
B11: Fatality | D11: 0 | E11: 0 | F11: 0 | G11: 0
B12: Fire Incident Cases | D12: 0 | E12: 0 | F12: 0 | G12: 0
B13: Vehicle Incident | D13: 0 | E13: 0 | F13: 0 | G13: 0
B14: Property Damages | D14: 0 | E14: 0 | F14: 0 | G14: 0
A15: Proactive | B15: Induction Training - Sessions(Headcount) | D15: 3(6) | E15: 9(21) | F15: 23(137) | G15: 23(137)
B16: No.of Internal Training - Sessions(Headcount) | D16: 0 | E16: 0 | F16: 2(14) | G16: 2(14)
B17: No.of Internal Audit | D17: 0 | E17: 0 | F17: 3 | G17: 3
B18: No. of Toolbox Talks - Sessions(Headcount) | D18: 1(8) | E18: 3(27) | F18: 17(230) | G18: 17(230)
B19: Safety Awards/Incentives | D19: 0 | E19: 0 | F19: 0
I20: Category | J20: Item | L20: This Week | M20: This Month | N20: Year to Date | O20: Cumulative
A22: Consultant Safety Inspection | I22: Overall Average | J22: =AVERAGE(E24:E194) -> 0.85583333
A23: Week Number | B23: Date of Audit | C23: Date Issued | D23: Numbers Of Comments | E23: Overall Score | F23: Date Closed | G23: Closure Duration | I23: This Week Score | J23: 0.85
A24: Week-1 | B24: 46207 | C24: 46208 | D24: 2 | E24: 0.88 | F24: 46210 | G24: 2
A25: Week-2 | B25: 46214 | C25: 46215 | D25: 3 | E25: 0.85 | F25: 46217 | G25: 2
A26: Week-3 | B26: 46221 | C26: 46222 | D26: 1 | E26: 0.86 | F26: 46224 | G26: 1
A27: Week-4 | B27: 46228 | C27: 46229 | D27: 1 | E27: 0.85 | F27: 46229 | G27: 1
A28: Week-5 | B28: 46235 | C28: 46235 | D28: 1 | E28: 0.86 | F28: 46236 | G28: 1
A29: Week-6 | B29: 46242 | C29: 46243 | D29: 1 | E29: 0.85 | F29: 46243 | G29: 1
A30: Week-7 | B30: 46249 | C30: 46249 | D30: 1 | E30: 0.86 | F30: 46249 | G30: 1
A31: Week-8 | B31: 46256 | C31: 46256 | D31: 1 | E31: 0.85 | F31: 46256 | G31: 1
A32: Week-9 | B32: 46263 | C32: 46263 | D32: 1 | E32: 0.85 | F32: 46263 | G32: 1
A33: Week-10 | B33: 46270 | C33: 46270 | D33: 1 | E33: 0.86 | F33: 46270 | G33: 1
A34: Week-11 | B34: 46277 | C34: 46277 | D34: 1 | E34: 0.85 | F34: 46278 | G34: 1
A35: Week-12 | B35: 46284 | C35: 46284 | D35: 1 | E35: 0.85 | F35: 46285 | G35: 1
A36: Week-13
A37: Week-14
A38: Week-15
A39: Week-16
A40: Week-17

Sheet Risk Register 
B2: Department: | G2: RISK MANAGEMENT | M2: Status Date:31-Dec-2024
B3: Program | G3: RISK REGISTER
B4: Project: | G4: Improvement of Waad Al Shamal Industrial City Fence & Gates
B5: Project No.: | G5: WAS1-05-006
B6: Project Location: | G6: WAAD ALSHAMAL Industrial City
T8: Before Treatment | AE8: Post Treatment
B9: Risk Data | J9: Category | M9: Risk Description | P9: Risk Control Dates | R9: Risk Manageability | S9: Risk Proximity | T9: Most Likely | W9: Risk Owner | X9: Risk Response & Treatment Action | AB9: Treatment Control Dates | AE9: Most Likely | AH9: Treatment Status
B10: Risk ID | C10: Project Name | D10: MODON PM | E10: Region | F10: Section / Group | G10: City | H10: Project ID | I10: Risk Status | J10: T/O/I | K10: Internal/External | L10: Category | M10: Cause / Source | N10: Risk | O10: Consequence / Effect | P10: Identified | Q10: Closed | T10: Liklihood | U10: Impact | V10: Risk Score | X10: Risk Response Strategy | Y10: Treatment Action | Z10: Treatment Acton Description | AA10: Treatment Action Owner | AB10: Start | AC10: Due | AD10: Closed | AE10: Liklihood | AF10: Impact | AG10: Risk Score
B11: WAS-WAS1-05-RI-001 | C11: Improvement of Waad Al Shamal Industrial City Fence & Gates | D11: Muhammed H. Al-Essa | E11: WAS | F11: Exec-WAS | G11: wad alshammal | H11: WAS1-05-006 | I11: Open | J11: Threat | K11: Internal | L11: construction | M11: contractor delay materials approval and delivery | N11: contractor delay materials approval and delivery | O11: delay the project completion date | P11: 46179 | R11: Moderate | S11: Overdue | T11: Medium | U11: Medium | V11: l3 | W11: contractor | X11: Accept | Y11: Mitigate | Z11: the contractor expedite the materials approval & delivery | AA11: Project manager | AB11: 46179 | AC11: 46295 | AD11: open | AE11: Very High | AF11: Very High | AG11: L3 | AH11: Active
B27: Risk Status: 1.Open, 2.Closed, or 3.Realized
B28: T/O/I: 1.Threat, 2.Opportunity, or 3.Issue
B30: Category (select 1):
B31: 1. Political
B32: 2. Legal, Regulatory, Compliance
B33: 3. Funding, Finance, Budget
B34: 4. Management, Governance, Policies, KPI, Performance
B35: 5. Human Resources
B36: 6. Stakeholders, Authorities, Approvals, Permits
B37: 7. Requirements, Specifications, Scope, Procurement, Contract
B38: 8. Process, Tools, Technique, Technology
B39: 9. Design, Engineering
... B54: Risk Level/Score: Likelihood x Highest Impact (Safety, Cost, Schedule, Environment, Quality, or Reputation. See Risk Scoring Matrix tab)

Sheet Major Quantities
A1: BOQ Number | B1: Description of Item | C1: Total Quantity | D1: Unit of Measurement | E1: Plan To Date | F1: Actual To Date | G1: Remaining Total | H1: Variance | I1: Variance % | J1: Notices | L1: Actual To Date %
L2: =F2/C2 -> #DIV/0!
L3: =F3/C3 -> #DIV/0!
L4: =F4/C4 -> #DIV/0!
L5: =F5/C5 -> #DIV/0!
L6: =F6/C6 -> #DIV/0!
L7: =F7/C7 -> #DIV/0!
L8: =F8/C8 -> #DIV/0!
L9: =F9/C9 -> #DIV/0!
L10: =F10/C10 -> #DIV/0!
L11: =F11/C11 -> #DIV/0!
L12: =F12/C12 -> #DIV/0!
L13: =F13/C13 -> #DIV/0!
... L24: =F24/C24 -> #DIV/0!
A31: Activity ID | B31: Activity Name | C31: Resource Name | D31: Price / Unit | E31: Budgeted Units | F31: Actual Units | G31: Budgeted Cost | H31: Budgeted Cost | I31: Actual | J31: 45319 | K31: 45320 | L31: 45321 | M31: 45322 | N31: 45323 | O31: 45324 | P31: 45325 | Q31: 45326 | R31: 45327 | S31: 45328 | T31: 45329 | U31: 45330 | V31: 45331 | W31: 45332 | X31: 45333 | Y31: 45334 | Z31: 45335 | AA31: 45336 | AB31: 45337 | AC31: 45338 | AD31: 45339 | AE31: 45340 | AF31: 45341 | AG31: 45342 | AH31: 45343 | AI31: 45344 | AJ31: 45345 | AK31: 45346 | AL31: 45347 | AM31: 45348 | AN31: 45349 | AO31: 45350 | AP31: 45351 | AQ31: 45352 | AR31: 45353 | AS31: 45354 | AT31: 45355 | AU31: 45356 | AV31: 45357 | AW31: 45358 | AX31: 45359 | AY31: 45360 | AZ31: 45361 | BA31: 45362 | BB31: 45363 | BC31: 45364 | BD31: 45365 | BE31: 45366 | BF31: 45367 | BG31: 45368 | BH31: 45369 | BI31: 45370 | BJ31: 45371 | BK31: 45372 | BL31: 45373 | BM31: 45374 | BN31: 45375 | BO31: 45376 | BP31: 45377 | BQ31: 45378 | BR31: 45379 | BS31: 45380 | BT31: 45381 | BU31: 45382 | BV31: 45383 | BW31: 45384 | BX31: 45385 | BY31: 45386 | BZ31: 45387 | CA31: 45388 | CB31: 45389 | CC31: 45390 | CD31: 45391 | CE31: 45392 | CF31: 45393 | CG31: 45394 | CH31: 45395 | CI31: 45396 | CJ31: 45397 | CK31: 45398 | CL31: 45399 | CM31: 45400 | CN31: 45401 | CO31: 45402 | CP31: 45403 | CQ31: 45404 | CR31: 45405 | CS31: 45406 | CT31: 45407 | CU31: 45408 | CV31: 45409 | CW31: 45410 | CX31: 45411 | CY31: 45412 | CZ31: 45413 | DA31: 45414 | DB31: 45415 | DC31: 45416 | DD31: 45417 | DE31: 45418 | DF31: 45419 | DG31: 45420 | DH31: 45421 | DI31: 45422 | DJ31: 45423 | DK31: 45424 | DL31: 45425 | DM31: 45426 | DN31: 45427 | DO31: 45428 | DP31: 45429 | DQ31: 45430 | DR31: 45431 | DS31: 45432 | DT31: 45433 | DU31: 45434 | DV31: 45435 | DW31: 45436 | DX31: 45437 | DY31: 45438 | DZ31: 45439 | EA31: 45440 | EB31: 45441 | EC31: 45442 | ED31: 45443 | EE31: 45444 | EF31: 45445 | EG31: 45446 | EH31: 45447 | EI31: 45448 | EJ31: 45449 | EK31: 45450 | EL31: 45451 | EM31: 45452 | EN31: 45453 | EO31: 45454 | EP31: 45455 | EQ31: 45456 | ER31: 45457 | ES31: 45458 | ET31: 45459 | EU31: 45460 | EV31: 45461 | EW31: 45462 | EX31: 45463 | EY31: 45464 | EZ31: 45465 | FA31: 45466 | FB31: 45467 | FC31: 45468 | FD31: 45469 | FE31: 45470 | FF31: 45471 | FG31: 45472 | FH31: 45473 | FI31: 45474 | FJ31: 45475 | FK31: 45476 | FL31: 45477 | FM31: 45478 | FN31: 45479 | FO31: 45480 | FP31: 45481 | FQ31: 45482 | FR31: 45483 | FS31: 45484 | FT31: 45485 | FU31: 45486 | FV31: 45487 | FW31: 45488 | FX31: 45489 | FY31: 45490 | FZ31: 45491 | GA31: 45492 | GB31: 45493 | GC31: 45494 | GD31: 45495 | GE31: 45496 | GF31: 45497 | GG31: 45498 | GH31: 45499 | GI31: 45500 | GJ31: 45501 | GK31: 45502 | GL31: 45503 | GM31: 45504 | GN31: 45505 | GO31: 45506 | GP31: 45507 | GQ31: 45508 | GR31: 45509 | GS31: 45510 | GT31: 45511 | GU31: 45512 | GV31: 45513 | GW31: 45514 | GX31: 45515 | GY31: 45516 | GZ31: 45517 | HA31: 45518 | HB31: 45519 | HC31: 45520 | HD31: 45521 | HE31: 45522 | HF31: 45523 | HG31: 45524 | HH31: 45525 | HI31: 45526 | HJ31: 45527 | HK31: 45528 | HL31: 45529 | HM31: 45530 | HN31: 45531 | HO31: 45532 | HP31: 45533 | HQ31: 45534 | HR31: 45535 | HS31: 45536 | HT31: 45537 | HU31: 45538 | HV31: 45539 | HW31: 45540 | HX31: 45541 | HY31: 45542 | HZ31: 45543 | IA31: 45544 | IB31: 45545 | IC31: 45546 | ID31: 45547 | IE31: 45548 | IF31: 45549 | IG31: 45550 | IH31: 45551 | II31: 45552 | IJ31: 45553 | IK31: 45554 | IL31: 45555 | IM31: 45556 | IN31: 45557 | IO31: 45558 | IP31: 45559 | IQ31: 45560 | IR31: 45561 | IS31: 45562 | IT31: 45563 | IU31: 45564 | IV31: 45565 | IW31: 45566 | IX31: 45567 | IY31: 45568 | IZ31: 45569 | JA31: 45570 | JB31: 45571 | JC31: 45572 | JD31: 45573 | JE31: 45574 | JF31: 45575 | JG31: 45576 | JH31: 45577 | JI31: 45578 | JJ31: 45579 | JK31: 45580 | JL31: 45581 | JM31: 45582 | JN31: 45583 | JO31: 45584 | JP31: 45585 | JQ31: 45586 | JR31: 45587 | JS31: 45588 | JT31: 45589 | JU31: 45590 | JV31: 45591 | JW31: 45592 | JX31: 45593 | JY31: 45594 | JZ31: 45595 | KA31: 45596 | KB31: 45597 | KC31: 45598 | KD31: 45599 | KE31: 45600 | KF31: 45601 | KG31: 45602 | KH31: 45603 | KI31: 45604 | KJ31: 45605 | KK31: 45606 | KL31: 45607 | KM31: 45608 | KN31: 45609 | KO31: 45610 | KP31: 45611 | KQ31: 45612 | KR31: 45613 | KS31: 45614 | KT31: 45615 | KU31: 45616 | KV31: 45617 | KW31: 45618 | KX31: 45619 | KY31: 45620 | KZ31: 45621 | LA31: 45622 | LB31: 45623 | LC31: 45624 | LD31: 45625 | LE31: 45626 | LF31: 45627 | LG31: 45628 | LH31: 45629 | LI31: 45630 | LJ31: 45631 | LK31: 45632 | LL31: 45633 | LM31: 45634 | LN31: 45635 | LO31: 45636 | LP31: 45637 | LQ31: 45638 | LR31: 45639 | LS31: 45640 | LT31: 45641 | LU31: 45642 | LV31: 45643 | LW31: 45644 | LX31: 45645 | LY31: 45646 | LZ31: 45647 | MA31: 45648 | MB31: 45649 | MC31: 45650 | MD31: 45651 | ME31: 45652 | MF31: 45653 | MG31: 45654 | MH31: 45655 | MI31: 45656 | MJ31: 45657 | MK31: 45658 | ML31: 45659 | MM31: 45660 | MN31: 45661 | MO31: 45662 | MP31: 45663 | MQ31: 45664 | MR31: 45665 | MS31: 45666 | MT31: 45667 | MU31: 45668 | MV31: 45669 | MW31: 45670 | MX31: 45671 | MY31: 45672 | MZ31: 45673 | NA31: 45674 | NB31: 45675 | NC31: 45676 | ND31: 45677 | NE31: 45678 | NF31: 45679 | NG31: 45680 | NH31: 45681 | NI31: 45682 | NJ31: 45683 | NK31: 45684 | NL31: 45685 | NM31: 45686 | NN31: 45687 | NO31: 45688 | NP31: 45689 | NQ31: 45690 | NR31: 45691 | NS31: 45692 | NT31: 45693 | NU31: 45694 | NV31: 45695 | NW31: 45696 | NX31: 45697 | NY31: 45698 | NZ31: 45699 | OA31: 45700 | OB31: 45701 | OC31: 45702 | OD31: 45703 | OE31: 45704 | OF31: 45705 | OG31: 45706 | OH31: 45707 | OI31: 45708 | OJ31: 45709 | OK31: 45710 | OL31: 45711 | OM31: 45712 | ON31: 45713 | OO31: 45714 | OP31: 45715 | OQ31: 45716 | OR31: 45717 | OS31: 45718 | OT31: 45719 | OU31: 45720 | OV31: 45721 | OW31: 45722 | OX31: 45723 | OY31: 45724 | OZ31: 45725 | PA31: 45726 | PB31: 45727 | PC31: 45728 | PD31: 45729 | PE31: 45730 | PF31: 45731 | PG31: 45732 | PH31: 45733 | PI31: 45734 | PJ31: 45735 | PK31: 45736 | PL31: 45737 | PM31: 45738 | PN31: 45739 | PO31: 45740 | PP31: 45741 | PQ31: 45742 | PR31: 45743 | PS31: 45744 | PT31: 45745 | PU31: 45746 | PV31: 45747 | PW31: 45748 | PX31: 45749 | PY31: 45750 | PZ31: 45751 | QA31: 45752 | QB31: 45753 | QC31: 45754 | QD31: 45755 | QE31: 45756 | QF31: 45757 | QG31: 45758 | QH31: 45759 | QI31: 45760 | QJ31: 45761 | QK31: 45762 | QL31: 45763 | QM31: 45764 | QN31: 45765 | QO31: 45766 | QP31: 45767 | QQ31: 45768 | QR31: 45769 | QS31: 45770 | QT31: 45771 | QU31: 45772 | QV31: 45773 | QW31: 45774 | QX31: 45775 | QY31: 45776 | QZ31: 45777 | RA31: 45778 | RB31: 45779 | RC31: 45780 | RD31: 45781 | RE31: 45782 | RF31: 45783 | RG31: 45784 | RH31: 45785 | RI31: 45786 | RJ31: 45787 | RK31: 45788 | RL31: 45789 | RM31: 45790 | RN31: 45791 | RO31: 45792 | RP31: 45793 | RQ31: 45794 | RR31: 45795 | RS31: 45796 | RT31: 45797 | RU31: 45798 | RV31: 45799 | RW31: 45800 | RX31: 45801 | RY31: 45802 | RZ31: 45803 | SA31: 45804 | SB31: 45805 | SC31: 45806 | SD31: 45807 | SE31: 45808 | SF31: 45809 | SG31: 45810 | SH31: 45811 | SI31: 45812 | SJ31: 45813 | SK31: 45814 | SL31: 45815 | SM31: 45816 | SN31: 45817 | SO31: 45818 | SP31: 45819 | SQ31: 45820 | SR31: 45821 | SS31: 45822 | ST31: 45823 | SU31: 45824 | SV31: 45825 | SW31: 45826 | SX31: 45827 | SY31: 45828 | SZ31: 45829 | TA31: 45830 | TB31: 45831 | TC31: 45832 | TD31: 45833 | TE31: 45834 | TF31: 45835 | TG31: 45836 | TH31: 45837 | TI31: 45838 | TJ31: 45839 | TK31: 45840 | TL31: 45841 | TM31: 45842 | TN31: 45843 | TO31: 45844 | TP31: 45845 | TQ31: 45846 | TR31: 45847 | TS31: 45848 | TT31: 45849 | TU31: 45850 | TV31: 45851 | TW31: 45852 | TX31: 45853 | TY31: 45854 | TZ31: 45855 | UA31: 45856 | UB31: 45857 | UC31: 45858 | UD31: 45859 | UE31: 45860 | UF31: 45861 | UG31: 45862 | UH31: 45863 | UI31: 45864 | UJ31: 45865 | UK31: 45866 | UL31: 45867 | UM31: 45868 | UN31: 45869 | UO31: 45870 | UP31: 45871 | UQ31: 45872 | UR31: 45873 | US31: 45874 | UT31: 45875 | UU31: 45876 | UV31: 45877 | UW31: 45878 | UX31: 45879 | UY31: 45880 | UZ31: 45881 | VA31: 45882 | VB31: 45883 | VC31: 45884 | VD31: 45885 | VE31: 45886 | VF31: 45887 | VG31: 45888 | VH31: 45889 | VI31: 45890 | VJ31: 45891 | VK31: 45892 | VL31: 45893 | VM31: 45894 | VN31: 45895 | VO31: 45896 | VP31: 45897 | VQ31: 45898 | VR31: 45899 | VS31: 45900 | VT31: 45901 | VU31: 45902 | VV31: 45903 | VW31: 45904 | VX31: 45905 | VY31: 45906 | VZ31: 45907 | WA31: 45908 | WB31: 45909 | WC31: 45910 | WD31: 45911 | WE31: 45912 | WF31: 45913 | WG31: 45914 | WH31: 45915 | WI31: 45916 | WJ31: 45917 | WK31: 45918 | WL31: 45919 | WM31: 45920 | WN31: 45921 | WO31: 45922 | WP31: 45923 | WQ31: 45924 | WR31: 45925 | WS31: 45926 | WT31: 45927 | WU31: 45928 | WV31: 45929 | WW31: 45930 | WX31: 45931 | WY31: 45932 | WZ31: 45933 | XA31: 45934 | XB31: 45935 | XC31: 45936 | XD31: 45937 | XE31: 45938 | XF31: 45939 | XG31: 45940 | XH31: 45941 | XI31: 45942 | XJ31: 45943 | XK31: 45944 | XL31: 45945 | XM31: 45946 | XN31: 45947 | XO31: 45948 | XP31: 45949 | XQ31: 45950 | XR31: 45951 | XS31: 45952 | XT31: 45953 | XU31: 45954 | XV31: 45955 | XW31: 45956 | XX31: 45957 | XY31: 45958 | XZ31: 45959 | YA31: 45960 | YB31: 45961 | YC31: 45962 | YD31: 45963 | YE31: 45964 | YF31: 45965 | YG31: 45966 | YH31: 45967 | YI31: 45968 | YJ31: 45969 | YK31: 45970 | YL31: 45971 | YM31: 45972 | YN31: 45973 | YO31: 45974 | YP31: 45975 | YQ31: 45976 | YR31: 45977 | YS31: 45978 | YT31: 45979 | YU31: 45980 | YV31: 45981 | YW31: 45982 | YX31: 45983 | YY31: 45984 | YZ31: 45985 | ZA31: 45986 | ZB31: 45987 | ZC31: 45988 | ZD31: 45989 | ZE31: 45990 | ZF31: 45991 | ZG31: 45992 | ZH31: 45993 | ZI31: 45994 | ZJ31: 45995 | ZK31: 45996 | ZL31: 45997 | ZM31: 45998 | ZN31: 45999 | ZO31: 46000 | ZP31: 46001 | ZQ31: 46002 | ZR31: 46003 | ZS31: 46004 | ZT31: 46005 | ZU31: 46006 | ZV31: 46007 | ZW31: 46008 | ZX31: 46009
A32: Total | E32: 102031 | F32: 23531.31 | G32: 45093675 | H32: 45093675 | I32: =F32 -> 23531.31 | J32: 21.55 | K32: 21.55 | L32: 21.55 | M32: 21.55 | N32: 21.55 | P32: 21.83 | Q32: 21.83 | R32: 21.83 | S32: 0.27 | T32: 0.27 | U32: 1.46 | W32: 1.46 | X32: 1.46 | Y32: 70.33 | Z32: 70.33 | AA32: 70.33 | AB32: 112.19 | AD32: 112.19 | AE32: 112.19 | AF32: 59.21 | AG32: 59.21 | AH32: 59.21 | AK32: 35.32 | AL32: 35.32 | AM32: 16.44 | AN32: 16.85 | AO32: 16.85 | AP32: 0.87 | AR32: 0.27 | AS32: 0.27 | AT32: 0 | AU32: 0 | AV32: 0 | AW32: 189.2 | AY32: 189.2 | AZ32: 189.2 | BA32: 141.9 | BB32: 141.9 | BC32: 141.9 | BD32: 141.9 | BF32: 141.9 | BG32: 141.9 | BH32: 141.9 | BI32: 141.9 | BJ32: 141.9 | BK32: 141.9 | BM32: 141.9 | BN32: 141.9 | BO32: 141.9 | BP32: 141.9 | BQ32: 141.9 | BR32: 141.9 | BT32: 141.9 | BU32: 141.9 | BV32: 141.9 | BW32: 141.9 | BX32: 127.2 | BY32: 126.6 | CA32: 126.6 | CB32: 126.6 | CC32: 126.6 | CD32: 126.6 | CJ32: 168.8 | CK32: 168.8 | CL32: 168.8 | CM32: 168.8 | CO32: 168.8 | CP32: 168.8 | CQ32: 168.8 | CR32: 168.8 | CS32: 168.8 | CT32: 168.8 | CV32: 168.8 | CW32: 168.8 | CX32: 168.8 | CY32: 176.59 | CZ32: 184.37 | DA32: 184.37 | DC32: 184.37 | DD32: 184.37 | DE32: 184.37 | DF32: 184.37 | DG32: 184.48 | DH32: 184.59 | DJ32: 184.59 | DK32: 184.59 | DL32: 184.59 | DM32: 188.22 | DN32: 191.86 | DO32: 191.87 | DQ32: 192.51 | DR32: 193.15 | DS32: 189.52 | DT32: 173.9 | DU32: 161.91 | DV32: 162.5 | DX32: 164.88 | DY32: 167.11 | DZ32: 167.57 | EA32: 167.58 | EB32: 166.99 | EC32: 168.41 | EE32: 169.07 | EF32: 168.89 | EG32: 170.07 | EH32: 170.1 | EI32: 168.12 | EJ32: 166.1 | EL32: 173.18 | EM32: 181.19 | EN32: 182.12 | EO32: 182.19 | EP32: 182.26 | EQ32: 715.97 | ES32: 1253.81 | ET32: 1257.95 | EZ32: 1259.46 | FA32: 1260.97 | FB32: 1261.4 | FC32: 1257.71 | FD32: 1256.27 | FE32: 1258.96 | FG32: 1258.8 | FH32: 1259.08 | FI32: 1257.81 | FJ32: 1253.41 | FK32: 1250.72 | FL32: 1250.72 | FN32: 1256.66 | FO32: 1261.05 | FP32: 1261.24 | FQ32: 1262.99 | FR32: 1262.99 | FS32: 1396.73 | FU32: 1526.57 | FV32: 1521.77 | FW32: 1520.73 | FX32: 1520.58 | FY32: 1520.58 | FZ32: 1518.2 | GB32: 1516.6 | GC32: 1522.61 | GD32: 1531.64 | GE32: 1535.45 | GF32: 785.51 | GG32: 35.59 | GI32: 28.78 | GJ32: 21.94 | GK32: 21.94 | GL32: 23.84 | GM32: 25.12 | GN32: 24.42 | GP32: 24.2 | GQ32: 36.24 | GR32: 48.4 | GS32: 52.11 | GT32: 55.84 | GU32: 55.69 | GW32: 42.55 | GX32: 28.38 | GY32: 33.58 | GZ32: 40.48 | HA32: 41.01 | HB32: 41.81 | HD32: 72.51 | HE32: 274.38 | HF32: 459.01 | HG32: 471.56 | HH32: 471.46 | HI32: 467.45 | HK32: 464.26 | HL32: 452.44 | HM32: 444.04 | HN32: 448.3 | HO32: 448.19 | HP32: 445.73 | HR32: 444.97 | HS32: 442.3 | HT32: 438.04 | HU32: 260.54 | HV32: 83.03 | HW32: 78.29 | HY32: 43.88 | HZ32: 13.3 | IA32: 197.77 | IB32: 383.29 | IC32: 383.45 | ID32: 381.68 | IF32: 380 | IG32: 194.34 | IH32: 8.59 | II32: 8.59 | IJ32: 8.77 | IK32: 8.69 | IM32: 8.43 | IN32: 8.44 | IP32: 8.28 | IQ32: 8.96 | IR32: 9.8 | IT32: 9.74 | IU32: 11.69 | IV32: 13.68 | IW32: 14.81 | IX32: 15.72 | IY32: 15.51 | JA32: 14.14 | JB32: 15.53 | JC32: 19.42 | JD32: 22.57 | JE32: 24.53 | JF32: 27.69 | JH32: 35.94 | JI32: 41.52 | JJ32: 42.66 | JK32: 42.76 | JL32: 53.47 | JM32: 69.64 | JO32: 62.96 | JP32: 58.15 | JQ32: 72.8 | JR32: 112.27 | JS32: 142.58 | JT32: 129.26 | JV32: 127.31 | JW32: 144.73 | JX32: 105.34 | JY32: 57.11 | JZ32: 64.4 | KA32: 64.56 | KC32: 46.25 | KD32: 41.41 | KE32: 50.63 | KF32: 54.8 | KG32: 49.72 | KH32: 44.52 | KJ32: 47.52 | KK32: 50.57 | KL32: 39.97 | KM32: 29.71 | KN32: 37.26 | KO32: 44.53 | KQ32: 39.58 | KR32: 33.69 | KS32: 51.95 | KT32: 91.66 | KU32: 108.72 | KV32: 106.4 | KX32: 107.85 | KY32: 99.66 | KZ32: 92.65 | LA32: 83.03 | LB32: 72.46 | LC32: 60.56 | LE32: 48.38 | LF32: 45.24 | LG32: 44.94 | LH32: 57.38 | LI32: 66.43 | LJ32: 97.63 | LL32: 122.69 | LM32: 88.44 | LN32: 64.32 | LO32: 139.59 | LP32: 214.39 | LQ32: 219.2 | LS32: 217.1 | LT32: 215.73 | LU32: 224.41 | LV32: 153.08 | LW32: 75.72 | LX32: 77.28 | LZ32: 77.93 | MA32: 79.36 | MB32: 76.9 | MC32: 73.16 | MD32: 71.12 | ME32: 78.67 | MG32: 87.82 | MH32: 87.1 | MI32: 77.2 | MJ32: 62.8 | MK32: 63.13 | ML32: 66.81 | MN32: 64.95 | MO32: 63.67 | MP32: 51.03 | MQ32: 37.85 | MR32: 33.5 | MS32: 29.9 | MU32: 29.85 | MV32: 28.91 | MW32: 27.97 | MX32: 23.83 | MY32: 38.57 | MZ32: 58.66 | NB32: 38.82 | NC32: 17.75 | ND32: 17.73 | NE32: 16.56 | NF32: 15.49 | NG32: 15.6 | NI32: 15.6 | NJ32: 15.6 | NK32: 15.59 | NL32: 15.58 | NM32: 15.59 | NN32: 14.44 | NP32: 18.24 | NQ32: 23.21 | NR32: 23.26 | NS32: 23.31 | NT32: 23.31 | NU32: 23.31 | NW32: 32.13 | NX32: 40.95 | NY32: 40.95 | NZ32: 44.56 | OA32: 44.66 | OB32: 41.15 | OD32: 41.15 | OE32: 37.19 | OF32: 33.23 | OG32: 40.64 | OH32: 48.13 | OI32: 48.21 | OL32: 49.78 | OM32: 51.42 | ON32: 51.48 | OO32: 55.47 | OP32: 49.97 | OR32: 30.38 | OS32: 30.4 | OT32: 42.94 | OU32: 42.94 | OV32: 42.62 | OW32: 41.99 | OY32: 39.52 | OZ32: 39.62 | PA32: 38.85 | PB32: 37.2 | PC32: 41.88 | PD32: 39.29 | PF32: 38 | PG32: 38 | PH32: 36.57 | PI32: 34.12 | PJ32: 32.89 | PK32: 32.89 | PM32: 38.78 | PN32: 34.91 | PO32: 33.02 | PP32: 33.11 | PQ32: 33.11 | PR32: 33.11 | PT32: 33.11 | PY32: 44.87 | QA32: 41.58 | QB32: 25.17 | QC32: 25.17 | QD32: 24.87 | QE32: 23.97 | QF32: 21.96 | QH32: 26.95 | QI32: 59.98 | QJ32: 59.98 | QK32: 57.9 | QL32: 51.64 | QM32: 51.68 | QO32: 67.07 | QP32: 112.2 | QQ32: 110.21 | QR32: 105.83 | QS32: 105.85 | QT32: 93.69 | QV32: 57.03 | QW32: 57.06 | QX32: 60.03 | QY32: 73 | QZ32: 85.47 | RA32: 84.59 | RC32: 84.59 | RD32: 83.47 | RE32: 74.96 | RF32: 65.16 | RG32: 87.05 | RH32: 96.26 | RJ32: 81.82 | RK32: 88.54 | RL32: 92.61 | RM32: 92.47 | RN32: 92.47 | RO32: 88.12 | RQ32: 93.15 | RR32: 80.89 | RS32: 77.48 | RT32: 77.44 | RU32: 71.49 | RV32: 77.95 | RX32: 109.23 | RY32: 94.06 | RZ32: 48.46 | SA32: 57.19 | SB32: 82.65 | SC32: 70.88 | SE32: 33.17 | SF32: 23.85 | SG32: 26.07 | SH32: 23.38 | SI32: 15.24 | SJ32: 15.09 | SP32: 15.39 | SQ32: 15.14 | SS32: 14.41 | ST32: 15.11 | SU32: 18.47 | SV32: 23.22 | SW32: 23.21 | SX32: 23.18 | SZ32: 31.08 | TA32: 54.77 | TB32: 54.77 | TC32: 54.77 | TD32: 58.18 | TE32: 75.04 | TG32: 95.06 | TH32: 128.25 | TI32: 226.95 | TJ32: 228.05 | TK32: 188.29 | TL32: 69 | TN32: 67.01 | TO32: 57.64 | TP32: 47.52 | TQ32: 46.01 | TR32: 42.06 | TS32: 43.71 | TU32: 43.57 | TV32: 43.5 | TW32: 43.11 | TX32: 43.31 | TY32: 43.29 | TZ32: 41.84 | UB32: 32.36 | UC32: 16.67 | UD32: 15.57 | UE32: 18.25 | UF32: 27.31 | UG32: 29.33 | UI32: 29.03 | UJ32: 31.79 | UK32: 29.01 | UL32: 73.54 | UM32: 71.55 | UN32: 35.98 | UP32: 36.5 | UQ32: 38.47 | UR32: 41.74 | US32: 49.19 | UT32: 69.2 | UU32: 126.69 | UW32: 100.17 | UX32: 39.12 | UY32: 41.31 | UZ32: 52.36 | VA32: 55.87 | VB32: 32.83 | VD32: 32.65 | VE32: 32.1 | VF32: 32.1 | VG32: 33.15 | VH32: 36.26 | VI32: 36.38 | VK32: 36.5 | VL32: 33.19 | VM32: 23.46 | VN32: 24.23 | VO32: 23.62 | VP32: 20.59 | VR32: 20.57 | VS32: 31.85 | VT32: 67.01 | VU32: 82.05 | VV32: 118.49 | VW32: 121.05 | VY32: 117.22 | VZ32: 148.48 | WA32: 243.82 | WB32: 243.97 | WC32: 242.68 | WD32: 242.22 | WF32: 230.75 | WG32: 238.39 | WH32: 352.51 | WI32: 355.95 | WJ32: 362.35 | WK32: 359.99 | WM32: 359.75 | WN32: 365.12 | WO32: 378.86 | WQ32: 321.98 | WR32: 172.61 | WT32: 172.81 | WU32: 173.28 | WV32: 176.82 | WW32: 182.75 | WX32: 182.4 | WY32: 190.28 | XA32: 207.41 | XB32: 208.55 | XC32: 188.07 | XD32: 150.81 | XE32: 207.66 | XF32: 171.87 | XH32: 72.23 | XI32: 98.64 | XJ32: 176.75 | XK32: 173.92 | XL32: 164.68 | XM32: 135.94 | XO32: 135.06 | XP32: 135.74 | XQ32: 134.42 | XR32: 170 | XS32: 300.86 | XT32: 333.41 | XV32: 335.99 | XW32: 379.73 | XX32: 335.5 | XY32: 202 | XZ32: 200.23 | YA32: 241.61 | YC32: 366.26 | YD32: 364.93 | YE32: 373.75 | YF32: 440.86 | YG32: 526.67 | YH32: 526.62 | YJ32: 527.57 | YK32: 500.4 | YL32: 404.75 | YM32: 388.18 | YN32: 388.38 | YO32: 351.31 | YQ32: 231.37 | YR32: 217.45 | YS32: 244.64 | YT32: 247.28 | YU32: 254.64 | YV32: 235.11 | YX32: 181.35 | YY32: 181.02 | YZ32: 166.1 | ZA32: 123.29 | ZB32: 123.29 | ZC32: 121.71 | ZE32: 108.76 | ZF32: 84.11 | ZG32: 83.53 | ZH32: 82.26 | ZI32: 82.26 | ZJ32: 82.26 | ZL32: 82.26 | ZM32: 96.75 | ZN32: 140.23 | ZO32: 140.23 | ZP32: 140.23 | ZQ32: 140.23 | ZS32: 140.23 | ZT32: 140.23 | ZU32: 140.23 | ZV32: 140.23 | ZW32: 140.23 | ZX32: 105.17
A33: 2 Way PVC | E33: 90 | F33: 0 | G33: 42300 | H33: 42300 | I33: =F33 -> 0 | VV33: 1.23 | VW33: 3.68 | VZ33: 0.73 | WA33: 2.94 | WB33: 2.94 | WC33: 2.94 | WD33: 2.94 | WF33: 2.51 | WG33: 1.23 | WH33: 1.23 | WI33: 1.23 | WJ33: 0.92 | XF33: 0.21 | XH33: 0.85 | XI33: 0.85 | XJ33: 0.85 | XK33: 0.85 | XL33: 2.5 | XM33: 7.45 | XO33: 7.59 | XP33: 8.02 | XQ33: 6.87 | XR33: 3.41 | XS33: 4.07 | XT33: 5.34 | XV33: 3.21 | XW33: 3.21 | XX33: 3.21 | XY33: 2.64 | XZ33: 0.92 | YA33: 0.92 | YC33: 0.92 | YD33: 0.92 | YE33: 0.69
A34: 3-outlet Fire Hydrant (2 x 2.5 inch and 1 x 4 inch) | E34: 60 | F34: 1.8 | G34: 1043400 | H34: 1043400 | I34: =F34 -> 1.8 | AN34: 0.6 | AO34: 0.6 | AP34: 0.6 | OM34: 0.07 | ON34: 0.13 | OO34: 0.13 | OP34: 0.13 | OR34: 0.1 | OS34: 0.1 | OT34: 0.1 | OU34: 0.1 | OV34: 0.1 | OW34: 0.1 | OY34: 0.1 | OZ34: 0.1 | PA34: 0.1 | PB34: 0.1 | PC34: 0.1 | PD34: 0.1 | PF34: 0.1 | PG34: 0.1 | PH34: 0.1 | PI34: 0.1 | PJ34: 0.1 | PK34: 0.1 | PM34: 0.1 | PN34: 0.1 | PO34: 0.1 | PP34: 0.1 | PQ34: 0.1 | PR34: 0.1 | PT34: 0.1 | PY34: 0.13 | QA34: 0.13 | QB34: 0.13 | QC34: 0.13 | QD34: 0.13 | QE34: 0.13 | QF34: 0.13 | QH34: 0.13 | QI34: 0.13 | QJ34: 0.13 | QK34: 0.13 | QL34: 0.13 | QM34: 0.13 | QO34: 0.13 | QP34: 0.13 | QQ34: 0.13 | QR34: 0.13 | QS34: 0.13 | QT34: 0.13 | QV34: 0.13 | QW34: 0.13 | QX34: 0.13 | QY34: 0.13 | QZ34: 0.13 | RA34: 0.13 | RC34: 0.13 | RD34: 0.13 | RE34: 0.13 | RF34: 0.13 | RG34: 0.13 | RH34: 0.13 | RJ34: 0.13 | RK34: 0.13 | RL34: 0.13 | RM34: 0.13 | RN34: 0.13 | RO34: 0.13 | RQ34: 0.13 | RR34: 0.13 | RS34: 0.13 | RT34: 0.23 | RU34: 0.5 | RV34: 0.5 | RX34: 0.5 | RY34: 0.56 | RZ34: 0.75 | SA34: 1.09 | SB34: 2.1 | SC34: 2.19 | SE34: 2.44 | SF34: 2.44 | SG34: 2.44 | SH34: 2.1 | SI34: 1.09 | SJ34: 1.09 | SP34: 1.09 | SQ34: 1.03 | SS34: 0.84 | ST34: 0.74 | SU34: 0.38 | SV34: 0.13 | SW34: 0.2 | SX34: 0.39 | SZ34: 0.39 | TA34: 0.39 | TB34: 0.39 | TC34: 0.39 | TD34: 0.36 | TE34: 0.26 | TG34: 0.26 | TH34: 0.42 | TI34: 0.9 | TJ34: 0.9 | TK34: 0.9 | TL34: 0.9 | TN34: 0.9 | TO34: 0.9 | TP34: 0.9 | TQ34: 0.9 | TR34: 0.9 | TS34: 0.9 | TU34: 0.9 | TV34: 0.75 | TW34: 0.29 | TX34: 0.29 | TY34: 0.29 | TZ34: 0.29 | UB34: 0.29 | UC34: 0.29 | UD34: 0.29 | UE34: 0.22 | UT34: 0.05 | UU34: 0.2 | UW34: 0.25 | UX34: 0.4 | UY34: 0.43 | UZ34: 0.51 | VA34: 0.44 | VB34: 0.23 | VD34: 0.23 | VE34: 0.23 | VF34: 0.18 | VG34: 0.03 | VH34: 0.03 | VI34: 0.03 | VK34: 0.03 | VL34: 0.03 | VM34: 0.03 | VN34: 0.02 | YT34: 0.19 | YU34: 0.75 | YV34: 0.75 | YX34: 0.75 | YY34: 0.75 | YZ34: 0.75 | ZA34: 0.75 | ZB34: 0.75 | ZC34: 0.56
A35: 300 mm diameter pipe | E35: 925 | F35: 0 | G35: 342250 | H35: 342250 | I35: =F35 -> 0 | HD35: 12.68 | HE35: 25.37 | HF35: 25.37 | HG35: 25.37 | HH35: 25.37 | HI35: 25.37 | HK35: 25.37 | HL35: 25.37 | HM35: 25.37 | HN35: 25.37 | HO35: 25.37 | HP35: 25.37 | HR35: 25.37 | HS35: 25.37 | HT35: 25.37 | HU35: 25.37 | HV35: 25.37 | HW35: 25.37 | HY35: 12.68 | IU35: 0.57 | IV35: 1.14 | IW35: 1.14 | IX35: 1.14 | IY35: 1.14 | JA35: 0.57 | JR35: 9.58 | JS35: 19.16 | JT35: 19.16 | JV35: 19.16 | JW35: 20.97 | JX35: 13.21 | JY35: 3.63 | JZ35: 3.63 | KA35: 1.81 | KT35: 6.5 | KU35: 13 | KV35: 13 | KX35: 13 | KY35: 6.5 | LJ35: 7.54 | LL35: 15.09 | LM35: 7.54 | LO35: 18.02 | LP35: 36.04 | LQ35: 36.04 | LS35: 36.04 | LT35: 36.04 | LU35: 36.04 | LV35: 18.02 | MY35: 10.13 | MZ35: 20.25 | NB35: 10.13 | NW35: 1.69 | NX35: 3.38 | NY35: 3.38 | NZ35: 3.38 | OA35: 1.69
A36: 4 Way PVC | E36: 102 | F36: 0 | G36: 95880 | H36: 95880 | I36: =F36 -> 0 | XR36: 0.85 | XS36: 3.4 | XT36: 3.4 | XV36: 6.12 | XW36: 14.28 | XX36: 14.28 | XY36: 14.28 | XZ36: 14.28 | YA36: 12.41 | YC36: 6.8 | YD36: 6.8 | YE36: 5.1
A37: 400 mm diameter pipe | E37: 1231 | F37: 0 | G37: 689360 | H37: 689360 | I37: =F37 -> 0 | HD37: 14.86 | HE37: 29.73 | HF37: 29.73 | HG37: 29.73 | HH37: 29.73 | HI37: 29.73 | HK37: 29.73 | HL37: 29.73 | HM37: 29.73 | HN37: 29.73 | HO37: 29.73 | HP37: 29.73 | HR37: 29.73 | HS37: 29.73 | HT37: 29.73 | HU37: 29.73 | HV37: 29.73 | HW37: 29.73 | HY37: 14.86 | IU37: 0.67 | IV37: 1.34 | IW37: 1.34 | IX37: 1.34 | IY37: 1.34 | JA37: 0.67 | JR37: 12.29 | JS37: 24.58 | JT37: 24.58 | JV37: 24.58 | JW37: 26.9 | JX37: 16.94 | JY37: 4.65 | JZ37: 4.65 | KA37: 2.33 | KT37: 11.8 | KU37: 23.6 | KV37: 23.6 | KX37: 23.6 | KY37: 11.8 | LJ37: 12.63 | LL37: 25.26 | LM37: 12.63 | LO37: 30.17 | LP37: 60.33 | LQ37: 60.33 | LS37: 60.33 | LT37: 60.33 | LU37: 60.33 | LV37: 30.17 | MY37: 7.65 | MZ37: 15.3 | NB37: 7.65 | NW37: 1.27 | NX37: 2.55 | NY37: 2.55 | NZ37: 2.55 | OA37: 1.27
A38: 500 mm diameter pipe | E38: 625 | F38: 0 | G38: 468750 | H38: 468750 | I38: =F38 -> 0 | HD38: 2.98 | HE38: 5.96 | HF38: 5.96 | HG38: 5.96 | HH38: 5.96 | HI38: 5.96 | HK38: 5.96 | HL38: 5.96 | HM38: 5.96 | HN38: 5.96 | HO38: 5.96 | HP38: 5.96 | HR38: 5.96 | HS38: 5.96 | HT38: 5.96 | HU38: 5.96 | HV38: 5.96 | HW38: 5.96 | HY38: 2.98 | IU38: 0.13 | IV38: 0.27 | IW38: 0.27 | IX38: 0.27 | IY38: 0.27 | JA38: 0.13 | JR38: 15.53 | JS38: 31.05 | JT38: 31.05 | JV38: 31.05 | JW38: 34 | JX38: 21.41 | JY38: 5.88 | JZ38: 5.88 | KA38: 2.94 | KT38: 3.05 | KU38: 6.1 | KV38: 6.1 | KX38: 6.1 | KY38: 3.05 | LJ38: 9.04 | LL38: 18.09 | LM38: 9.04 | LO38: 21.6 | LP38: 43.2 | LQ38: 43.2 | LS38: 43.2 | LT38: 43.2 | LU38: 43.2 | LV38: 21.6 | MY38: 3.34 | MZ38: 6.68 | NB38: 3.34 | NW38: 0.56 | NX38: 1.11 | NY38: 1.11 | NZ38: 1.11 | OA38: 0.56
A39: Acess Entrace Ramp | E39: 2 | F39: 0 | G39: 70500 | H39: 70500 | I39: =F39 -> 0 | HU39: 0.2 | HV39: 0.4 | HW39: 0.4 | HY39: 0.4 | HZ39: 0.4 | IA39: 0.2
A40: Air V CH On pipes Dia. 160 mm | E40: 3 | F40: 0 | G40: 28680 | H40: 28680 | I40: =F40 -> 0 | QT40: 0.02 | QV40: 0.08 | QW40: 0.08 | QX40: 0.08 | QY40: 0.09 | QZ40: 0.15 | RA40: 0.15 | RC40: 0.15 | RD40: 0.15 | RE40: 0.15 | RF40: 0.15 | RG40: 0.15 | RH40: 0.14 | RJ40: 0.1 | RK40: 0.1 | RL40: 0.18 | RM40: 0.4 | RN40: 0.4 | RO40: 0.3
A41: Air V CH On pipes Dia. 250 mm | E41: 3 | F41: 0 | G41: 28680 | H41: 28680 | I41: =F41 -> 0 | RS41: 0.01 | RT41: 0.03 | RU41: 0.03 | RV41: 0.05 | RX41: 0.1 | RY41: 0.1 | RZ41: 0.1 | SA41: 0.09 | SB41: 0.05 | SC41: 0.1 | SE41: 0.25 | SF41: 0.23 | SG41: 0.15 | SH41: 0.16 | SI41: 0.2 | SJ41: 0.18 | SP41: 0.13 | SQ41: 0.12 | SS41: 0.11 | ST41: 0.23 | SU41: 0.23 | SV41: 0.2 | SW41: 0.15
A42: Air V CH On pipes Dia. 315 mm | E42: 1 | F42: 0 | G42: 9560 | H42: 9560 | I42: =F42 -> 0 | TZ42: 0.01 | UB42: 0.02 | UC42: 0.02 | UD42: 0.02 | UE42: 0.02 | UF42: 0.03 | UG42: 0.07 | UI42: 0.07 | UJ42: 0.07 | UK42: 0.07 | UL42: 0.07 | UM42: 0.06 | UN42: 0.03 | UP42: 0.03 | UQ42: 0.06 | UR42: 0.13 | US42: 0.13 | UT42: 0.1
A43: Air valve chamber; on 160 mm dia pipeline Depth 1.5- 3 m | E43: 7 | F43: 0 | G43: 66990 | H43: 66990 | I43: =F43 -> 0 | UC43: 0.03 | UD43: 0.1 | UE43: 0.1 | UF43: 0.11 | UG43: 0.15 | UI43: 0.15 | UJ43: 0.15 | UK43: 0.15 | UL43: 0.15 | UM43: 0.15 | UN43: 0.15 | UP43: 0.13 | UQ43: 0.08 | UR43: 0.08 | US43: 0.08 | UT43: 0.13 | UU43: 0.3 | UW43: 0.3 | UX43: 0.3 | UY43: 0.22 | VI43: 0.01 | VK43: 0.05 | VL43: 0.05 | VM43: 0.05 | VN43: 0.06 | VO43: 0.08 | VP43: 0.08 | VR43: 0.08 | VS43: 0.08 | VT43: 0.08 | VU43: 0.07 | VV43: 0.07 | VW43: 0.07 | VY43: 0.07 | VZ43: 0.07 | WA43: 0.07 | WB43: 0.07 | WC43: 0.07 | WD43: 0.07 | WF43: 0.07 | WG43: 0.09 | WH43: 0.16 | WI43: 0.16 | WJ43: 0.17 | WK43: 0.2 | WM43: 0.2 | WN43: 0.17 | WO43: 0.07 | WQ43: 0.07 | WR43: 0.07 | WT43: 0.07 | WU43: 0.07 | WV43: 0.07 | WW43: 0.07 | WX43: 0.07 | WY43: 0.06 | XA43: 0.02 | XB43: 0.02 | XC43: 0.02 | XD43: 0.02 | XE43: 0.02 | XF43: 0.02 | XH43: 0.02 | XI43: 0.02 | XJ43: 0.02 | XK43: 0.06 | XL43: 0.16 | XM43: 0.16 | XO43: 0.16 | XP43: 0.16 | XQ43: 0.12
A44: Chain link fence | E44: 650 | F44: 0 | G44: 113750 | H44: 113750 | I44: =F44 -> 0 | YD44: 4.88 | YE44: 19.5 | YF44: 19.5 | YG44: 19.5 | YH44: 19.5 | YJ44: 20.43 | YK44: 23.21 | YL44: 23.21 | YM44: 23.21 | YN44: 23.21 | YO44: 23.21 | YQ44: 23.21 | YR44: 31.34 | YS44: 55.71 | YT44: 55.71 | YU44: 55.71 | YV44: 55.71 | YX44: 55.71 | YY44: 55.71 | YZ44: 41.79
A45: Conc. lining, incl PC & Expansion Joints | E45: 3000 | F45: 0 | G45: 4935000 | H45: 4935000 | I45: =F45 -> 0 | XD45: 27.69 | XE45: 110.77 | XF45: 83.07 | XI45: 27.69 | XJ45: 110.77 | XK45: 110.77 | XL45: 99.69 | XM45: 66.46 | XO45: 66.46 | XP45: 66.46 | XQ45: 66.46 | XR45: 105.23 | XS45: 221.53 | XT45: 221.53 | XV45: 221.53 | XW45: 221.53 | XX45: 177.22 | XY45: 44.31 | XZ45: 44.31 | YA45: 68.83 | YC45: 142.39 | YD45: 131.32 | YE45: 98.09 | YF45: 98.09 | YG45: 98.09 | YH45: 98.09 | YJ45: 98.09 | YK45: 73.56
A46: Double Catch basin | E46: 20 | F46: 0 | G46: 483000 | H46: 483000 | I46: =F46 -> 0 | U46: 0.1 | W46: 0.1 | X46: 0.1 | Y46: 0.1 | Z46: 0.1 | AA46: 0.1 | BX46: 0.02 | BY46: 0.02 | CA46: 0.02 | CB46: 0.02 | CC46: 0.02 | CD46: 0.02 | CJ46: 0.02 | CK46: 0.02 | CL46: 0.02 | CM46: 0.02 | CO46: 0.02 | CP46: 0.02 | CQ46: 0.02 | CR46: 0.02 | CS46: 0.02 | CT46: 0.02 | CV46: 0.02 | CW46: 0.02 | CX46: 0.02 | CY46: 0.02 | CZ46: 0.02 | DA46: 0.02 | DC46: 0.02 | DD46: 0.02 | DE46: 0.02 | DF46: 0.02 | DG46: 0.02 | DH46: 0.02 | DJ46: 0.02 | DK46: 0.02 | DL46: 0.02 | DM46: 0.02 | DN46: 0.02 | DO46: 0.02 | DQ46: 0.02 | DR46: 0.02 | DS46: 0.02 | DT46: 0.02 | DU46: 0.02 | DV46: 0.02 | DX46: 0.02 | DY46: 0.02 | DZ46: 0.02 | EA46: 0.02 | EB46: 0.02 | EC46: 0.02 | EE46: 0.02 | EF46: 0.02 | EG46: 0.02 | EH46: 0.02 | EI46: 0.02 | EJ46: 0.02 | EL46: 0.02 | EM46: 0.02 | EN46: 0.02 | EO46: 0.02 | EP46: 0.02 | EQ46: 0.02 | ES46: 0.02 | ET46: 0.02 | EZ46: 0.02 | FA46: 0.02 | FB46: 0.02 | FC46: 0.02 | FD46: 0.02 | FE46: 0.02 | FG46: 0.02 | FH46: 0.02 | FI46: 0.02 | FJ46: 0.02 | FK46: 0.02 | FL46: 0.02 | FN46: 0.02 | FO46: 0.02 | FP46: 0.02 | FQ46: 0.02 | FR46: 0.02 | FS46: 0.02 | FU46: 0.02 | FV46: 0.02 | FW46: 0.02 | FX46: 0.02 | FY46: 0.02 | FZ46: 0.02 | GB46: 0.02 | GC46: 0.02 | GD46: 0.02 | GE46: 0.02 | GF46: 0.02 | GG46: 0.02 | GI46: 0.02 | GJ46: 0.02 | GK46: 0.02 | GL46: 0.02 | GM46: 0.02 | GN46: 0.02 | GP46: 0.02 | GQ46: 0.02 | GR46: 0.02 | GS46: 0.02 | GT46: 0.02 | GU46: 0.02 | GW46: 0.02 | GX46: 0.02 | GY46: 0.02 | GZ46: 0.02 | HA46: 0.02 | HB46: 0.02 | HD46: 0.02 | HE46: 0.02 | HF46: 0.02 | HG46: 0.02 | HH46: 0.02 | HI46: 0.02 | HK46: 0.02 | HL46: 0.02 | HM46: 0.02 | HN46: 0.02 | HO46: 0.02 | HP46: 0.02 | HR46: 0.02 | HS46: 0.02 | HT46: 0.02 | HU46: 0.02 | HV46: 0.02 | HW46: 0.02 | HY46: 0.02 | HZ46: 0.02 | IA46: 0.02 | IB46: 0.03 | IC46: 0.04 | ID46: 0.04 | IF46: 0.04 | IG46: 0.04 | IH46: 0.04 | II46: 0.04 | IJ46: 0.05 | IK46: 0.05 | IM46: 0.05 | IN46: 0.05 | IP46: 0.08 | IQ46: 0.1 | IR46: 0.1 | IT46: 0.1 | IU46: 0.06 | IV46: 0.02 | IW46: 0.02 | IX46: 0.02 | IY46: 0.02 | JA46: 0.03 | JB46: 0.03 | JC46: 0.03 | JD46: 0.03 | JE46: 0.03 | JF46: 0.08 | JH46: 0.13 | JI46: 0.13 | JJ46: 0.13 | JK46: 0.13 | JL46: 0.13 | JM46: 0.16 | JO46: 0.19 | JP46: 0.19 | JQ46: 0.19 | JR46: 0.31 | JS46: 0.44 | JT46: 0.44 | JV46: 0.44 | JW46: 0.23 | JX46: 0.02 | JY46: 0.02 | JZ46: 0.02 | KA46: 0.04 | KC46: 0.06 | KD46: 0.06 | KE46: 0.06 | KF46: 0.06 | KG46: 0.06 | KH46: 0.06 | KJ46: 0.06 | KK46: 0.06 | KL46: 0.04 | KM46: 0.02 | KN46: 0.02 | KO46: 0.02 | KQ46: 0.02 | KR46: 0.02 | KS46: 0.02 | KT46: 0.02 | KU46: 0.02 | KV46: 0.02 | KX46: 0.01 | LB46: 0.27 | LC46: 0.54 | LE46: 0.54 | LF46: 0.67 | LG46: 0.8 | LH46: 1.41 | LI46: 2.01 | LJ46: 1 | LM46: 0.1 | LN46: 0.2 | LO46: 0.2 | LP46: 0.2 | LQ46: 0.1 | NF46: 0.02 | NG46: 0.04 | NI46: 0.04 | NJ46: 0.04 | NK46: 0.04 | NL46: 0.04 | NM46: 0.06 | NN46: 0.07 | NP46: 0.07 | NQ46: 0.07 | NR46: 0.12 | NS46: 0.17 | NT46: 0.17 | NU46: 0.17 | NW46: 0.08 | OA46: 0.01 | OB46: 0.02 | OD46: 0.02 | OE46: 0.02 | OF46: 0.02 | OG46: 0.02 | OH46: 0.02 | OI46: 0.01 | YA46: 0.06 | YC46: 0.25 | YD46: 0.25 | YE46: 0.25 | YF46: 0.25 | YG46: 0.25 | YH46: 0.25 | YJ46: 0.25 | YK46: 0.19
A47: Double swing main entrance gate | E47: 2 | F47: 0 | G47: 117500 | H47: 117500 | I47: =F47 -> 0 | YZ47: 0.17 | ZA47: 0.67 | ZB47: 0.67 | ZC47: 0.5
A48: Drawpit incl. cover | E48: 23 | F48: 0 | G48: 135700 | H48: 135700 | I48: =F48 -> 0 | VS48: 0.05 | VT48: 0.2 | VU48: 0.2 | VV48: 0.24 | VW48: 0.38 | VY48: 0.38 | VZ48: 0.38 | WA48: 0.38 | WB48: 0.38 | WC48: 0.38 | WD48: 0.38 | WF48: 0.39 | WG48: 0.45 | WH48: 0.45 | WI48: 0.45 | WJ48: 0.42 | WK48: 0.27 | WM48: 0.12 | WN48: 0.2 | WO48: 0.45 | WQ48: 0.42 | WR48: 0.3 | WT48: 0.2 | WU48: 0.2 | WV48: 0.17 | WW48: 0.07 | WX48: 0.07 | WY48: 0.05 | XB48: 0.28 | XC48: 0.83 | XF48: 0.46 | XH48: 1.93 | XI48: 2.13 | XJ48: 1.65 | XK48: 1.1 | XL48: 1.1 | XM48: 0.92 | XO48: 0.45 | XP48: 0.7 | XQ48: 0.61 | XR48: 0.33 | XS48: 0.33 | XT48: 0.33 | XV48: 0.32 | XW48: 0.3 | XX48: 0.3 | XY48: 0.3 | XZ48: 0.25 | YA48: 0.08 | YC48: 0.08 | YD48: 0.08 | YE48: 0.08 | YF48: 0.06
A49: Earthing | E49: 13 | F49: 0 | G49: 152750 | H49: 152750 | I49: =F49 -> 0 | YN49: 0.33 | YO49: 0.98 | YR49: 0.76 | YS49: 3.03 | YT49: 3.03 | YU49: 2.49 | YV49: 0.87 | YX49: 0.87 | YY49: 0.65
A50: Excavation | E50: 37125 | F50: 22506.58 | G50: 2227500 | H50: 2227500 | I50: =F50 -> 22506.58 | AW50: 189.2 | AY50: 189.2 | AZ50: 189.2 | BA50: 141.9 | BB50: 141.9 | BC50: 141.9 | BD50: 141.9 | BF50: 141.9 | BG50: 141.9 | BH50: 141.9 | BI50: 141.9 | BJ50: 141.9 | BK50: 141.9 | BM50: 141.9 | BN50: 141.9 | BO50: 141.9 | BP50: 141.9 | BQ50: 141.9 | BR50: 141.9 | BT50: 141.9 | BU50: 141.9 | BV50: 141.9 | BW50: 141.9 | BX50: 120.97 | BY50: 120.97 | CA50: 120.97 | CB50: 120.97 | CC50: 120.97 | CD50: 120.97 | CJ50: 161.29 | CK50: 161.29 | CL50: 161.29 | CM50: 161.29 | CO50: 161.29 | CP50: 161.29 | CQ50: 161.29 | CR50: 161.29 | CS50: 161.29 | CT50: 161.29 | CV50: 161.29 | CW50: 161.29 | CX50: 161.29 | CY50: 168.11 | CZ50: 174.92 | DA50: 174.92 | DC50: 174.92 | DD50: 174.92 | DE50: 174.92 | DF50: 174.92 | DG50: 174.92 | DH50: 174.92 | DJ50: 174.92 | DK50: 174.92 | DL50: 174.92 | DM50: 174.92 | DN50: 174.92 | DO50: 174.92 | DQ50: 174.92 | DR50: 174.92 | DS50: 174.92 | DT50: 162.89 | DU50: 150.86 | DV50: 150.86 | DX50: 150.86 | DY50: 150.86 | DZ50: 150.86 | EA50: 150.86 | EB50: 150.86 | EC50: 150.86 | EE50: 150.86 | EF50: 150.86 | EG50: 150.86 | EH50: 150.86 | EI50: 150.86 | EJ50: 150.86 | EL50: 150.86 | EM50: 150.86 | EN50: 150.86 | EO50: 150.86 | EP50: 150.86 | EQ50: 691.69 | ES50: 1232.52 | ET50: 1232.52 | EZ50: 1232.52 | FA50: 1232.52 | FB50: 1232.52 | FC50: 1232.52 | FD50: 1232.52 | FE50: 1232.52 | FG50: 1232.52 | FH50: 1232.52 | FI50: 1232.52 | FJ50: 1232.52 | FK50: 1232.52 | FL50: 1232.52 | FN50: 1232.52 | FO50: 1232.52 | FP50: 1232.52 | FQ50: 1232.52 | FR50: 1232.52 | FS50: 616.26
A51: Filling | E51: 16500 | F51: 0 | G51: 825000 | H51: 825000 | I51: =F51 -> 0 | FS51: 750 | FU51: 1500 | FV51: 1500 | FW51: 1500 | FX51: 1500 | FY51: 1500 | FZ51: 1500 | GB51: 1500 | GC51: 1500 | GD51: 1500 | GE51: 1500 | GF51: 750
A52: Filling with imported Material | E52: 1856 | F52: 0 | G52: 129920 | H52: 129920 | I52: =F52 -> 0 | IA52: 185.6 | IB52: 371.2 | IC52: 371.2 | ID52: 371.2 | IF52: 371.2 | IG52: 185.6
A53: Flow meter chamber on 630 mm dia pipeline Depth 0- 1.5 m | E53: 1 | F53: 0 | G53: 9570 | H53: 9570 | I53: =F53 -> 0 | AK53: 0.01 | AL53: 0.01 | AM53: 0.01 | XB53: 0.01 | XC53: 0.02 | XD53: 0.02 | XE53: 0.02 | XF53: 0.02 | XH53: 0.02 | XI53: 0.02 | XJ53: 0.02 | XK53: 0.02 | XL53: 0.02 | XM53: 0.02 | XO53: 0.03 | XP53: 0.03 | XQ53: 0.03 | XR53: 0.03 | XS53: 0.02 | XT53: 0.02 | XV53: 0.02 | XW53: 0.04 | XX53: 0.12 | XY53: 0.12 | XZ53: 0.12 | YA53: 0.09 | ZC53: 0 | ZE53: 0.01 | ZF53: 0.01 | ZG53: 0.01 | ZH53: 0.01 | ZI53: 0.01 | ZJ53: 0.01 | ZL53: 0.01 | ZM53: 0.01
A54: LED Lumin 110 W | E54: 193 | F54: 0 | G54: 675500 | H54: 675500 | I54: =F54 -> 0 | AB54: 0.97 | AD54: 0.97 | AE54: 0.97 | AF54: 0.97 | AG54: 0.97 | AH54: 0.97 | TG54: 0.14 | TH54: 0.55 | TI54: 0.55 | TJ54: 0.55 | TK54: 0.55 | TL54: 0.55 | TN54: 0.55 | TO54: 0.55 | TP54: 0.55 | TQ54: 0.55 | TR54: 0.55 | TS54: 0.55 | TU54: 0.55 | TV54: 0.55 | TW54: 0.55 | TX54: 0.55 | TY54: 0.55 | TZ54: 0.55 | UB54: 0.55 | UC54: 0.55 | UD54: 0.55 | UE54: 0.55 | UF54: 0.55 | UG54: 0.55 | UI54: 0.55 | UJ54: 0.55 | UK54: 0.55 | UL54: 0.55 | UM54: 0.55 | UN54: 0.55 | UP54: 0.55 | UQ54: 0.55 | UR54: 0.55 | US54: 0.55 | UT54: 0.55 | UU54: 0.55 | UW54: 0.55 | UX54: 0.55 | UY54: 0.55 | UZ54: 0.55 | VA54: 0.55 | VB54: 0.55 | VD54: 0.55 | VE54: 0.55 | VF54: 0.55 | VG54: 0.55 | VH54: 0.55 | VI54: 0.55 | VK54: 0.55 | VL54: 0.55 | VM54: 0.55 | VN54: 0.55 | VO54: 0.55 | VP54: 0.55 | VR54: 0.55 | VS54: 0.55 | VT54: 0.55 | VU54: 0.55 | VV54: 0.55 | VW54: 0.55 | VY54: 0.55 | VZ54: 0.55 | WA54: 0.55 | WB54: 0.55 | WC54: 0.55 | WD54: 0.55 | WF54: 0.55 | WG54: 0.55 | WH54: 0.55 | WI54: 0.55 | WJ54: 0.41 | WX54: 1.27 | WY54: 5.06 | XA54: 6.07 | XB54: 9.08 | XC54: 9.08 | XD54: 9.08 | XE54: 8.08 | XF54: 5.9 | XH54: 8.41 | XI54: 7.15 | XJ54: 2.51 | YD54: 1.82 | YE54: 7.27 | YF54: 7.27 | YG54: 7.27 | YH54: 7.27 | YJ54: 7.27 | YK54: 7.27 | YL54: 5.45 | YV54: 0.56 | YX54: 2.23 | YY54: 2.23 | YZ54: 1.68 | ZM54: 0.48 | ZN54: 1.93 | ZO54: 1.93 | ZP54: 1.93 | ZQ54: 1.93 | ZS54: 1.93 | ZT54: 1.93 | ZU54: 1.93 | ZV54: 1.93 | ZW54: 1.93 | ZX54: 1.45
A55: Outfall 1000 | E55: 1 | F55: 0 | G55: 18800 | H55: 18800 | I55: =F55 -> 0 | GM55: 0.03 | GN55: 0.06 | GP55: 0.06 | GQ55: 0.06 | GR55: 0.06 | GS55: 0.18 | GT55: 0.3 | GU55: 0.16 | GW55: 0.02 | GX55: 0.02 | GY55: 0.02 | GZ55: 0.02 | HA55: 0.01
A56: Outfall 1400 | E56: 1 | F56: 0 | G56: 23500 | H56: 23500 | I56: =F56 -> 0 | GG56: 0.03 | GI56: 0.06 | GJ56: 0.06 | GK56: 0.06 | GL56: 0.06 | GM56: 0.18 | GN56: 0.3 | GP56: 0.16 | GQ56: 0.02 | GR56: 0.02 | GS56: 0.02 | GT56: 0.02 | GU56: 0.01
A57: Pipe encasement dia 200mm | E57: 215 | F57: 0 | G57: 202100 | H57: 202100 | I57: =F57 -> 0 | LN57: 1.89 | LO57: 3.77 | LP57: 3.77 | LQ57: 3.77 | LS57: 3.77 | LT57: 3.77 | LU57: 8.17 | LV57: 12.57 | LW57: 12.57 | LX57: 7.79 | LZ57: 3.02 | MA57: 3.02 | MB57: 3.02 | MC57: 3.02 | MD57: 5 | ME57: 6.98 | MG57: 6.98 | MH57: 6.98 | MI57: 6.98 | MJ57: 6.98 | MK57: 9.31 | ML57: 11.63 | MN57: 11.63 | MO57: 11.63 | MP57: 11.63 | MQ57: 11.63 | MR57: 8.14 | MS57: 4.65 | MU57: 4.65 | MV57: 4.65 | MW57: 4.65 | MX57: 4.65 | MY57: 2.33
A58: Pipe encasement dia 250mm | E58: 215 | F58: 0 | G58: 202100 | H58: 202100 | I58: =F58 -> 0 | KL58: 0.64 | KM58: 1.29 | KN58: 1.29 | KO58: 1.29 | KQ58: 1.29 | KR58: 1.29 | KS58: 1.29 | KT58: 1.29 | KU58: 1.29 | KV58: 2.02 | KX58: 2.76 | KY58: 2.76 | KZ58: 2.76 | LA58: 2.76 | LB58: 2.76 | LC58: 2.76 | LE58: 1.86 | LF58: 0.97 | LG58: 0.97 | LH58: 0.97 | LI58: 0.97 | LJ58: 0.97 | LL58: 0.97 | LM58: 0.97 | LN58: 0.48 | LU58: 3.61 | LV58: 7.21 | LW58: 7.21 | LX58: 7.21 | LZ58: 7.21 | MA58: 7.21 | MB58: 9.62 | MC58: 12.02 | MD58: 12.02 | ME58: 12.02 | MG58: 12.02 | MH58: 12.02 | MI58: 8.42 | MJ58: 4.81 | MK58: 4.81 | ML58: 4.81 | MN58: 4.81 | MO58: 4.81 | MP58: 2.4 | OP58: 0.97 | OR58: 1.45 | OS58: 1.45 | OT58: 1.45 | OU58: 1.45 | OV58: 1.45 | OW58: 1.45 | OY58: 6.03 | OZ58: 6.03 | PA58: 4.42 | PB58: 1.21 | PC58: 1.21 | PD58: 1.21 | PF58: 1.21 | PG58: 1.21
A59: Pipe encasement dia 315mm | E59: 215 | F59: 0 | G59: 202100 | H59: 202100 | I59: =F59 -> 0 | LV59: 1.08 | LW59: 2.17 | LX59: 2.17 | LZ59: 2.17 | MA59: 2.17 | MB59: 2.17 | MC59: 4.7 | MD59: 7.22 | ME59: 7.22 | MG59: 4.48 | MH59: 1.73 | MI59: 1.73 | MJ59: 1.73 | MK59: 1.73 | ML59: 0.87 | OE59: 3.22 | OF59: 6.44 | OG59: 6.44 | OH59: 6.44 | OI59: 6.44 | OL59: 6.44 | OM59: 6.44 | ON59: 6.44 | OO59: 10.37 | OP59: 14.31 | OR59: 10.73 | OS59: 10.73 | OT59: 10.73 | OU59: 10.73 | OV59: 10.73 | OW59: 10.73 | OY59: 3.68 | OZ59: 3.68 | PA59: 3.68 | PB59: 3.68 | PC59: 3.68 | PD59: 3.68 | PF59: 3.68 | PG59: 3.68 | PH59: 3.68 | PI59: 1.23
A60: Pot Air V on pipes with dia(160) mm. | E60: 4 | F60: 0.11 | G60: 11280 | H60: 11280 | I60: =F60 -> 0.11 | AF60: 0.02 | AG60: 0.02 | AH60: 0.02 | AK60: 0.02 | AL60: 0.02 | AM60: 0.02 | AN60: 0.02 | AO60: 0.02 | NN60: 0 | NP60: 0.01 | NQ60: 0.01 | NR60: 0.01 | NS60: 0.01 | NT60: 0.01 | NU60: 0.01 | NW60: 0.01 | NX60: 0.01 | NY60: 0.01 | NZ60: 0.01 | OA60: 0.01 | OB60: 0.01 | OD60: 0.01 | OE60: 0.01 | OF60: 0.01 | OG60: 0.01 | OH60: 0.01 | OI60: 0.01 | OL60: 0.01 | OM60: 0.01 | ON60: 0.01 | OO60: 0.01 | OP60: 0.01 | OR60: 0.01 | OS60: 0.01 | OT60: 0.01 | OU60: 0.01 | OV60: 0.01 | OW60: 0.01 | OY60: 0.01 | OZ60: 0.01 | PA60: 0.01 | PB60: 0.01 | PC60: 0.01 | PD60: 0.01 | PF60: 0.01 | PG60: 0.01 | PH60: 0.01 | PI60: 0.01 | PJ60: 0.01 | PK60: 0.01 | PM60: 0.01 | PN60: 0.01 | PO60: 0.01 | PP60: 0.01 | PQ60: 0.01 | PR60: 0.01 | PT60: 0.01 | PY60: 0.01 | QA60: 0.01 | QB60: 0.01 | QC60: 0.01 | QD60: 0.01 | QE60: 0.01 | QF60: 0.01 | QH60: 0.01 | QI60: 0.01 | QJ60: 0.01 | QK60: 0.01 | QL60: 0.01 | QM60: 0.01 | QO60: 0.01 | QP60: 0.01 | QQ60: 0.01 | QR60: 0.01 | QS60: 0.01 | QT60: 0.02 | QV60: 0.07 | QW60: 0.07 | QX60: 0.07 | QY60: 0.09 | QZ60: 0.14 | RA60: 0.14 | RC60: 0.14 | RD60: 0.14 | RE60: 0.14 | RF60: 0.14 | RG60: 0.14 | RH60: 0.13 | RJ60: 0.09 | RK60: 0.09 | RL60: 0.16 | RM60: 0.37 | RN60: 0.37 | RO60: 0.28 | RQ60: 0.01 | RR60: 0.01 | RS60: 0.01 | RT60: 0.01 | RU60: 0.01 | RV60: 0.01 | RX60: 0.01 | RY60: 0.01 | RZ60: 0.01 | SA60: 0.01 | SB60: 0.01 | SC60: 0.01 | SE60: 0.01 | SF60: 0.01 | SG60: 0.01 | SH60: 0.01 | SI60: 0.01 | SJ60: 0.01 | SP60: 0.01 | SQ60: 0.01 | SS60: 0.01 | YT60: 0.01 | YU60: 0.05 | YV60: 0.05 | YX60: 0.05 | YY60: 0.05 | YZ60: 0.05 | ZA60: 0.05 | ZB60: 0.05 | ZC60: 0.04
A61: Pot Air V on pipes with dia(250) mm. | E61: 2 | F61: 0.05 | G61: 5640 | H61: 5640 | I61: =F61 -> 0.05 | AF61: 0.01 | AG61: 0.01 | AH61: 0.01 | AK61: 0.01 | AL61: 0.01 | AM61: 0.01 | AN61: 0.01 | AO61: 0.01 | NN61: 0 | NP61: 0 | NQ61: 0 | NR61: 0 | NS61: 0 | NT61: 0 | NU61: 0 | NW61: 0 | NX61: 0 | NY61: 0 | NZ61: 0 | OA61: 0 | OB61: 0 | OD61: 0 | OE61: 0 | OF61: 0 | OG61: 0 | OH61: 0 | OI61: 0 | OL61: 0 | OM61: 0 | ON61: 0 | OO61: 0 | OP61: 0 | OR61: 0 | OS61: 0 | OT61: 0 | OU61: 0 | OV61: 0 | OW61: 0 | OY61: 0 | OZ61: 0 | PA61: 0 | PB61: 0 | PC61: 0 | PD61: 0 | PF61: 0 | PG61: 0 | PH61: 0 | PI61: 0 | PJ61: 0 | PK61: 0 | PM61: 0 | PN61: 0 | PO61: 0 | PP61: 0 | PQ61: 0 | PR61: 0 | PT61: 0 | PY61: 0 | QA61: 0 | QB61: 0 | QC61: 0 | QD61: 0 | QE61: 0 | QF61: 0 | QH61: 0 | QI61: 0 | QJ61: 0 | QK61: 0 | QL61: 0 | QM61: 0 | QO61: 0 | QP61: 0 | QQ61: 0 | QR61: 0 | QS61: 0 | QT61: 0 | QV61: 0 | QW61: 0 | QX61: 0 | QY61: 0 | QZ61: 0 | RA61: 0 | RC61: 0 | RD61: 0 | RE61: 0 | RF61: 0 | RG61: 0 | RH61: 0 | RJ61: 0 | RK61: 0 | RL61: 0 | RM61: 0 | RN61: 0 | RO61: 0 | RQ61: 0 | RR61: 0 | RS61: 0.01 | RT61: 0.02 | RU61: 0.02 | RV61: 0.03 | RX61: 0.05 | RY61: 0.05 | RZ61: 0.05 | SA61: 0.04 | SB61: 0.03 | SC61: 0.05 | SE61: 0.12 | SF61: 0.1 | SG61: 0.07 | SH61: 0.08 | SI61: 0.09 | SJ61: 0.09 | SP61: 0.06 | SQ61: 0.06 | SS61: 0.05 | ST61: 0.1 | SU61: 0.1 | SV61: 0.09 | SW61: 0.07 | YT61: 0.01 | YU61: 0.03 | YV61: 0.03 | YX61: 0.03 | YY61: 0.03 | YZ61: 0.03 | ZA61: 0.03 | ZB61: 0.03 | ZC61: 0.02
A62: Pot Air V on pipes with dia(315) mm. | E62: 1 | F62: 0.03 | G62: 2820 | H62: 2820 | I62: =F62 -> 0.03 | AF62: 0 | AG62: 0 | AH62: 0 | AK62: 0 | AL62: 0 | AM62: 0 | AN62: 0 | AO62: 0 | NN62: 0 | NP62: 0 | NQ62: 0 | NR62: 0 | NS62: 0 | NT62: 0 | NU62: 0 | NW62: 0 | NX62: 0 | NY62: 0 | NZ62: 0 | OA62: 0 | OB62: 0 | OD62: 0 | OE62: 0 | OF62: 0 | OG62: 0 | OH62: 0 | OI62: 0 | OL62: 0 | OM62: 0 | ON62: 0 | OO62: 0 | OP62: 0 | OR62: 0 | OS62: 0 | OT62: 0 | OU62: 0 | OV62: 0 | OW62: 0 | OY62: 0 | OZ62: 0 | PA62: 0 | PB62: 0 | PC62: 0 | PD62: 0 | PF62: 0 | PG62: 0 | PH62: 0 | PI62: 0 | PJ62: 0 | PK62: 0 | PM62: 0 | PN62: 0 | PO62: 0 | PP62: 0 | PQ62: 0 | PR62: 0 | PT62: 0 | PY62: 0 | QA62: 0 | QB62: 0 | QC62: 0 | QD62: 0 | QE62: 0 | QF62: 0 | QH62: 0 | QI62: 0 | QJ62: 0 | QK62: 0 | QL62: 0 | QM62: 0 | QO62: 0 | QP62: 0 | QQ62: 0 | QR62: 0 | QS62: 0 | QT62: 0 | QV62: 0 | QW62: 0 | QX62: 0 | QY62: 0 | QZ62: 0 | RA62: 0 | RC62: 0 | RD62: 0 | RE62: 0 | RF62: 0 | RG62: 0 | RH62: 0 | RJ62: 0 | RK62: 0 | RL62: 0 | RM62: 0 | RN62: 0 | RO62: 0 | RQ62: 0 | RR62: 0 | RS62: 0 | RT62: 0 | RU62: 0 | RV62: 0 | RX62: 0 | RY62: 0 | RZ62: 0 | SA62: 0 | SB62: 0 | SC62: 0 | SE62: 0 | SF62: 0 | SG62: 0 | SH62: 0 | SI62: 0 | SJ62: 0 | SP62: 0 | SQ62: 0 | SS62: 0 | TZ62: 0.01 | UB62: 0.03 | UC62: 0.03 | UD62: 0.03 | UE62: 0.03 | UF62: 0.03 | UG62: 0.02 | UI62: 0.02 | UJ62: 0.02 | UK62: 0.02 | UL62: 0.02 | UM62: 0.03 | UN62: 0.04 | UP62: 0.04 | UQ62: 0.06 | UR62: 0.09 | US62: 0.09 | UT62: 0.07 | YT62: 0 | YU62: 0.01 | YV62: 0.01 | YX62: 0.01 | YY62: 0.01 | YZ62: 0.01 | ZA62: 0.01 | ZB62: 0.01 | ZC62: 0.01
A63: Pot Butterfly Valves Dia. 315 mm | E63: 1 | F63: 0.03 | G63: 13630 | H63: 13630 | I63: =F63 -> 0.03 | AF63: 0 | AG63: 0 | AH63: 0 | AK63: 0 | AL63: 0 | AM63: 0 | AN63: 0 | AO63: 0 | NN63: 0 | NP63: 0 | NQ63: 0 | NR63: 0 | NS63: 0 | NT63: 0 | NU63: 0 | NW63: 0 | NX63: 0 | NY63: 0 | NZ63: 0 | OA63: 0 | OB63: 0 | OD63: 0 | OE63: 0 | OF63: 0 | OG63: 0 | OH63: 0 | OI63: 0 | OL63: 0 | OM63: 0 | ON63: 0 | OO63: 0 | OP63: 0 | OR63: 0 | OS63: 0 | OT63: 0 | OU63: 0 | OV63: 0 | OW63: 0 | OY63: 0 | OZ63: 0 | PA63: 0 | PB63: 0 | PC63: 0 | PD63: 0 | PF63: 0 | PG63: 0 | PH63: 0 | PI63: 0 | PJ63: 0 | PK63: 0 | PM63: 0 | PN63: 0 | PO63: 0 | PP63: 0 | PQ63: 0 | PR63: 0 | PT63: 0 | PY63: 0 | QA63: 0 | QB63: 0 | QC63: 0 | QD63: 0 | QE63: 0 | QF63: 0 | QH63: 0 | QI63: 0 | QJ63: 0 | QK63: 0.02 | QL63: 0.05 | QM63: 0.01 | QO63: 0.05 | QP63: 0.05 | QQ63: 0.05 | QR63: 0.05 | QS63: 0.05 | QT63: 0.04 | QV63: 0.04 | QW63: 0.06 | QX63: 0.14 | QY63: 0.1 | QZ63: 0 | RA63: 0 | RC63: 0 | RD63: 0 | RE63: 0 | RF63: 0 | RG63: 0 | RH63: 0 | RJ63: 0 | RK63: 0 | RL63: 0 | RM63: 0 | RN63: 0 | RO63: 0 | RQ63: 0 | RR63: 0 | RS63: 0 | RT63: 0 | RU63: 0 | RV63: 0 | RX63: 0 | RY63: 0 | RZ63: 0 | SA63: 0 | SB63: 0 | SC63: 0 | SE63: 0 | SF63: 0 | SG63: 0 | SH63: 0 | SI63: 0 | SJ63: 0 | SP63: 0 | SQ63: 0 | SS63: 0 | YT63: 0 | YU63: 0.01 | YV63: 0.01 | YX63: 0.01 | YY63: 0.01 | YZ63: 0.01 | ZA63: 0.01 | ZB63: 0.01 | ZC63: 0.01
A64: Pot Gate Valves Dia. 160 mm | E64: 12 | F64: 0.32 | G64: 36720 | H64: 36720 | I64: =F64 -> 0.32 | AF64: 0.05 | AG64: 0.05 | AH64: 0.05 | AK64: 0.05 | AL64: 0.05 | AM64: 0.05 | AN64: 0.05 | AO64: 0.05 | NN64: 0.01 | NP64: 0.02 | NQ64: 0.02 | NR64: 0.02 | NS64: 0.02 | NT64: 0.02 | NU64: 0.02 | NW64: 0.02 | NX64: 0.02 | NY64: 0.02 | NZ64: 0.02 | OA64: 0.02 | OB64: 0.02 | OD64: 0.02 | OE64: 0.02 | OF64: 0.02 | OG64: 0.02 | OH64: 0.02 | OI64: 0.02 | OL64: 0.02 | OM64: 0.02 | ON64: 0.02 | OO64: 0.02 | OP64: 0.02 | OR64: 0.02 | OS64: 0.02 | OT64: 0.02 | OU64: 0.02 | OV64: 0.02 | OW64: 0.02 | OY64: 0.02 | OZ64: 0.02 | PA64: 0.02 | PB64: 0.02 | PC64: 0.02 | PD64: 0.02 | PF64: 0.02 | PG64: 0.02 | PH64: 0.02 | PI64: 0.02 | PJ64: 0.02 | PK64: 0.02 | PM64: 0.02 | PN64: 0.02 | PO64: 0.02 | PP64: 0.02 | PQ64: 0.02 | PR64: 0.02 | PT64: 0.02 | PY64: 0.02 | QA64: 0.02 | QB64: 0.02 | QC64: 0.02 | QD64: 0.02 | QE64: 0.02 | QF64: 0.02 | QH64: 0.02 | QI64: 0.02 | QJ64: 0.02 | QK64: 0.26 | QL64: 0.96 | QM64: 0.96 | QO64: 0.96 | QP64: 0.79 | QQ64: 0.26 | QR64: 0.26 | QS64: 0.26 | QT64: 0.2 | QV64: 0.02 | QW64: 0.02 | QX64: 0.02 | QY64: 0.02 | QZ64: 0.02 | RA64: 0.02 | RC64: 0.02 | RD64: 0.02 | RE64: 0.02 | RF64: 0.02 | RG64: 0.02 | RH64: 0.16 | RJ64: 0.56 | RK64: 0.46 | RL64: 0.16 | RM64: 0.12 | RN64: 0.02 | RO64: 0.02 | RQ64: 0.06 | RR64: 0.16 | RS64: 0.16 | RT64: 0.16 | RU64: 0.13 | RV64: 0.06 | RX64: 0.06 | RY64: 0.06 | RZ64: 0.05 | SA64: 0.02 | SB64: 0.02 | SC64: 0.02 | SE64: 0.02 | SF64: 0.02 | SG64: 0.02 | SH64: 0.02 | SI64: 0.02 | SJ64: 0.02 | SP64: 0.02 | SQ64: 0.02 | SS64: 0.02 | UM64: 0.09 | UN64: 0.36 | UP64: 0.36 | UQ64: 0.29 | UR64: 0.09 | US64: 0.09 | UT64: 0.07 | YT64: 0.04 | YU64: 0.15 | YV64: 0.15 | YX64: 0.15 | YY64: 0.15 | YZ64: 0.15 | ZA64: 0.15 | ZB64: 0.15 | ZC64: 0.11
A65: Pot Gate Valves Dia. 200 mm | E65: 2 | F65: 0.05 | G65: 8460 | H65: 8460 | I65: =F65 -> 0.05 | AF65: 0.01 | AG65: 0.01 | AH65: 0.01 | AK65: 0.01 | AL65: 0.01 | AM65: 0.01 | AN65: 0.01 | AO65: 0.01 | NN65: 0 | NP65: 0 | NQ65: 0 | NR65: 0 | NS65: 0 | NT65: 0 | NU65: 0 | NW65: 0 | NX65: 0 | NY65: 0 | NZ65: 0 | OA65: 0 | OB65: 0 | OD65: 0 | OE65: 0 | OF65: 0 | OG65: 0 | OH65: 0 | OI65: 0 | OL65: 0 | OM65: 0 | ON65: 0 | OO65: 0 | OP65: 0 | OR65: 0 | OS65: 0 | OT65: 0 | OU65: 0 | OV65: 0 | OW65: 0 | OY65: 0 | OZ65: 0 | PA65: 0 | PB65: 0 | PC65: 0 | PD65: 0 | PF65: 0 | PG65: 0 | PH65: 0 | PI65: 0 | PJ65: 0 | PK65: 0 | PM65: 0 | PN65: 0 | PO65: 0 | PP65: 0 | PQ65: 0 | PR65: 0 | PT65: 0 | PY65: 0 | QA65: 0 | QB65: 0 | QC65: 0 | QD65: 0 | QE65: 0 | QF65: 0 | QH65: 0 | QI65: 0 | QJ65: 0 | QK65: 0 | QL65: 0 | QM65: 0 | QO65: 0 | QP65: 0 | QQ65: 0 | QR65: 0 | QS65: 0 | QT65: 0 | QV65: 0 | QW65: 0 | QX65: 0 | QY65: 0 | QZ65: 0 | RA65: 0 | RC65: 0 | RD65: 0 | RE65: 0 | RF65: 0 | RG65: 0 | RH65: 0 | RJ65: 0 | RK65: 0 | RL65: 0 | RM65: 0 | RN65: 0 | RO65: 0 | RQ65: 0 | RR65: 0 | RS65: 0 | RT65: 0 | RU65: 0.07 | RV65: 0.27 | RX65: 0.27 | RY65: 0.27 | RZ65: 0.22 | SA65: 0.07 | SB65: 0.07 | SC65: 0.07 | SE65: 0.05 | SF65: 0 | SG65: 0 | SH65: 0 | SI65: 0 | SJ65: 0 | SP65: 0 | SQ65: 0 | SS65: 0 | YT65: 0.01 | YU65: 0.03 | YV65: 0.03 | YX65: 0.03 | YY65: 0.03 | YZ65: 0.03 | ZA65: 0.03 | ZB65: 0.03 | ZC65: 0.02
A66: Pot Gate Valves Dia. 225 mm | E66: 3 | F66: 0.08 | G66: 18330 | H66: 18330 | I66: =F66 -> 0.08 | AF66: 0.01 | AG66: 0.01 | AH66: 0.01 | AK66: 0.01 | AL66: 0.01 | AM66: 0.01 | AN66: 0.01 | AO66: 0.01 | NN66: 0 | NP66: 0.01 | NQ66: 0.01 | NR66: 0.01 | NS66: 0.01 | NT66: 0.01 | NU66: 0.01 | NW66: 0.01 | NX66: 0.01 | NY66: 0.01 | NZ66: 0.01 | OA66: 0.01 | OB66: 0.01 | OD66: 0.01 | OE66: 0.01 | OF66: 0.01 | OG66: 0.01 | OH66: 0.01 | OI66: 0.01 | OL66: 0.01 | OM66: 0.01 | ON66: 0.01 | OO66: 0.01 | OP66: 0.01 | OR66: 0 | OS66: 0 | OT66: 0 | OU66: 0 | OV66: 0 | OW66: 0 | OY66: 0 | OZ66: 0 | PA66: 0 | PB66: 0 | PC66: 0 | PD66: 0 | PF66: 0 | PG66: 0 | PH66: 0 | PI66: 0 | PJ66: 0 | PK66: 0 | PM66: 0 | PN66: 0 | PO66: 0 | PP66: 0 | PQ66: 0 | PR66: 0 | PT66: 0 | PY66: 0.01 | QA66: 0.01 | QB66: 0.01 | QC66: 0.01 | QD66: 0.01 | QE66: 0.01 | QF66: 0.01 | QH66: 0.01 | QI66: 0.01 | QJ66: 0.01 | QK66: 0.01 | QL66: 0.01 | QM66: 0.01 | QO66: 0.01 | QP66: 0.01 | QQ66: 0.01 | QR66: 0.01 | QS66: 0.01 | QT66: 0.01 | QV66: 0.01 | QW66: 0.01 | QX66: 0.01 | QY66: 0.01 | QZ66: 0.01 | RA66: 0.01 | RC66: 0.01 | RD66: 0.01 | RE66: 0.01 | RF66: 0.01 | RG66: 0.01 | RH66: 0.01 | RJ66: 0.01 | RK66: 0.14 | RL66: 0.54 | RM66: 0.44 | RN66: 0.14 | RO66: 0.11 | RQ66: 0.01 | RR66: 0.01 | RS66: 0.01 | RT66: 0.01 | RU66: 0.01 | RV66: 0.01 | RX66: 0.01 | RY66: 0.01 | RZ66: 0.01 | SA66: 0.01 | SB66: 0.01 | SC66: 0.01 | SE66: 0.01 | SF66: 0.01 | SG66: 0.01 | SH66: 0.01 | SI66: 0.01 | SJ66: 0.01 | SP66: 0.01 | SQ66: 0.01 | SS66: 0 | TO66: 0.03 | TP66: 0.13 | TQ66: 0.13 | TR66: 0.13 | TS66: 0.11 | TU66: 0.03 | TV66: 0.03 | TW66: 0.03 | TX66: 0.03 | YT66: 0.01 | YU66: 0.04 | YV66: 0.04 | YX66: 0.04 | YY66: 0.04 | YZ66: 0.04 | ZA66: 0.04 | ZB66: 0.04 | ZC66: 0.03
A67: Pot Gate Valves Dia. 250 mm | E67: 3 | F67: 0.08 | G67: 21150 | H67: 21150 | I67: =F67 -> 0.08 | AF67: 0.01 | AG67: 0.01 | AH67: 0.01 | AK67: 0.01 | AL67: 0.01 | AM67: 0.01 | AN67: 0.01 | AO67: 0.01 | NN67: 0 | NP67: 0.01 | NQ67: 0.01 | NR67: 0.01 | NS67: 0.01 | NT67: 0.01 | NU67: 0.01 | NW67: 0.01 | NX67: 0.01 | NY67: 0.01 | NZ67: 0.01 | OA67: 0.01 | OB67: 0.01 | OD67: 0.01 | OE67: 0.01 | OF67: 0.01 | OG67: 0.01 | OH67: 0.01 | OI67: 0.01 | OL67: 0.01 | OM67: 0.01 | ON67: 0.01 | OO67: 0.01 | OP67: 0.01 | OR67: 0 | OS67: 0 | OT67: 0 | OU67: 0 | OV67: 0 | OW67: 0 | OY67: 0 | OZ67: 0 | PA67: 0 | PB67: 0 | PC67: 0 | PD67: 0 | PF67: 0 | PG67: 0 | PH67: 0 | PI67: 0 | PJ67: 0 | PK67: 0 | PM67: 0 | PN67: 0 | PO67: 0 | PP67: 0 | PQ67: 0 | PR67: 0 | PT67: 0 | PY67: 0.01 | QA67: 0.01 | QB67: 0.01 | QC67: 0.01 | QD67: 0.01 | QE67: 0.01 | QF67: 0.01 | QH67: 0.01 | QI67: 0.01 | QJ67: 0.01 | QK67: 0.01 | QL67: 0.01 | QM67: 0.01 | QO67: 0.01 | QP67: 0.01 | QQ67: 0.01 | QR67: 0.01 | QS67: 0.01 | QT67: 0.01 | QV67: 0.01 | QW67: 0.01 | QX67: 0.01 | QY67: 0.01 | QZ67: 0.01 | RA67: 0.01 | RC67: 0.01 | RD67: 0.01 | RE67: 0.01 | RF67: 0.01 | RG67: 0.01 | RH67: 0.01 | RJ67: 0.01 | RK67: 0.01 | RL67: 0.01 | RM67: 0.07 | RN67: 0.27 | RO67: 0.22 | RQ67: 0.07 | RR67: 0.06 | RS67: 0.01 | RT67: 0.01 | RU67: 0.01 | RV67: 0.01 | RX67: 0.01 | RY67: 0.01 | RZ67: 0.07 | SA67: 0.27 | SB67: 0.27 | SC67: 0.27 | SE67: 0.22 | SF67: 0.07 | SG67: 0.07 | SH67: 0.07 | SI67: 0.06 | SJ67: 0.01 | SP67: 0.01 | SQ67: 0.01 | SS67: 0 | YT67: 0.01 | YU67: 0.04 | YV67: 0.04 | YX67: 0.04 | YY67: 0.04 | YZ67: 0.04 | ZA67: 0.04 | ZB67: 0.04 | ZC67: 0.03
A68: Pot Gate Valves Dia. 280 mm | E68: 1 | F68: 0.03 | G68: 8225 | H68: 8225 | I68: =F68 -> 0.03 | AF68: 0 | AG68: 0 | AH68: 0 | AK68: 0 | AL68: 0 | AM68: 0 | AN68: 0 | AO68: 0 | NN68: 0 | NP68: 0 | NQ68: 0 | NR68: 0 | NS68: 0 | NT68: 0 | NU68: 0 | NW68: 0 | NX68: 0 | NY68: 0 | NZ68: 0 | OA68: 0 | OB68: 0 | OD68: 0 | OE68: 0 | OF68: 0 | OG68: 0 | OH68: 0 | OI68: 0 | OL68: 0 | OM68: 0 | ON68: 0 | OO68: 0 | OP68: 0 | OR68: 0 | OS68: 0 | OT68: 0 | OU68: 0 | OV68: 0 | OW68: 0 | OY68: 0 | OZ68: 0 | PA68: 0 | PB68: 0 | PC68: 0 | PD68: 0 | PF68: 0 | PG68: 0 | PH68: 0 | PI68: 0 | PJ68: 0 | PK68: 0 | PM68: 0 | PN68: 0 | PO68: 0 | PP68: 0 | PQ68: 0 | PR68: 0 | PT68: 0 | PY68: 0 | QA68: 0 | QB68: 0 | QC68: 0 | QD68: 0 | QE68: 0 | QF68: 0 | QH68: 0 | QI68: 0 | QJ68: 0 | QK68: 0 | QL68: 0 | QM68: 0 | QO68: 0 | QP68: 0 | QQ68: 0 | QR68: 0 | QS68: 0 | QT68: 0 | QV68: 0 | QW68: 0 | QX68: 0 | QY68: 0 | QZ68: 0 | RA68: 0 | RC68: 0 | RD68: 0 | RE68: 0 | RF68: 0 | RG68: 0 | RH68: 0 | RJ68: 0 | RK68: 0 | RL68: 0 | RM68: 0 | RN68: 0 | RO68: 0 | RQ68: 0 | RR68: 0 | RS68: 0 | RT68: 0 | RU68: 0 | RV68: 0 | RX68: 0 | RY68: 0 | RZ68: 0 | SA68: 0 | SB68: 0 | SC68: 0 | SE68: 0.04 | SF68: 0.14 | SG68: 0.14 | SH68: 0.14 | SI68: 0.11 | SJ68: 0.04 | SP68: 0.04 | SQ68: 0.04 | SS68: 0.03 | YT68: 0 | YU68: 0.01 | YV68: 0.01 | YX68: 0.01 | YY68: 0.01 | YZ68: 0.01 | ZA68: 0.01 | ZB68: 0.01 | ZC68: 0.01
A69: Pot HDPE 160mm 0.0 to 1.5m | E69: 300 | F69: 9 | G69: 96000 | H69: 96000 | I69: =F69 -> 9 | AB69: 1.13 | AD69: 1.13 | AE69: 1.13 | AF69: 1.13 | AG69: 1.13 | AH69: 1.13 | AK69: 1.13 | AL69: 1.13 | NP69: 0.33 | NQ69: 0.67 | NR69: 0.67 | NS69: 0.67 | NT69: 0.67 | NU69: 0.67 | NW69: 0.67 | NX69: 0.67 | NY69: 0.67 | NZ69: 0.67 | OA69: 0.67 | OB69: 0.67 | OD69: 0.67 | OE69: 0.67 | OF69: 0.67 | OG69: 0.67 | OH69: 0.67 | OI69: 0.67 | OL69: 0.67 | OM69: 0.67 | ON69: 0.67 | OO69: 0.67 | OP69: 0.67 | OR69: 0.5 | OS69: 0.5 | OT69: 0.5 | OU69: 0.5 | OV69: 0.5 | OW69: 0.5 | OY69: 0.5 | OZ69: 0.5 | PA69: 0.5 | PB69: 0.5 | PC69: 0.5 | PD69: 0.5 | PF69: 0.5 | PG69: 0.5 | PH69: 0.5 | PI69: 0.5 | PJ69: 0.5 | PK69: 0.5 | PM69: 0.5 | PN69: 0.5 | PO69: 0.5 | PP69: 0.5 | PQ69: 0.5 | PR69: 0.5 | PT69: 0.5 | PY69: 0.67 | QA69: 0.67 | QB69: 0.67 | QC69: 0.67 | QD69: 1.76 | QE69: 5.04 | QF69: 5.04 | QH69: 4.68 | QI69: 3.59 | QJ69: 3.59 | QK69: 5.04 | QL69: 9.42 | QM69: 9.42 | QO69: 9.42 | QP69: 9.42 | QQ69: 7.96 | QR69: 3.59 | QS69: 3.59 | QT69: 3.51 | QV69: 3.29 | QW69: 3.29 | QX69: 3.29 | QY69: 7.55 | QZ69: 15.4 | RA69: 0.67 | RC69: 0.67 | RD69: 2.08 | RE69: 6.34 | RF69: 12.01 | RG69: 29.03 | RH69: 23.36 | RJ69: 6.34 | RK69: 7.05 | RL69: 9.17 | RM69: 7.05 | RN69: 0.67 | RO69: 0.67 | RQ69: 0.67 | RR69: 0.67 | RS69: 0.67 | RT69: 0.67 | RU69: 0.67 | RV69: 0.67 | RX69: 0.67 | RY69: 0.67 | RZ69: 0.67 | SA69: 0.67 | SB69: 0.67 | SC69: 0.5 | YT69: 0.94 | YU69: 3.75 | YV69: 3.75 | YX69: 3.75 | YY69: 3.75 | YZ69: 3.75 | ZA69: 3.75 | ZB69: 3.75 | ZC69: 2.81
A70: Pot HDPE 160mm 1.5 to 3.0m | E70: 2300 | F70: 69 | G70: 1081000 | H70: 1081000 | I70: =F70 -> 69 | AB70: 8.63 | AD70: 8.63 | AE70: 8.63 | AF70: 8.63 | AG70: 8.63 | AH70: 8.63 | AK70: 8.63 | AL70: 8.63 | NP70: 2.56 | NQ70: 5.11 | NR70: 5.11 | NS70: 5.11 | NT70: 5.11 | NU70: 5.11 | NW70: 5.11 | NX70: 5.11 | NY70: 5.11 | NZ70: 5.11 | OA70: 5.11 | OB70: 5.11 | OD70: 5.11 | OE70: 5.11 | OF70: 5.11 | OG70: 5.11 | OH70: 5.11 | OI70: 5.11 | OL70: 5.11 | OM70: 5.11 | ON70: 5.11 | OO70: 5.11 | OP70: 5.11 | OR70: 3.83 | OS70: 3.83 | OT70: 3.83 | OU70: 3.83 | OV70: 3.83 | OW70: 3.83 | OY70: 3.83 | OZ70: 3.83 | PA70: 3.83 | PB70: 3.83 | PC70: 3.83 | PD70: 3.83 | PF70: 3.83 | PG70: 3.83 | PH70: 3.83 | PI70: 3.83 | PJ70: 3.83 | PK70: 3.83 | PM70: 3.83 | PN70: 3.83 | PO70: 3.83 | PP70: 3.83 | PQ70: 3.83 | PR70: 3.83 | PT70: 3.83 | PY70: 5.11 | QA70: 5.11 | QB70: 5.11 | QC70: 5.11 | QD70: 5.11 | QE70: 5.11 | QF70: 5.11 | QH70: 16.49 | QI70: 50.61 | QJ70: 50.61 | QK70: 46.82 | QL70: 35.45 | QM70: 35.45 | QO70: 50.62 | QP70: 96.12 | QQ70: 96.12 | QR70: 96.12 | QS70: 96.12 | QT70: 84.03 | QV70: 47.76 | QW70: 47.76 | QX70: 47 | QY70: 44.73 | QZ70: 49.34 | RA70: 63.19 | RC70: 63.19 | RD70: 56.36 | RE70: 31.27 | RF70: 17.43 | RG70: 16.19 | RH70: 12.5 | RJ70: 12.5 | RK70: 12.5 | RL70: 12.5 | RM70: 10.65 | RN70: 5.11 | RO70: 5.11 | RQ70: 5.11 | RR70: 5.11 | RS70: 5.11 | RT70: 5.11 | RU70: 5.11 | RV70: 5.11 | RX70: 5.11 | RY70: 5.11 | RZ70: 5.11 | SA70: 5.11 | SB70: 5.11 | SC70: 3.83 | SU70: 1.54 | SV70: 6.16 | SW70: 6.16 | SX70: 6.16 | SZ70: 5.65 | TA70: 4.11 | TB70: 4.11 | TC70: 4.11 | TD70: 6.51 | TE70: 13.69 | TG70: 13.69 | TH70: 13.69 | TI70: 13.69 | TJ70: 13.69 | TK70: 11.3 | TL70: 4.11 | TN70: 4.11 | TO70: 4.11 | TP70: 4.11 | TQ70: 4.11 | TR70: 4.11 | TS70: 4.11 | TU70: 4.11 | TV70: 4.11 | TW70: 3.08 | UE70: 2.75 | UF70: 11.02 | UG70: 11.02 | UI70: 13.77 | UJ70: 16.53 | UK70: 13.77 | UL70: 55.09 | UM70: 43.15 | UN70: 7.35 | UP70: 7.35 | UQ70: 7.58 | UR70: 8.26 | US70: 8.26 | UT70: 8.26 | UU70: 6.2 | YT70: 7.19 | YU70: 28.75 | YV70: 28.75 | YX70: 28.75 | YY70: 28.75 | YZ70: 28.75 | ZA70: 28.75 | ZB70: 28.75 | ZC70: 21.56
A71: Pot HDPE 200mm 1.5 to 3.0m | E71: 750 | F71: 22.5 | G71: 412500 | H71: 412500 | I71: =F71 -> 22.5 | AB71: 2.81 | AD71: 2.81 | AE71: 2.81 | AF71: 2.81 | AG71: 2.81 | AH71: 2.81 | AK71: 2.81 | AL71: 2.81 | NP71: 0.83 | NQ71: 1.67 | NR71: 1.67 | NS71: 1.67 | NT71: 1.67 | NU71: 1.67 | NW71: 1.67 | NX71: 1.67 | NY71: 1.67 | NZ71: 1.67 | OA71: 1.67 | OB71: 1.67 | OD71: 1.67 | OE71: 1.67 | OF71: 1.67 | OG71: 1.67 | OH71: 1.67 | OI71: 1.67 | OL71: 1.67 | OM71: 1.67 | ON71: 1.67 | OO71: 1.67 | OP71: 1.67 | OR71: 1.25 | OS71: 1.25 | OT71: 1.25 | OU71: 1.25 | OV71: 1.25 | OW71: 1.25 | OY71: 1.25 | OZ71: 1.25 | PA71: 1.25 | PB71: 1.25 | PC71: 1.25 | PD71: 1.25 | PF71: 1.25 | PG71: 1.25 | PH71: 1.25 | PI71: 1.25 | PJ71: 1.25 | PK71: 1.25 | PM71: 1.25 | PN71: 1.25 | PO71: 1.25 | PP71: 1.25 | PQ71: 1.25 | PR71: 1.25 | PT71: 1.25 | PY71: 1.67 | QA71: 1.67 | QB71: 1.67 | QC71: 1.67 | QD71: 1.67 | QE71: 1.67 | QF71: 1.67 | QH71: 1.67 | QI71: 1.67 | QJ71: 1.67 | QK71: 1.67 | QL71: 1.67 | QM71: 1.67 | QO71: 1.67 | QP71: 1.67 | QQ71: 1.67 | QR71: 1.67 | QS71: 1.67 | QT71: 1.67 | QV71: 1.67 | QW71: 1.67 | QX71: 5.33 | QY71: 16.31 | QZ71: 16.31 | RA71: 16.31 | RC71: 16.31 | RD71: 17.26 | RE71: 19.56 | RF71: 17.94 | RG71: 24.04 | RH71: 42.52 | RJ71: 43.06 | RK71: 43.78 | RL71: 45.94 | RM71: 45.22 | RN71: 36.96 | RO71: 18.75 | RQ71: 19.02 | RR71: 17.73 | RS71: 13.87 | RT71: 13.87 | RU71: 13.87 | RV71: 13.87 | RX71: 13.87 | RY71: 10.82 | RZ71: 1.67 | SA71: 1.67 | SB71: 1.67 | SC71: 1.25 | YT71: 2.34 | YU71: 9.38 | YV71: 9.38 | YX71: 9.38 | YY71: 9.38 | YZ71: 9.38 | ZA71: 9.38 | ZB71: 9.38 | ZC71: 7.03
A72: Pot HDPE 225mm 1.5 to 3.0m | E72: 550 | F72: 16.5 | G72: 324501.3 | H72: 324501.3 | I72: =F72 -> 16.5 | AB72: 2.06 | AD72: 2.06 | AE72: 2.06 | AF72: 2.06 | AG72: 2.06 | AH72: 2.06 | AK72: 2.06 | AL72: 2.06 | NP72: 0.61 | NQ72: 1.22 | NR72: 1.22 | NS72: 1.22 | NT72: 1.22 | NU72: 1.22 | NW72: 1.22 | NX72: 1.22 | NY72: 1.22 | NZ72: 1.22 | OA72: 1.22 | OB72: 1.22 | OD72: 1.22 | OE72: 1.22 | OF72: 1.22 | OG72: 1.22 | OH72: 1.22 | OI72: 1.22 | OL72: 1.22 | OM72: 1.22 | ON72: 1.22 | OO72: 1.22 | OP72: 1.22 | OR72: 0.92 | OS72: 0.92 | OT72: 0.92 | OU72: 0.92 | OV72: 0.92 | OW72: 0.92 | OY72: 0.92 | OZ72: 0.92 | PA72: 0.92 | PB72: 0.92 | PC72: 0.92 | PD72: 0.92 | PF72: 0.92 | PG72: 0.92 | PH72: 0.92 | PI72: 0.92 | PJ72: 0.92 | PK72: 0.92 | PM72: 0.92 | PN72: 0.92 | PO72: 0.92 | PP72: 0.92 | PQ72: 0.92 | PR72: 0.92 | PT72: 0.92 | PY72: 1.22 | QA72: 1.22 | QB72: 1.22 | QC72: 1.22 | QD72: 1.22 | QE72: 1.22 | QF72: 1.22 | QH72: 1.22 | QI72: 1.22 | QJ72: 1.22 | QK72: 1.22 | QL72: 1.22 | QM72: 1.22 | QO72: 1.22 | QP72: 1.22 | QQ72: 1.22 | QR72: 1.22 | QS72: 1.22 | QT72: 1.22 | QV72: 1.22 | QW72: 1.22 | QX72: 1.22 | QY72: 1.22 | QZ72: 1.22 | RA72: 1.22 | RC72: 1.22 | RD72: 1.22 | RE72: 1.22 | RF72: 1.22 | RG72: 1.22 | RH72: 1.22 | RJ72: 1.22 | RK72: 1.22 | RL72: 1.22 | RM72: 1.22 | RN72: 1.22 | RO72: 4.22 | RQ72: 13.2 | RR72: 13.2 | RS72: 13.2 | RT72: 14.19 | RU72: 17.19 | RV72: 33.15 | RX72: 81.05 | RY72: 65.08 | RZ72: 17.19 | SA72: 19.18 | SB72: 25.17 | SC72: 18.88 | SZ72: 0.46 | TA72: 1.84 | TB72: 1.84 | TC72: 1.84 | TD72: 1.79 | TE72: 1.64 | TG72: 1.64 | TH72: 2.46 | TI72: 4.92 | TJ72: 4.92 | TK72: 4.92 | TL72: 4.92 | TN72: 4.1 | TO72: 1.64 | TP72: 1.64 | TQ72: 1.6 | TR72: 1.48 | TS72: 1.48 | TU72: 1.48 | TV72: 1.48 | TW72: 1.11 | YT72: 1.72 | YU72: 6.88 | YV72: 6.88 | YX72: 6.88 | YY72: 6.88 | YZ72: 6.88 | ZA72: 6.88 | ZB72: 6.88 | ZC72: 5.16
A73: Pot HDPE 250mm 1.5 to 3.0m | E73: 850 | F73: 25.5 | G73: 552498.7 | H73: 552498.7 | I73: =F73 -> 25.5 | AB73: 3.19 | AD73: 3.19 | AE73: 3.19 | AF73: 3.19 | AG73: 3.19 | AH73: 3.19 | AK73: 3.19 | AL73: 3.19 | NP73: 0.94 | NQ73: 1.89 | NR73: 1.89 | NS73: 1.89 | NT73: 1.89 | NU73: 1.89 | NW73: 1.89 | NX73: 1.89 | NY73: 1.89 | NZ73: 1.89 | OA73: 1.89 | OB73: 1.89 | OD73: 1.89 | OE73: 1.89 | OF73: 1.89 | OG73: 1.89 | OH73: 1.89 | OI73: 1.89 | OL73: 1.89 | OM73: 1.89 | ON73: 1.89 | OO73: 1.89 | OP73: 1.89 | OR73: 1.42 | OS73: 1.42 | OT73: 1.42 | OU73: 1.42 | OV73: 1.42 | OW73: 1.42 | OY73: 1.42 | OZ73: 1.42 | PA73: 1.42 | PB73: 1.42 | PC73: 1.42 | PD73: 1.42 | PF73: 1.42 | PG73: 1.42 | PH73: 1.42 | PI73: 1.42 | PJ73: 1.42 | PK73: 1.42 | PM73: 1.42 | PN73: 1.42 | PO73: 1.42 | PP73: 1.42 | PQ73: 1.42 | PR73: 1.42 | PT73: 1.42 | PY73: 1.89 | QA73: 1.89 | QB73: 1.89 | QC73: 1.89 | QD73: 1.89 | QE73: 1.89 | QF73: 1.89 | QH73: 1.89 | QI73: 1.89 | QJ73: 1.89 | QK73: 1.89 | QL73: 1.89 | QM73: 1.89 | QO73: 1.89 | QP73: 1.89 | QQ73: 1.89 | QR73: 1.89 | QS73: 1.89 | QT73: 1.89 | QV73: 1.89 | QW73: 1.89 | QX73: 1.89 | QY73: 1.89 | QZ73: 1.89 | RA73: 1.89 | RC73: 1.89 | RD73: 5.23 | RE73: 15.25 | RF73: 15.25 | RG73: 15.25 | RH73: 15.25 | RJ73: 15.62 | RK73: 16.74 | RL73: 16.74 | RM73: 22.3 | RN73: 39.01 | RO73: 39.01 | RQ73: 39.01 | RR73: 39.01 | RS73: 39.01 | RT73: 36.46 | RU73: 28.81 | RV73: 23.25 | RX73: 6.54 | RY73: 10.27 | RZ73: 21.46 | SA73: 27.66 | SB73: 46.27 | SC73: 39.6 | SE73: 16.23 | SF73: 6.98 | SG73: 9.31 | SH73: 6.98 | YT73: 2.66 | YU73: 10.63 | YV73: 10.63 | YX73: 10.63 | YY73: 10.63 | YZ73: 10.63 | ZA73: 10.63 | ZB73: 10.63 | ZC73: 7.97
A74: Pot HDPE 280mm 1.5 to 3.0m | E74: 110 | F74: 3.3 | G74: 79200 | H74: 79200 | I74: =F74 -> 3.3 | AB74: 0.41 | AD74: 0.41 | AE74: 0.41 | AF74: 0.41 | AG74: 0.41 | AH74: 0.41 | AK74: 0.41 | AL74: 0.41 | NP74: 0.12 | NQ74: 0.24 | NR74: 0.24 | NS74: 0.24 | NT74: 0.24 | NU74: 0.24 | NW74: 0.24 | NX74: 0.24 | NY74: 0.24 | NZ74: 0.24 | OA74: 0.24 | OB74: 0.24 | OD74: 0.24 | OE74: 0.24 | OF74: 0.24 | OG74: 0.24 | OH74: 0.24 | OI74: 0.24 | OL74: 0.24 | OM74: 0.24 | ON74: 0.24 | OO74: 0.24 | OP74: 0.24 | OR74: 0.18 | OS74: 0.18 | OT74: 0.18 | OU74: 0.18 | OV74: 0.18 | OW74: 0.18 | OY74: 0.18 | OZ74: 0.18 | PA74: 0.18 | PB74: 0.18 | PC74: 0.18 | PD74: 0.18 | PF74: 0.18 | PG74: 0.18 | PH74: 0.18 | PI74: 0.18 | PJ74: 0.18 | PK74: 0.18 | PM74: 0.18 | PN74: 0.18 | PO74: 0.18 | PP74: 0.18 | PQ74: 0.18 | PR74: 0.18 | PT74: 0.18 | PY74: 0.24 | QA74: 0.24 | QB74: 0.24 | QC74: 0.24 | QD74: 0.24 | QE74: 0.24 | QF74: 0.24 | QH74: 0.24 | QI74: 0.24 | QJ74: 0.24 | QK74: 0.24 | QL74: 0.24 | QM74: 0.24 | QO74: 0.24 | QP74: 0.24 | QQ74: 0.24 | QR74: 0.24 | QS74: 0.24 | QT74: 0.24 | QV74: 0.24 | QW74: 0.24 | QX74: 0.24 | QY74: 0.24 | QZ74: 0.24 | RA74: 0.24 | RC74: 0.24 | RD74: 0.24 | RE74: 0.24 | RF74: 0.24 | RG74: 0.24 | RH74: 0.24 | RJ74: 1.63 | RK74: 5.77 | RL74: 5.31 | RM74: 3.93 | RN74: 7.61 | RO74: 18.67 | RQ74: 14.98 | RR74: 3.93 | RS74: 4.39 | RT74: 5.77 | RU74: 4.39 | RV74: 0.24 | RX74: 0.24 | RY74: 0.24 | RZ74: 0.24 | SA74: 0.24 | SB74: 0.24 | SC74: 0.18 | YT74: 0.34 | YU74: 1.38 | YV74: 1.38 | YX74: 1.38 | YY74: 1.38 | YZ74: 1.38 | ZA74: 1.38 | ZB74: 1.38 | ZC74: 1.03
A75: Pot HDPE 315mm 0.0 to 1.5m | E75: 175 | F75: 5.25 | G75: 112000 | H75: 112000 | I75: =F75 -> 5.25 | AB75: 0.66 | AD75: 0.66 | AE75: 0.66 | AF75: 0.66 | AG75: 0.66 | AH75: 0.66 | AK75: 0.66 | AL75: 0.66 | NP75: 0.19 | NQ75: 0.39 | NR75: 0.39 | NS75: 0.39 | NT75: 0.39 | NU75: 0.39 | NW75: 0.39 | NX75: 0.39 | NY75: 0.39 | NZ75: 0.39 | OA75: 0.39 | OB75: 0.39 | OD75: 0.39 | OE75: 0.39 | OF75: 0.39 | OG75: 0.39 | OH75: 0.39 | OI75: 0.39 | OL75: 0.39 | OM75: 0.39 | ON75: 0.39 | OO75: 0.39 | OP75: 0.39 | OR75: 0.29 | OS75: 0.29 | OT75: 0.29 | OU75: 0.29 | OV75: 0.29 | OW75: 0.29 | OY75: 0.29 | OZ75: 0.29 | PA75: 0.29 | PB75: 0.29 | PC75: 0.29 | PD75: 0.29 | PF75: 0.29 | PG75: 0.29 | PH75: 0.29 | PI75: 0.29 | PJ75: 0.29 | PK75: 0.29 | PM75: 0.29 | PN75: 0.29 | PO75: 0.29 | PP75: 0.29 | PQ75: 0.29 | PR75: 0.29 | PT75: 0.29 | PY75: 0.39 | QA75: 0.39 | QB75: 0.39 | QC75: 0.39 | QD75: 0.39 | QE75: 0.39 | QF75: 0.39 | QH75: 0.39 | QI75: 0.39 | QJ75: 0.39 | QK75: 0.39 | QL75: 0.39 | QM75: 0.39 | QO75: 0.39 | QP75: 0.39 | QQ75: 0.39 | QR75: 0.39 | QS75: 0.39 | QT75: 0.39 | QV75: 0.39 | QW75: 0.39 | QX75: 0.39 | QY75: 0.39 | QZ75: 0.39 | RA75: 0.39 | RC75: 0.39 | RD75: 0.39 | RE75: 0.39 | RF75: 0.39 | RG75: 0.39 | RH75: 0.39 | RJ75: 0.39 | RK75: 0.39 | RL75: 0.39 | RM75: 0.39 | RN75: 0.39 | RO75: 0.39 | RQ75: 0.39 | RR75: 0.39 | RS75: 0.39 | RT75: 0.39 | RU75: 0.39 | RV75: 0.39 | RX75: 0.39 | RY75: 0.39 | RZ75: 0.39 | SA75: 0.39 | SB75: 0.39 | SC75: 0.29 | TD75: 1.1 | TE75: 4.4 | TG75: 4.4 | TH75: 4.4 | TI75: 4.76 | TJ75: 5.86 | TK75: 9.28 | TL75: 19.54 | TN75: 19.54 | TO75: 16.12 | TP75: 5.86 | TQ75: 4.4 | TW75: 1.47 | TX75: 5.86 | TY75: 5.86 | TZ75: 4.4 | YT75: 0.55 | YU75: 2.19 | YV75: 2.19 | YX75: 2.19 | YY75: 2.19 | YZ75: 2.19 | ZA75: 2.19 | ZB75: 2.19 | ZC75: 1.64
A76: Pot Wash out valve with dia (160) mm | E76: 2 | F76: 0.05 | G76: 6200 | H76: 6200 | I76: =F76 -> 0.05 | AF76: 0.01 | AG76: 0.01 | AH76: 0.01 | AK76: 0.01 | AL76: 0.01 | AM76: 0.01 | AN76: 0.01 | AO76: 0.01 | NN76: 0 | NP76: 0 | NQ76: 0 | NR76: 0 | NS76: 0 | NT76: 0 | NU76: 0 | NW76: 0 | NX76: 0 | NY76: 0 | NZ76: 0 | OA76: 0 | OB76: 0 | OD76: 0 | OE76: 0 | OF76: 0 | OG76: 0 | OH76: 0 | OI76: 0 | OL76: 0 | OM76: 0 | ON76: 0 | OO76: 0 | OP76: 0 | OR76: 0 | OS76: 0 | OT76: 0 | OU76: 0 | OV76: 0 | OW76: 0 | OY76: 0 | OZ76: 0 | PA76: 0 | PB76: 0 | PC76: 0 | PD76: 0 | PF76: 0 | PG76: 0 | PH76: 0 | PI76: 0 | PJ76: 0 | PK76: 0 | PM76: 0 | PN76: 0 | PO76: 0 | PP76: 0 | PQ76: 0 | PR76: 0 | PT76: 0 | PY76: 0 | QA76: 0 | QB76: 0 | QC76: 0 | QD76: 0 | QE76: 0 | QF76: 0 | QH76: 0 | QI76: 0 | QJ76: 0 | QK76: 0 | QL76: 0 | QM76: 0.04 | QO76: 0.1 | QP76: 0 | QQ76: 0 | QR76: 0 | QS76: 0 | QT76: 0.02 | QV76: 0.05 | QW76: 0.05 | QX76: 0.05 | QY76: 0.05 | QZ76: 0.05 | RA76: 0.05 | RC76: 0.05 | RD76: 0.05 | RE76: 0.05 | RF76: 0.05 | RG76: 0.05 | RH76: 0.04 | RJ76: 0.03 | RK76: 0.03 | RL76: 0.03 | RM76: 0.03 | RN76: 0.03 | RO76: 0.05 | RQ76: 0.14 | RR76: 0.14 | RS76: 0.14 | RT76: 0.1 | RU76: 0 | RV76: 0 | RX76: 0 | RY76: 0 | RZ76: 0 | SA76: 0 | SB76: 0 | SC76: 0 | SE76: 0 | SF76: 0 | SG76: 0 | SH76: 0 | SI76: 0 | SJ76: 0 | SP76: 0 | SQ76: 0 | SS76: 0 | YT76: 0.01 | YU76: 0.03 | YV76: 0.03 | YX76: 0.03 | YY76: 0.03 | YZ76: 0.03 | ZA76: 0.03 | ZB76: 0.03 | ZC76: 0.02
A77: Pot Wash out valve with dia (200) mm | E77: 1 | F77: 0.03 | G77: 4580 | H77: 4580 | I77: =F77 -> 0.03 | AF77: 0 | AG77: 0 | AH77: 0 | AK77: 0 | AL77: 0 | AM77: 0 | AN77: 0 | AO77: 0 | NN77: 0 | NP77: 0 | NQ77: 0 | NR77: 0 | NS77: 0 | NT77: 0 | NU77: 0 | NW77: 0 | NX77: 0 | NY77: 0 | NZ77: 0 | OA77: 0 | OB77: 0 | OD77: 0 | OE77: 0 | OF77: 0 | OG77: 0 | OH77: 0 | OI77: 0 | OL77: 0 | OM77: 0 | ON77: 0 | OO77: 0 | OP77: 0 | OR77: 0 | OS77: 0 | OT77: 0 | OU77: 0 | OV77: 0 | OW77: 0 | OY77: 0 | OZ77: 0 | PA77: 0 | PB77: 0 | PC77: 0 | PD77: 0 | PF77: 0 | PG77: 0 | PH77: 0 | PI77: 0 | PJ77: 0 | PK77: 0 | PM77: 0 | PN77: 0 | PO77: 0 | PP77: 0 | PQ77: 0 | PR77: 0 | PT77: 0 | PY77: 0 | QA77: 0 | QB77: 0 | QC77: 0 | QD77: 0 | QE77: 0 | QF77: 0 | QH77: 0 | QI77: 0 | QJ77: 0 | QK77: 0 | QL77: 0 | QM77: 0 | QO77: 0 | QP77: 0 | QQ77: 0 | QR77: 0 | QS77: 0 | QT77: 0 | QV77: 0 | QW77: 0 | QX77: 0 | QY77: 0 | QZ77: 0 | RA77: 0 | RC77: 0 | RD77: 0 | RE77: 0 | RF77: 0 | RG77: 0 | RH77: 0 | RJ77: 0 | RK77: 0 | RL77: 0 | RM77: 0 | RN77: 0 | RO77: 0 | RQ77: 0 | RR77: 0 | RS77: 0 | RT77: 0 | RU77: 0.01 | RV77: 0.04 | RX77: 0.04 | RY77: 0.07 | RZ77: 0.07 | SA77: 0.07 | SB77: 0.06 | SC77: 0.04 | SE77: 0.04 | SF77: 0.07 | SG77: 0.07 | SH77: 0.07 | SI77: 0.05 | SJ77: 0 | SP77: 0 | SQ77: 0 | SS77: 0 | YT77: 0 | YU77: 0.01 | YV77: 0.01 | YX77: 0.01 | YY77: 0.01 | YZ77: 0.01 | ZA77: 0.01 | ZB77: 0.01 | ZC77: 0.01
A78: Pot Wash out valve with dia (250) mm | E78: 3 | F78: 0.08 | G78: 21510 | H78: 21510 | I78: =F78 -> 0.08 | AF78: 0.01 | AG78: 0.01 | AH78: 0.01 | AK78: 0.01 | AL78: 0.01 | AM78: 0.01 | AN78: 0.01 | AO78: 0.01 | NN78: 0 | NP78: 0.01 | NQ78: 0.01 | NR78: 0.01 | NS78: 0.01 | NT78: 0.01 | NU78: 0.01 | NW78: 0.01 | NX78: 0.01 | NY78: 0.01 | NZ78: 0.01 | OA78: 0.01 | OB78: 0.01 | OD78: 0.01 | OE78: 0.01 | OF78: 0.01 | OG78: 0.01 | OH78: 0.01 | OI78: 0.01 | OL78: 0.01 | OM78: 0.01 | ON78: 0.01 | OO78: 0.01 | OP78: 0.01 | OR78: 0 | OS78: 0 | OT78: 0 | OU78: 0 | OV78: 0 | OW78: 0 | OY78: 0 | OZ78: 0 | PA78: 0 | PB78: 0 | PC78: 0 | PD78: 0 | PF78: 0 | PG78: 0 | PH78: 0 | PI78: 0 | PJ78: 0 | PK78: 0 | PM78: 0 | PN78: 0 | PO78: 0 | PP78: 0 | PQ78: 0 | PR78: 0 | PT78: 0 | PY78: 0.01 | QA78: 0.01 | QB78: 0.01 | QC78: 0.01 | QD78: 0.01 | QE78: 0.01 | QF78: 0.01 | QH78: 0.01 | QI78: 0.01 | QJ78: 0.01 | QK78: 0.01 | QL78: 0.01 | QM78: 0.01 | QO78: 0.01 | QP78: 0.01 | QQ78: 0.01 | QR78: 0.01 | QS78: 0.01 | QT78: 0.01 | QV78: 0.01 | QW78: 0.01 | QX78: 0.01 | QY78: 0.01 | QZ78: 0.01 | RA78: 0.01 | RC78: 0.01 | RD78: 0.01 | RE78: 0.01 | RF78: 0.01 | RG78: 0.01 | RH78: 0.01 | RJ78: 0.01 | RK78: 0.01 | RL78: 0.01 | RM78: 0.01 | RN78: 0.01 | RO78: 0.01 | RQ78: 0.03 | RR78: 0.03 | RS78: 0.04 | RT78: 0.07 | RU78: 0.07 | RV78: 0.07 | RX78: 0.07 | RY78: 0.07 | RZ78: 0.09 | SA78: 0.17 | SB78: 0.13 | SC78: 0.06 | SE78: 0.14 | SF78: 0.14 | SG78: 0.14 | SH78: 0.12 | SI78: 0.07 | SJ78: 0.12 | SP78: 0.27 | SQ78: 0.21 | SS78: 0 | YT78: 0.01 | YU78: 0.04 | YV78: 0.04 | YX78: 0.04 | YY78: 0.04 | YZ78: 0.04 | ZA78: 0.04 | ZB78: 0.04 | ZC78: 0.03
A79: Riprap | E79: 5000 | F79: 0 | G79: 1300000 | H79: 1300000 | I79: =F79 -> 0 | HE79: 178.57 | HF79: 357.14 | HG79: 357.14 | HH79: 357.14 | HI79: 357.14 | HK79: 357.14 | HL79: 357.14 | HM79: 357.14 | HN79: 357.14 | HO79: 357.14 | HP79: 357.14 | HR79: 357.14 | HS79: 357.14 | HT79: 357.14 | HU79: 178.57
A80: Sewer Dia 200 mm; Depth : 1.5m - 2.5m | E80: 600 | F80: 18 | G80: 282000 | H80: 282000 | I80: =F80 -> 18 | AF80: 2.25 | AG80: 2.25 | AH80: 2.25 | AK80: 2.25 | AL80: 2.25 | AM80: 2.25 | AN80: 2.25 | AO80: 2.25 | JO80: 0.67 | JP80: 1.33 | JQ80: 1.33 | JR80: 1.33 | JS80: 1.33 | JT80: 1.33 | JV80: 1.33 | JW80: 1.33 | JX80: 1.33 | JY80: 1.33 | JZ80: 1.33 | KA80: 1.33 | KC80: 1.33 | KD80: 1.33 | KE80: 1.33 | KF80: 1.33 | KG80: 1.33 | KH80: 1.33 | KJ80: 1.33 | KK80: 1.33 | KL80: 1.33 | KM80: 1.33 | KN80: 1.33 | KO80: 1.33 | KQ80: 1.33 | KR80: 1.33 | KS80: 1.93 | KT80: 2.54 | KU80: 2.54 | KV80: 2.54 | KX80: 2.54 | KY80: 2.54 | KZ80: 2.23 | LA80: 1.93 | LB80: 1.93 | LC80: 1.93 | LE80: 1.93 | LF80: 1.93 | LG80: 2.83 | LH80: 3.74 | LI80: 3.74 | LJ80: 3.74 | LL80: 3.74 | LM80: 3.74 | LN80: 2.53 | LO80: 1.33 | LP80: 1.33 | LQ80: 1.33 | LS80: 1.33 | LT80: 1.33 | LU80: 1.33 | LV80: 1.33 | LW80: 1.33 | LX80: 1.33 | LZ80: 1.33 | MA80: 1.63 | MB80: 1.93 | MC80: 1.93 | MD80: 1.93 | ME80: 1.93 | MG80: 1.93 | MH80: 2.23 | MI80: 2.54 | MJ80: 2.54 | MK80: 2.54 | ML80: 2.54 | MN80: 2.54 | MO80: 1.93 | MP80: 1.33 | MQ80: 1.33 | MR80: 1.33 | MS80: 1.33 | MU80: 1.33 | MV80: 1.33 | MW80: 1.33 | MX80: 1.33 | MY80: 1.33 | MZ80: 1.33 | NB80: 1.33 | NC80: 1.33 | ND80: 1.33 | NE80: 1.33 | NF80: 1.33 | NG80: 1.33 | NI80: 1.33 | NJ80: 1.33 | NK80: 1.33 | NL80: 1.33 | NM80: 1.33 | NN80: 1.33 | NP80: 4.73 | NQ80: 8.13 | NR80: 8.13 | NS80: 8.13 | NT80: 8.13 | NU80: 8.13 | NW80: 8.13 | NX80: 8.13 | NY80: 8.13 | NZ80: 7.12 | OA80: 6.1 | OB80: 6.1 | OD80: 6.1 | OE80: 6.1 | OF80: 6.1 | OG80: 13.51 | OH80: 20.91 | OI80: 20.91 | OL80: 20.91 | OM80: 20.91 | ON80: 20.91 | OO80: 20.91 | OP80: 10.46 | PC80: 4.58 | PD80: 4.58 | PF80: 4.58 | PG80: 4.58 | PH80: 4.58 | PI80: 4.58 | PJ80: 4.58 | PK80: 4.58 | PM80: 7.84 | PN80: 7.84 | PO80: 7.84 | PP80: 7.84 | PQ80: 7.84 | PR80: 7.84 | PT80: 7.84 | PY80: 10.46 | QA80: 7.84 | YK80: 1.88 | YL80: 7.5 | YM80: 7.5 | YN80: 7.5 | YO80: 7.5 | YQ80: 7.5 | YR80: 7.5 | YS80: 7.5 | YT80: 5.63
A81: Sewer Dia 250 mm; Depth : 1.5m - 2.5m | E81: 715 | F81: 21.45 | G81: 357500 | H81: 357500 | I81: =F81 -> 21.45 | AF81: 2.68 | AG81: 2.68 | AH81: 2.68 | AK81: 2.68 | AL81: 2.68 | AM81: 2.68 | AN81: 2.68 | AO81: 2.68 | JO81: 0.79 | JP81: 1.59 | JQ81: 1.59 | JR81: 1.59 | JS81: 1.59 | JT81: 1.59 | JV81: 1.59 | JW81: 1.59 | JX81: 1.59 | JY81: 1.59 | JZ81: 1.59 | KA81: 1.59 | KC81: 1.59 | KD81: 1.59 | KE81: 1.59 | KF81: 1.59 | KG81: 1.59 | KH81: 1.59 | KJ81: 1.59 | KK81: 1.59 | KL81: 1.59 | KM81: 1.59 | KN81: 1.59 | KO81: 1.59 | KQ81: 1.59 | KR81: 1.59 | KS81: 1.59 | KT81: 1.59 | KU81: 1.59 | KV81: 1.59 | KX81: 1.59 | KY81: 1.59 | KZ81: 1.59 | LA81: 1.59 | LB81: 1.59 | LC81: 1.59 | LE81: 1.59 | LF81: 1.59 | LG81: 1.59 | LH81: 2.69 | LI81: 3.79 | LJ81: 3.79 | LL81: 3.79 | LM81: 3.79 | LN81: 3.79 | LO81: 3.36 | LP81: 2.93 | LQ81: 2.93 | LS81: 2.93 | LT81: 2.93 | LU81: 4.17 | LV81: 5.41 | LW81: 5.41 | LX81: 5.41 | LZ81: 5.41 | MA81: 5.41 | MB81: 5.41 | MC81: 3.5 | MD81: 1.59 | ME81: 1.59 | MG81: 1.59 | MH81: 1.59 | MI81: 1.59 | MJ81: 1.59 | MK81: 2.07 | ML81: 2.54 | MN81: 2.54 | MO81: 2.54 | MP81: 2.54 | MQ81: 2.54 | MR81: 2.54 | MS81: 2.07 | MU81: 1.59 | MV81: 1.59 | MW81: 1.59 | MX81: 2.69 | MY81: 3.79 | MZ81: 3.79 | NB81: 3.79 | NC81: 3.79 | ND81: 3.79 | NE81: 2.69 | NF81: 1.59 | NG81: 1.59 | NI81: 1.59 | NJ81: 1.59 | NK81: 1.59 | NL81: 1.59 | NM81: 1.59 | NN81: 1.59 | NP81: 0.79 | NZ81: 4.59 | OA81: 9.17 | OB81: 9.17 | OD81: 9.17 | OE81: 9.17 | OF81: 9.17 | OG81: 9.17 | OH81: 9.17 | OI81: 9.17 | OL81: 8.02 | OM81: 6.87 | ON81: 6.87 | OO81: 6.87 | OP81: 6.87 | OR81: 5.15 | OS81: 5.15 | OT81: 17.69 | OU81: 17.69 | OV81: 17.69 | OW81: 17.69 | OY81: 17.69 | OZ81: 17.69 | PA81: 17.69 | PB81: 17.69 | PC81: 17.69 | PD81: 10.02 | PF81: 6.18 | PG81: 6.18 | PH81: 6.18 | PI81: 6.18 | PJ81: 6.18 | PK81: 6.18 | PM81: 8.84 | PN81: 8.84 | PO81: 8.84 | PP81: 8.84 | PQ81: 8.84 | PR81: 8.84 | PT81: 8.84 | PY81: 11.79 | QA81: 8.84 | YK81: 2.23 | YL81: 8.94 | YM81: 8.94 | YN81: 8.94 | YO81: 8.94 | YQ81: 8.94 | YR81: 8.94 | YS81: 8.94 | YT81: 6.7
A82: Sewer Dia 315 mm; Depth : 2.5m - 3.5m | E82: 950 | F82: 28.5 | G82: 631750 | H82: 631750 | I82: =F82 -> 28.5 | AF82: 3.56 | AG82: 3.56 | AH82: 3.56 | AK82: 3.56 | AL82: 3.56 | AM82: 3.56 | AN82: 3.56 | AO82: 3.56 | JF82: 1.9 | JH82: 3.81 | JI82: 3.81 | JJ82: 3.81 | JK82: 3.81 | JL82: 3.81 | JM82: 3.81 | JO82: 4.86 | JP82: 5.92 | JQ82: 5.92 | JR82: 5.92 | JS82: 5.18 | JT82: 4.44 | JV82: 4.44 | JW82: 4.44 | JX82: 4.44 | JY82: 4.44 | JZ82: 4.44 | KA82: 4.44 | KC82: 4.44 | KD82: 9.25 | KE82: 14.07 | KF82: 14.07 | KG82: 14.07 | KH82: 14.07 | KJ82: 14.07 | KK82: 14.07 | KL82: 8.09 | KM82: 2.11 | KN82: 2.11 | KO82: 2.11 | KQ82: 2.11 | KR82: 2.11 | KS82: 2.11 | KT82: 2.11 | KU82: 2.11 | KV82: 2.11 | KX82: 2.11 | KY82: 2.11 | KZ82: 4.2 | LA82: 6.3 | LB82: 6.3 | LC82: 6.3 | LE82: 6.3 | LF82: 6.3 | LG82: 7.46 | LH82: 7.75 | LI82: 6.88 | LJ82: 6.88 | LL82: 6.88 | LM82: 6.88 | LN82: 6.88 | LO82: 11.44 | LP82: 16 | LQ82: 16.74 | LS82: 17.48 | LT82: 17.48 | LU82: 17.48 | LV82: 12.59 | LW82: 7.34 | LX82: 6.96 | LZ82: 6.96 | MA82: 6.96 | MB82: 6.96 | MC82: 6.96 | MD82: 6.63 | ME82: 6.3 | MG82: 6.3 | MH82: 6.3 | MI82: 7.52 | MJ82: 8.74 | MK82: 6.65 | ML82: 4.55 | MN82: 4.55 | MO82: 4.55 | MP82: 5.42 | MQ82: 6.3 | MR82: 6.3 | MS82: 6.3 | MU82: 6.3 | MV82: 6.3 | MW82: 6.3 | MX82: 4.2 | MY82: 2.63 | MZ82: 3.16 | NB82: 3.16 | NC82: 3.16 | ND82: 3.16 | NE82: 3.16 | NF82: 3.53 | NG82: 3.91 | NI82: 3.91 | NJ82: 3.91 | NK82: 3.91 | NL82: 3.91 | NM82: 3.91 | NN82: 3.01 | NP82: 1.06 | OL82: 2.72 | OM82: 5.45 | ON82: 5.45 | OO82: 5.45 | OP82: 5.45 | OR82: 4.09 | OS82: 4.09 | OT82: 4.09 | OU82: 4.09 | OV82: 3.81 | OW82: 3.27 | OY82: 3.27 | OZ82: 3.27 | PA82: 3.27 | PB82: 3.27 | PC82: 3.27 | PD82: 8.35 | PF82: 10.9 | PG82: 10.9 | PH82: 10.9 | PI82: 10.9 | PJ82: 10.9 | PK82: 10.9 | PM82: 10.9 | PN82: 5.81 | PO82: 3.27 | PP82: 3.27 | PQ82: 3.27 | PR82: 3.27 | PT82: 3.27 | PY82: 5.08 | QA82: 7.27 | QB82: 7.27 | QC82: 7.27 | QD82: 7.27 | QE82: 7.27 | QF82: 5.45 | YK82: 2.97 | YL82: 11.88 | YM82: 11.88 | YN82: 11.88 | YO82: 11.88 | YQ82: 11.88 | YR82: 11.88 | YS82: 11.88 | YT82: 8.91
A83: Sewer Dia 315 mm; Depth : 3.5m - 4.5m | E83: 1150 | F83: 34.5 | G83: 920000 | H83: 920000 | I83: =F83 -> 34.5 | AF83: 4.31 | AG83: 4.31 | AH83: 4.31 | AK83: 4.31 | AL83: 4.31 | AM83: 4.31 | AN83: 4.31 | AO83: 4.31 | JO83: 1.28 | JP83: 2.56 | JQ83: 2.56 | JR83: 2.56 | JS83: 8.06 | JT83: 13.56 | JV83: 13.56 | JW83: 13.56 | JX83: 13.56 | JY83: 13.56 | JZ83: 13.56 | KA83: 13.56 | KC83: 13.56 | KD83: 13.56 | KE83: 13.56 | KF83: 13.56 | KG83: 13.56 | KH83: 13.56 | KJ83: 12.87 | KK83: 12.19 | KL83: 12.19 | KM83: 12.19 | KN83: 12.19 | KO83: 12.19 | KQ83: 12.19 | KR83: 12.19 | KS83: 24.49 | KT83: 36.8 | KU83: 36.8 | KV83: 36.8 | KX83: 36.8 | KY83: 36.8 | KZ83: 36.8 | LA83: 36.8 | LB83: 36.8 | LC83: 19.68 | LE83: 2.56 | LF83: 2.56 | LG83: 6.84 | LH83: 11.12 | LI83: 11.12 | LJ83: 11.12 | LL83: 11.12 | LM83: 11.12 | LN83: 11.12 | LO83: 11.12 | LP83: 11.12 | LQ83: 13.84 | LS83: 16.56 | LT83: 16.56 | LU83: 16.56 | LV83: 16.56 | LW83: 16.56 | LX83: 16.56 | LZ83: 16.56 | MA83: 16.56 | MB83: 16.56 | MC83: 16.56 | MD83: 9.56 | ME83: 2.56 | MG83: 2.56 | MH83: 2.56 | MI83: 2.56 | MJ83: 2.56 | MK83: 2.56 | ML83: 2.56 | MN83: 2.56 | MO83: 2.56 | MP83: 2.56 | MQ83: 2.56 | MR83: 2.56 | MS83: 2.56 | MU83: 2.56 | MV83: 2.56 | MW83: 2.56 | MX83: 2.56 | MY83: 2.56 | MZ83: 2.56 | NB83: 2.56 | NC83: 2.56 | ND83: 2.56 | NE83: 2.56 | NF83: 2.56 | NG83: 2.56 | NI83: 2.56 | NJ83: 2.56 | NK83: 2.56 | NL83: 2.56 | NM83: 2.56 | NN83: 2.56 | NP83: 1.28 | YK83: 3.59 | YL83: 14.38 | YM83: 14.38 | YN83: 14.38 | YO83: 14.38 | YQ83: 14.38 | YR83: 14.38 | YS83: 14.38 | YT83: 10.78
A84: Sewer Dia 315 mm; Depth : 4.5m - 5.5m | E84: 15 | F84: 0.45 | G84: 13725 | H84: 13725 | I84: =F84 -> 0.45 | AF84: 0.06 | AG84: 0.06 | AH84: 0.06 | AK84: 0.06 | AL84: 0.06 | AM84: 0.06 | AN84: 0.06 | AO84: 0.06 | JO84: 0.02 | JP84: 0.03 | JQ84: 0.03 | JR84: 0.03 | JS84: 0.03 | JT84: 0.03 | JV84: 0.03 | JW84: 0.03 | JX84: 0.03 | JY84: 0.03 | JZ84: 0.03 | KA84: 0.03 | KC84: 0.03 | KD84: 0.03 | KE84: 0.03 | KF84: 0.03 | KG84: 0.03 | KH84: 0.03 | KJ84: 0.16 | KK84: 0.28 | KL84: 0.28 | KM84: 0.28 | KN84: 0.28 | KO84: 0.28 | KQ84: 0.28 | KR84: 0.28 | KS84: 0.24 | KT84: 0.2 | KU84: 0.2 | KV84: 0.2 | KX84: 0.2 | KY84: 0.2 | KZ84: 0.37 | LA84: 0.54 | LB84: 0.54 | LC84: 0.54 | LE84: 0.54 | LF84: 0.54 | LG84: 0.54 | LH84: 0.54 | LI84: 0.36 | LJ84: 0.18 | LL84: 0.18 | LM84: 0.18 | LN84: 0.18 | LO84: 0.18 | LP84: 0.18 | LQ84: 0.25 | LS84: 0.32 | LT84: 0.32 | LU84: 0.32 | LV84: 0.32 | LW84: 0.32 | LX84: 0.32 | LZ84: 0.18 | MA84: 0.03 | MB84: 0.03 | MC84: 0.03 | MD84: 0.03 | ME84: 0.03 | MG84: 0.03 | MH84: 0.03 | MI84: 0.03 | MJ84: 0.03 | MK84: 0.03 | ML84: 0.03 | MN84: 0.03 | MO84: 0.03 | MP84: 0.03 | MQ84: 0.03 | MR84: 0.03 | MS84: 0.03 | MU84: 0.03 | MV84: 0.03 | MW84: 0.03 | MX84: 0.03 | MY84: 0.03 | MZ84: 0.03 | NB84: 0.03 | NC84: 0.03 | ND84: 0.03 | NE84: 0.03 | NF84: 0.03 | NG84: 0.03 | NI84: 0.03 | NJ84: 0.03 | NK84: 0.03 | NL84: 0.03 | NM84: 0.03 | NN84: 0.03 | NP84: 0.02 | YK84: 0.05 | YL84: 0.19 | YM84: 0.19 | YN84: 0.19 | YO84: 0.19 | YQ84: 0.19 | YR84: 0.19 | YS84: 0.19 | YT84: 0.14
A85: Sewer Dia 400 mm; Depth : 3.5m - 4.5m | E85: 420 | F85: 12.6 | G85: 390600 | H85: 390600 | I85: =F85 -> 12.6 | AF85: 1.58 | AG85: 1.58 | AH85: 1.58 | AK85: 1.58 | AL85: 1.58 | AM85: 1.58 | AN85: 1.58 | AO85: 1.58 | JO85: 0.47 | JP85: 0.93 | JQ85: 0.93 | JR85: 0.93 | JS85: 0.93 | JT85: 0.93 | JV85: 0.93 | JW85: 0.93 | JX85: 0.93 | JY85: 0.93 | JZ85: 0.93 | KA85: 0.93 | KC85: 0.93 | KD85: 0.93 | KE85: 0.93 | KF85: 0.93 | KG85: 0.93 | KH85: 0.93 | KJ85: 0.93 | KK85: 0.93 | KL85: 0.93 | KM85: 0.93 | KN85: 0.93 | KO85: 0.93 | KQ85: 0.93 | KR85: 0.93 | KS85: 3.28 | KT85: 5.62 | KU85: 5.62 | KV85: 5.62 | KX85: 5.62 | KY85: 5.62 | KZ85: 5.62 | LA85: 5.62 | LB85: 5.62 | LC85: 5.62 | LE85: 5.62 | LF85: 5.62 | LG85: 5.62 | LH85: 5.62 | LI85: 5.62 | LJ85: 5.62 | LL85: 5.62 | LM85: 5.62 | LN85: 11.32 | LO85: 17.01 | LP85: 17.01 | LQ85: 17.01 | LS85: 17.01 | LT85: 17.01 | LU85: 17.01 | LV85: 10.73 | LW85: 4.45 | LX85: 4.45 | LZ85: 4.45 | MA85: 4.45 | MB85: 4.45 | MC85: 4.45 | MD85: 4.45 | ME85: 5.82 | MG85: 7.19 | MH85: 7.19 | MI85: 7.19 | MJ85: 7.19 | MK85: 7.19 | ML85: 7.19 | MN85: 7.19 | MO85: 7.19 | MP85: 4.06 | MQ85: 0.93 | MR85: 0.93 | MS85: 0.93 | MU85: 0.93 | MV85: 0.93 | MW85: 0.93 | MX85: 0.93 | MY85: 0.93 | MZ85: 0.93 | NB85: 0.93 | NC85: 0.93 | ND85: 0.93 | NE85: 0.93 | NF85: 0.93 | NG85: 0.93 | NI85: 0.93 | NJ85: 0.93 | NK85: 0.93 | NL85: 0.93 | NM85: 0.93 | NN85: 0.93 | NP85: 0.47 | YK85: 1.31 | YL85: 5.25 | YM85: 5.25 | YN85: 5.25 | YO85: 5.25 | YQ85: 5.25 | YR85: 5.25 | YS85: 5.25 | YT85: 3.94
A86: Sewer Dia 400 mm; Depth : 4.5m - 5.5m | E86: 375 | F86: 11.25 | G86: 397500 | H86: 397500 | I86: =F86 -> 11.25 | AF86: 1.41 | AG86: 1.41 | AH86: 1.41 | AK86: 1.41 | AL86: 1.41 | AM86: 1.41 | AN86: 1.41 | AO86: 1.41 | JO86: 0.42 | JP86: 0.83 | JQ86: 0.83 | JR86: 0.83 | JS86: 0.83 | JT86: 0.83 | JV86: 0.83 | JW86: 0.83 | JX86: 0.83 | JY86: 0.83 | JZ86: 0.83 | KA86: 0.83 | KC86: 0.83 | KD86: 0.83 | KE86: 0.83 | KF86: 0.83 | KG86: 0.83 | KH86: 0.83 | KJ86: 0.83 | KK86: 0.83 | KL86: 0.83 | KM86: 0.83 | KN86: 0.83 | KO86: 0.83 | KQ86: 0.83 | KR86: 0.83 | KS86: 0.83 | KT86: 0.83 | KU86: 0.83 | KV86: 0.83 | KX86: 0.83 | KY86: 0.83 | KZ86: 0.83 | LA86: 0.83 | LB86: 0.83 | LC86: 0.83 | LE86: 0.83 | LF86: 0.83 | LG86: 0.83 | LH86: 0.83 | LI86: 0.83 | LJ86: 0.83 | LL86: 0.83 | LM86: 0.83 | LN86: 0.83 | LO86: 0.83 | LP86: 0.83 | LQ86: 0.83 | LS86: 0.83 | LT86: 0.83 | LU86: 0.83 | LV86: 0.83 | LW86: 0.83 | LX86: 0.83 | LZ86: 0.83 | MA86: 0.83 | MB86: 0.83 | MC86: 0.83 | MD86: 0.83 | ME86: 0.83 | MG86: 0.83 | MH86: 0.83 | MI86: 0.83 | MJ86: 0.83 | MK86: 0.83 | ML86: 0.83 | MN86: 0.83 | MO86: 0.83 | MP86: 0.83 | MQ86: 0.83 | MR86: 0.83 | MS86: 0.83 | MU86: 0.83 | MV86: 0.83 | MW86: 0.83 | MX86: 0.83 | MY86: 0.83 | MZ86: 2.93 | NB86: 5.02 | NC86: 5.02 | ND86: 5.02 | NE86: 5.02 | NF86: 5.02 | NG86: 5.02 | NI86: 5.02 | NJ86: 5.02 | NK86: 5.02 | NL86: 5.02 | NM86: 5.02 | NN86: 4.72 | NP86: 4.01 | NQ86: 3.59 | NR86: 3.59 | NS86: 3.59 | NT86: 3.59 | NU86: 3.59 | NW86: 8.97 | NX86: 14.36 | NY86: 14.36 | NZ86: 14.36 | OA86: 14.36 | OB86: 14.36 | OD86: 14.36 | OE86: 7.18 | PA86: 0.79 | PB86: 2.36 | PC86: 2.36 | PD86: 2.36 | PF86: 2.36 | PG86: 2.36 | PH86: 2.36 | PI86: 2.36 | PJ86: 2.36 | PK86: 2.36 | PM86: 2.36 | PN86: 3.58 | PO86: 4.19 | PP86: 4.19 | PQ86: 4.19 | PR86: 4.19 | PT86: 4.19 | PY86: 5.58 | QA86: 5.58 | QB86: 5.58 | QC86: 5.58 | QD86: 4.19 | YK86: 1.17 | YL86: 4.69 | YM86: 4.69 | YN86: 4.69 | YO86: 4.69 | YQ86: 4.69 | YR86: 4.69 | YS86: 4.69 | YT86: 3.52
A87: Sewer Manhole Dia 1200 mm, Depth: 1.5 - 2.5m | E87: 22 | F87: 0 | G87: 325600 | H87: 325600 | I87: =F87 -> 0 | AK87: 0.08 | AL87: 0.08 | AM87: 0.08 | AN87: 0.08 | AO87: 0.08 | AP87: 0.08 | AR87: 0.08 | AS87: 0.08 | KC87: 0.11 | KD87: 0.22 | KE87: 0.22 | KF87: 0.22 | KG87: 0.22 | KH87: 0.22 | KJ87: 0.22 | KK87: 0.22 | KL87: 0.22 | KM87: 0.22 | KN87: 0.22 | KO87: 0.22 | KQ87: 0.22 | KR87: 0.22 | KS87: 0.22 | KT87: 0.22 | KU87: 0.22 | KV87: 0.22 | KX87: 0.35 | KY87: 0.48 | KZ87: 0.48 | LA87: 0.48 | LB87: 0.48 | LC87: 0.48 | LE87: 0.48 | LF87: 0.48 | LG87: 0.48 | LH87: 0.32 | LI87: 0.16 | LJ87: 0.16 | LL87: 0.16 | LM87: 0.16 | LN87: 0.16 | LO87: 0.16 | LP87: 0.16 | LQ87: 0.16 | LS87: 0.15 | LT87: 0.14 | LU87: 0.14 | LV87: 0.14 | LW87: 0.14 | LX87: 0.14 | LZ87: 0.14 | MA87: 0.14 | MB87: 0.14 | MC87: 0.14 | MD87: 0.14 | ME87: 0.09 | MG87: 0.05 | MH87: 0.05 | MI87: 0.05 | MJ87: 0.05 | MK87: 0.05 | ML87: 0.05 | MN87: 0.05 | MO87: 0.05 | MP87: 0.05 | MQ87: 0.05 | MR87: 0.05 | MS87: 0.05 | MU87: 0.05 | MV87: 0.05 | MW87: 0.05 | MX87: 0.05 | MY87: 0.05 | MZ87: 0.05 | NB87: 0.05 | NC87: 0.05 | ND87: 0.05 | NE87: 0.05 | NF87: 0.05 | NG87: 0.05 | NI87: 0.05 | NJ87: 0.05 | NK87: 0.05 | NL87: 0.05 | NM87: 0.05 | NN87: 0.05 | NP87: 0.05 | NQ87: 0.05 | NR87: 0.05 | NS87: 0.05 | NT87: 0.05 | NU87: 0.05 | NW87: 0.05 | NX87: 0.05 | NY87: 0.05 | NZ87: 0.05 | OA87: 0.05 | OB87: 0.05 | OD87: 0.05 | OE87: 0.05 | OF87: 0.05 | OG87: 0.05 | OH87: 0.12 | OI87: 0.19 | OL87: 0.19 | OM87: 0.19 | ON87: 0.19 | OO87: 0.19 | OP87: 0.19 | OR87: 0.16 | OS87: 0.19 | OT87: 0.19 | OU87: 0.19 | OV87: 0.19 | OW87: 0.19 | OY87: 0.19 | OZ87: 0.29 | PA87: 0.34 | PB87: 0.34 | PC87: 0.3 | PD87: 0.3 | PF87: 0.3 | PG87: 0.3 | PH87: 0.08 | PI87: 0.08 | PJ87: 0.08 | PK87: 0.08 | PM87: 0.08 | PN87: 0.08 | PO87: 0.08 | PP87: 0.08 | PQ87: 0.08 | PR87: 0.08 | PT87: 0.08 | PY87: 0.1 | QA87: 0.08 | YK87: 0.07 | YL87: 0.28 | YM87: 0.28 | YN87: 0.28 | YO87: 0.28 | YQ87: 0.28 | YR87: 0.28 | YS87: 0.28 | YT87: 0.21
A88: Sewer Manhole Dia 1200 mm, Depth: 2.5 - 3.5m | E88: 27 | F88: 0 | G88: 617760 | H88: 617760 | I88: =F88 -> 0 | AK88: 0.1 | AL88: 0.1 | AM88: 0.1 | AN88: 0.1 | AO88: 0.1 | AP88: 0.1 | AR88: 0.1 | AS88: 0.1 | KM88: 0.04 | KN88: 0.09 | KO88: 0.09 | KQ88: 0.09 | KR88: 0.09 | KS88: 0.09 | KT88: 0.09 | KU88: 0.09 | KV88: 0.09 | KX88: 0.12 | KY88: 0.16 | KZ88: 0.16 | LA88: 0.16 | LB88: 0.16 | LC88: 0.16 | LE88: 0.16 | LF88: 0.16 | LG88: 0.22 | LH88: 0.3 | LI88: 0.32 | LJ88: 0.32 | LL88: 0.32 | LM88: 0.32 | LN88: 0.32 | LO88: 0.25 | LP88: 0.2 | LQ88: 0.2 | LS88: 0.2 | LT88: 0.2 | LU88: 0.2 | LV88: 0.23 | LW88: 0.26 | LX88: 0.26 | LZ88: 0.26 | MA88: 0.26 | MB88: 0.22 | MC88: 0.18 | MD88: 0.21 | ME88: 0.23 | MG88: 0.2 | MH88: 0.17 | MI88: 0.17 | MJ88: 0.17 | MK88: 0.14 | ML88: 0.1 | MN88: 0.09 | MO88: 0.09 | MP88: 0.09 | MQ88: 0.08 | MR88: 0.08 | MS88: 0.08 | MU88: 0.08 | MV88: 0.08 | MW88: 0.08 | MX88: 0.07 | MY88: 0.06 | MZ88: 0.06 | NB88: 0.06 | NC88: 0.06 | ND88: 0.06 | NE88: 0.06 | NF88: 0.06 | NG88: 0.06 | NI88: 0.06 | NJ88: 0.06 | NK88: 0.06 | NL88: 0.06 | NM88: 0.06 | NN88: 0.06 | NP88: 0.06 | NQ88: 0.06 | NR88: 0.06 | NS88: 0.06 | NT88: 0.06 | NU88: 0.06 | NW88: 0.06 | NX88: 0.06 | NY88: 0.06 | NZ88: 0.06 | OA88: 0.06 | OB88: 0.06 | OD88: 0.06 | OE88: 0.06 | OF88: 0.06 | OG88: 0.06 | OH88: 0.06 | OI88: 0.06 | OL88: 0.06 | OM88: 0.06 | ON88: 0.06 | OO88: 0.06 | OP88: 0.06 | OR88: 0.05 | OS88: 0.05 | OT88: 0.05 | OU88: 0.05 | OV88: 0.05 | OW88: 0.05 | OY88: 0.05 | OZ88: 0.05 | PA88: 0.05 | PB88: 0.05 | PC88: 0.22 | PD88: 0.22 | PF88: 0.22 | PG88: 0.22 | PH88: 0.22 | PI88: 0.22 | PJ88: 0.22 | PK88: 0.22 | PM88: 0.22 | PN88: 0.22 | PO88: 0.26 | PP88: 0.35 | PQ88: 0.35 | PR88: 0.35 | PT88: 0.35 | PY88: 0.47 | QA88: 0.58 | QB88: 0.93 | QC88: 0.93 | QD88: 0.93 | QE88: 0.93 | QF88: 0.74 | QH88: 0.17 | QI88: 0.17 | QJ88: 0.17 | QK88: 0.17 | QL88: 0.17 | QM88: 0.17 | QO88: 0.18 | QP88: 0.23 | QQ88: 0.23 | QR88: 0.23 | QS88: 0.23 | QT88: 0.17 | YK88: 0.08 | YL88: 0.34 | YM88: 0.34 | YN88: 0.34 | YO88: 0.34 | YQ88: 0.34 | YR88: 0.34 | YS88: 0.34 | YT88: 0.25
A89: Sewer Manhole Dia 1200 mm, Depth: 3.5 - 4.5m | E89: 7 | F89: 0 | G89: 226800 | H89: 226800 | I89: =F89 -> 0 | AK89: 0.03 | AL89: 0.03 | AM89: 0.03 | AN89: 0.03 | AO89: 0.03 | AP89: 0.03 | AR89: 0.03 | AS89: 0.03 | KX89: 0.06 | KY89: 0.12 | KZ89: 0.12 | LA89: 0.12 | LB89: 0.12 | LC89: 0.12 | LE89: 0.12 | LF89: 0.12 | LG89: 0.12 | LH89: 0.12 | LI89: 0.12 | LJ89: 0.12 | LL89: 0.12 | LM89: 0.12 | LN89: 0.12 | LO89: 0.12 | LP89: 0.12 | LQ89: 0.12 | LS89: 0.2 | LT89: 0.28 | LU89: 0.28 | LV89: 0.28 | LW89: 0.28 | LX89: 0.28 | LZ89: 0.28 | MA89: 0.18 | MB89: 0.08 | MC89: 0.08 | MD89: 0.08 | ME89: 0.08 | MG89: 0.08 | MH89: 0.08 | MI89: 0.08 | MJ89: 0.07 | MK89: 0.07 | ML89: 0.07 | MN89: 0.07 | MO89: 0.07 | MP89: 0.07 | MQ89: 0.07 | MR89: 0.04 | MS89: 0.02 | MU89: 0.02 | MV89: 0.02 | MW89: 0.02 | MX89: 0.02 | MY89: 0.02 | MZ89: 0.02 | NB89: 0.02 | NC89: 0.02 | ND89: 0.02 | NE89: 0.02 | NF89: 0.02 | NG89: 0.02 | NI89: 0.02 | NJ89: 0.02 | NK89: 0.02 | NL89: 0.02 | NM89: 0.02 | NN89: 0.02 | NP89: 0.02 | NQ89: 0.02 | NR89: 0.02 | NS89: 0.02 | NT89: 0.02 | NU89: 0.02 | NW89: 0.02 | NX89: 0.02 | NY89: 0.02 | NZ89: 0.02 | OA89: 0.02 | OB89: 0.02 | OD89: 0.02 | OE89: 0.02 | OF89: 0.02 | OG89: 0.02 | OH89: 0.02 | OI89: 0.02 | OL89: 0.02 | OM89: 0.02 | ON89: 0.02 | OO89: 0.02 | OP89: 0.02 | OR89: 0.01 | OS89: 0.01 | OT89: 0.01 | OU89: 0.01 | OV89: 0.01 | OW89: 0.01 | OY89: 0.01 | OZ89: 0.01 | PA89: 0.01 | PB89: 0.01 | YK89: 0.02 | YL89: 0.09 | YM89: 0.09 | YN89: 0.09 | YO89: 0.09 | YQ89: 0.09 | YR89: 0.09 | YS89: 0.09 | YT89: 0.07
A90: Sewer Manhole Dia 1200 mm, Depth: 4.5 - 5.5m | E90: 6 | F90: 0 | G90: 237600 | H90: 237600 | I90: =F90 -> 0 | AK90: 0.02 | AL90: 0.02 | AM90: 0.02 | AN90: 0.02 | AO90: 0.02 | AP90: 0.02 | AR90: 0.02 | AS90: 0.02 | KX90: 0.01 | KY90: 0.01 | KZ90: 0.01 | LA90: 0.01 | LB90: 0.01 | LC90: 0.01 | LE90: 0.01 | LF90: 0.01 | LG90: 0.01 | LH90: 0.05 | LI90: 0.08 | LJ90: 0.08 | LL90: 0.08 | LM90: 0.08 | LN90: 0.08 | LO90: 0.08 | LP90: 0.08 | LQ90: 0.08 | LS90: 0.08 | LT90: 0.08 | LU90: 0.08 | LV90: 0.08 | LW90: 0.1 | LX90: 0.11 | LZ90: 0.11 | MA90: 0.11 | MB90: 0.11 | MC90: 0.16 | MD90: 0.22 | ME90: 0.22 | MG90: 0.22 | MH90: 0.22 | MI90: 0.22 | MJ90: 0.22 | MK90: 0.16 | ML90: 0.13 | MN90: 0.17 | MO90: 0.17 | MP90: 0.13 | MQ90: 0.09 | MR90: 0.09 | MS90: 0.07 | MU90: 0.05 | MV90: 0.05 | MW90: 0.05 | MX90: 0.06 | MY90: 0.07 | MZ90: 0.07 | NB90: 0.07 | NC90: 0.05 | ND90: 0.02 | NE90: 0.01 | NF90: 0.01 | NG90: 0.01 | NI90: 0.01 | NJ90: 0.01 | NK90: 0.01 | NL90: 0.01 | NM90: 0.01 | NN90: 0.01 | NP90: 0.01 | NQ90: 0.01 | NR90: 0.01 | NS90: 0.01 | NT90: 0.01 | NU90: 0.01 | NW90: 0.01 | NX90: 0.01 | NY90: 0.01 | NZ90: 0.01 | OA90: 0.01 | OB90: 0.01 | OD90: 0.01 | OE90: 0.01 | OF90: 0.01 | OG90: 0.01 | OH90: 0.01 | OI90: 0.01 | OL90: 0.01 | OM90: 0.01 | ON90: 0.01 | OO90: 0.01 | OP90: 0.01 | OR90: 0.01 | OS90: 0.01 | OT90: 0.01 | OU90: 0.01 | OV90: 0.01 | OW90: 0.01 | OY90: 0.01 | OZ90: 0.01 | PA90: 0.01 | PB90: 0.01 | YK90: 0.02 | YL90: 0.08 | YM90: 0.08 | YN90: 0.08 | YO90: 0.08 | YQ90: 0.08 | YR90: 0.08 | YS90: 0.08 | YT90: 0.06
A91: Sewer Manhole Dia 1200 mm, Depth: 5.5 - 6.5m | E91: 2 | F91: 0 | G91: 93400 | H91: 93400 | I91: =F91 -> 0 | AK91: 0.01 | AL91: 0.01 | AM91: 0.01 | AN91: 0.01 | AO91: 0.01 | AP91: 0.01 | AR91: 0.01 | AS91: 0.01 | KX91: 0 | KY91: 0 | KZ91: 0 | LA91: 0 | LB91: 0 | LC91: 0 | LE91: 0 | LF91: 0 | LG91: 0 | LH91: 0 | LI91: 0 | LJ91: 0 | LL91: 0 | LM91: 0 | LN91: 0 | LO91: 0 | LP91: 0 | LQ91: 0 | LS91: 0.02 | LT91: 0.03 | LU91: 0.03 | LV91: 0.03 | LW91: 0.03 | LX91: 0.03 | LZ91: 0.03 | MA91: 0.03 | MB91: 0.03 | MC91: 0.04 | MD91: 0.04 | ME91: 0.04 | MG91: 0.04 | MH91: 0.04 | MI91: 0.04 | MJ91: 0.04 | MK91: 0.07 | ML91: 0.09 | MN91: 0.09 | MO91: 0.09 | MP91: 0.09 | MQ91: 0.09 | MR91: 0.06 | MS91: 0.02 | MU91: 0.02 | MV91: 0.02 | MW91: 0.02 | MX91: 0.02 | MY91: 0.02 | MZ91: 0.02 | NB91: 0.02 | NC91: 0.02 | ND91: 0.02 | NE91: 0.03 | NF91: 0.03 | NG91: 0.03 | NI91: 0.03 | NJ91: 0.03 | NK91: 0.02 | NL91: 0 | NM91: 0 | NN91: 0 | NP91: 0 | NQ91: 0 | NR91: 0 | NS91: 0 | NT91: 0 | NU91: 0 | NW91: 0 | NX91: 0 | NY91: 0 | NZ91: 0 | OA91: 0 | OB91: 0 | OD91: 0 | OE91: 0 | OF91: 0 | OG91: 0 | OH91: 0 | OI91: 0 | OL91: 0 | OM91: 0 | ON91: 0 | OO91: 0 | OP91: 0 | OR91: 0 | OS91: 0 | OT91: 0 | OU91: 0 | OV91: 0 | OW91: 0 | OY91: 0 | OZ91: 0 | PA91: 0 | PB91: 0 | YK91: 0.01 | YL91: 0.03 | YM91: 0.03 | YN91: 0.03 | YO91: 0.03 | YQ91: 0.03 | YR91: 0.03 | YS91: 0.03 | YT91: 0.02
A92: Sewer Manhole Dia 1200 mm; Depth < 1.5m | E92: 8 | F92: 0 | G92: 98240 | H92: 98240 | I92: =F92 -> 0 | AK92: 0.03 | AL92: 0.03 | AM92: 0.03 | AN92: 0.03 | AO92: 0.03 | AP92: 0.03 | AR92: 0.03 | AS92: 0.03 | JS92: 0.03 | JT92: 0.06 | JV92: 0.06 | JW92: 0.06 | JX92: 0.06 | JY92: 0.06 | JZ92: 0.06 | KA92: 0.06 | KC92: 0.06 | KD92: 0.06 | KE92: 0.06 | KF92: 0.06 | KG92: 0.06 | KH92: 0.06 | KJ92: 0.06 | KK92: 0.06 | KL92: 0.1 | KM92: 0.14 | KN92: 0.14 | KO92: 0.14 | KQ92: 0.14 | KR92: 0.14 | KS92: 0.14 | KT92: 0.09 | KU92: 0.03 | KV92: 0.03 | KX92: 0.04 | KY92: 0.05 | KZ92: 0.05 | LA92: 0.05 | LB92: 0.05 | LC92: 0.05 | LE92: 0.05 | LF92: 0.05 | LG92: 0.05 | LH92: 0.05 | LI92: 0.05 | LJ92: 0.05 | LL92: 0.03 | LM92: 0.02 | LN92: 0.02 | LO92: 0.02 | LP92: 0.02 | LQ92: 0.02 | LS92: 0.02 | LT92: 0.02 | LU92: 0.02 | LV92: 0.02 | LW92: 0.02 | LX92: 0.02 | LZ92: 0.02 | MA92: 0.02 | MB92: 0.02 | MC92: 0.02 | MD92: 0.02 | ME92: 0.02 | MG92: 0.02 | MH92: 0.02 | MI92: 0.02 | MJ92: 0.02 | MK92: 0.02 | ML92: 0.02 | MN92: 0.02 | MO92: 0.02 | MP92: 0.02 | MQ92: 0.02 | MR92: 0.02 | MS92: 0.02 | MU92: 0.02 | MV92: 0.02 | MW92: 0.02 | MX92: 0.02 | MY92: 0.02 | MZ92: 0.02 | NB92: 0.02 | NC92: 0.02 | ND92: 0.02 | NE92: 0.02 | NF92: 0.02 | NG92: 0.02 | NI92: 0.02 | NJ92: 0.02 | NK92: 0.02 | NL92: 0.02 | NM92: 0.02 | NN92: 0.02 | NP92: 0.02 | NQ92: 0.02 | NR92: 0.02 | NS92: 0.02 | NT92: 0.02 | NU92: 0.02 | NW92: 0.02 | NX92: 0.02 | NY92: 0.02 | NZ92: 0.06 | OA92: 0.1 | OB92: 0.1 | OD92: 0.1 | OE92: 0.1 | OF92: 0.1 | OG92: 0.1 | OH92: 0.12 | OI92: 0.14 | OL92: 0.14 | OM92: 0.14 | ON92: 0.14 | OO92: 0.19 | OP92: 0.25 | OR92: 0.19 | OS92: 0.19 | OT92: 0.19 | OU92: 0.19 | OV92: 0.15 | OW92: 0.06 | OY92: 0.06 | OZ92: 0.06 | PA92: 0.06 | PB92: 0.06 | PC92: 0.05 | PD92: 0.05 | PF92: 0.05 | PG92: 0.05 | PH92: 0.05 | PI92: 0.05 | PJ92: 0.05 | PK92: 0.05 | YK92: 0.03 | YL92: 0.1 | YM92: 0.1 | YN92: 0.1 | YO92: 0.1 | YQ92: 0.1 | YR92: 0.1 | YS92: 0.1 | YT92: 0.08
A93: Single Catch basin | E93: 217 | F93: 0 | G93: 1944320 | H93: 1944320 | I93: =F93 -> 0 | U93: 1.09 | W93: 1.09 | X93: 1.09 | Y93: 1.09 | Z93: 1.09 | AA93: 1.09 | BX93: 0.17 | BY93: 0.17 | CA93: 0.17 | CB93: 0.17 | CC93: 0.17 | CD93: 0.17 | CJ93: 0.23 | CK93: 0.23 | CL93: 0.23 | CM93: 0.23 | CO93: 0.23 | CP93: 0.23 | CQ93: 0.23 | CR93: 0.23 | CS93: 0.23 | CT93: 0.23 | CV93: 0.23 | CW93: 0.23 | CX93: 0.23 | CY93: 0.23 | CZ93: 0.23 | DA93: 0.23 | DC93: 0.23 | DD93: 0.23 | DE93: 0.23 | DF93: 0.23 | DG93: 0.23 | DH93: 0.23 | DJ93: 0.23 | DK93: 0.23 | DL93: 0.23 | DM93: 0.23 | DN93: 0.23 | DO93: 0.23 | DQ93: 0.23 | DR93: 0.23 | DS93: 0.23 | DT93: 0.23 | DU93: 0.23 | DV93: 0.23 | DX93: 0.23 | DY93: 0.23 | DZ93: 0.23 | EA93: 0.23 | EB93: 0.23 | EC93: 0.23 | EE93: 0.23 | EF93: 0.23 | EG93: 0.23 | EH93: 0.23 | EI93: 0.23 | EJ93: 0.23 | EL93: 0.23 | EM93: 0.61 | EN93: 0.99 | EO93: 0.99 | EP93: 0.99 | EQ93: 0.99 | ES93: 0.99 | ET93: 0.99 | EZ93: 0.99 | FA93: 0.99 | FB93: 0.99 | FC93: 0.99 | FD93: 0.99 | FE93: 0.99 | FG93: 0.99 | FH93: 0.89 | FI93: 0.79 | FJ93: 0.79 | FK93: 0.79 | FL93: 0.79 | FN93: 0.79 | FO93: 0.79 | FP93: 0.79 | FQ93: 0.79 | FR93: 0.79 | FS93: 0.79 | FU93: 0.79 | FV93: 0.79 | FW93: 0.79 | FX93: 0.79 | FY93: 0.79 | FZ93: 0.79 | GB93: 0.79 | GC93: 0.79 | GD93: 1.12 | GE93: 1.45 | GF93: 1.45 | GG93: 1.45 | GI93: 1.45 | GJ93: 1.45 | GK93: 1.45 | GL93: 1.45 | GM93: 1.45 | GN93: 1.45 | GP93: 1.45 | GQ93: 1.45 | GR93: 1.45 | GS93: 1.45 | GT93: 1.45 | GU93: 1.45 | GW93: 1.45 | GX93: 1.45 | GY93: 1.45 | GZ93: 1.45 | HA93: 1.45 | HB93: 1.45 | HD93: 0.84 | HE93: 0.23 | HF93: 0.23 | HG93: 0.23 | HH93: 0.23 | HI93: 0.23 | HK93: 0.23 | HL93: 0.23 | HM93: 0.23 | HN93: 0.23 | HO93: 0.23 | HP93: 0.23 | HR93: 0.23 | HS93: 0.23 | HT93: 0.23 | HU93: 0.23 | HV93: 0.23 | HW93: 0.23 | HY93: 0.42 | HZ93: 0.61 | IA93: 0.61 | IB93: 0.61 | IC93: 0.61 | ID93: 0.61 | IF93: 0.61 | IG93: 0.61 | IH93: 0.61 | II93: 0.61 | IJ93: 0.61 | IK93: 0.61 | IM93: 0.61 | IN93: 0.61 | IP93: 0.42 | IQ93: 0.23 | IR93: 0.23 | IT93: 0.23 | IU93: 0.23 | IV93: 0.23 | IW93: 0.23 | IX93: 0.54 | IY93: 0.86 | JA93: 0.86 | JB93: 0.86 | JC93: 0.86 | JD93: 0.86 | JE93: 0.86 | JF93: 0.99 | JH93: 1.11 | JI93: 1.11 | JJ93: 1.11 | JK93: 1.11 | JL93: 1.78 | JM93: 2.44 | JO93: 2.44 | JP93: 2.44 | JQ93: 2.44 | JR93: 1.33 | JS93: 0.23 | JT93: 0.23 | JV93: 0.23 | JW93: 0.23 | JX93: 0.45 | JY93: 0.67 | JZ93: 0.67 | KA93: 0.67 | KC93: 0.67 | KD93: 0.45 | KE93: 0.23 | KF93: 0.36 | KG93: 0.5 | KH93: 0.5 | KJ93: 0.5 | KK93: 0.5 | KL93: 0.5 | KM93: 0.63 | KN93: 0.76 | KO93: 0.76 | KQ93: 1.17 | KR93: 1.57 | KS93: 2.29 | KT93: 2.34 | KU93: 1.67 | KV93: 1.67 | KX93: 1.55 | KY93: 1.52 | KZ93: 1.6 | LA93: 1.6 | LB93: 2.03 | LC93: 2.47 | LE93: 2.39 | LF93: 2.3 | LG93: 2.3 | LH93: 3.55 | LI93: 4.8 | LJ93: 4.8 | LL93: 4.8 | LM93: 4.8 | LN93: 4.8 | LO93: 2.4 | LV93: 0.36 | LW93: 0.72 | LX93: 0.72 | LZ93: 0.72 | MA93: 0.72 | MB93: 0.72 | MC93: 0.72 | MD93: 0.72 | ME93: 0.36 | MO93: 0.1 | MP93: 0.2 | MQ93: 0.2 | MR93: 0.2 | MS93: 0.3 | MU93: 0.4 | MV93: 0.54 | MW93: 0.67 | MX93: 0.67 | MY93: 0.34 | NB93: 0.07 | NC93: 0.13 | ND93: 0.13 | NE93: 0.07 | YA93: 0.68 | YC93: 2.71 | YD93: 2.71 | YE93: 2.71 | YF93: 2.71 | YG93: 2.71 | YH93: 2.71 | YJ93: 2.71 | YK93: 2.03
A94: SL Pole 12 M | E94: 193 | F94: 0 | G94: 2354600 | H94: 2354600 | I94: =F94 -> 0 | Y94: 0.97 | Z94: 0.97 | AA94: 0.97 | AB94: 0.97 | AD94: 0.97 | AE94: 0.97 | SU94: 0.14 | SV94: 0.55 | SW94: 0.55 | SX94: 0.55 | SZ94: 0.55 | TA94: 0.55 | TB94: 0.55 | TC94: 0.55 | TD94: 0.55 | TE94: 0.55 | TG94: 0.55 | TH94: 0.55 | TI94: 0.55 | TJ94: 0.55 | TK94: 0.55 | TL94: 0.55 | TN94: 0.55 | TO94: 0.55 | TP94: 0.55 | TQ94: 0.55 | TR94: 0.55 | TS94: 0.55 | TU94: 0.55 | TV94: 0.55 | TW94: 0.55 | TX94: 0.55 | TY94: 0.55 | TZ94: 0.55 | UB94: 0.55 | UC94: 0.55 | UD94: 0.55 | UE94: 0.55 | UF94: 0.55 | UG94: 0.55 | UI94: 0.55 | UJ94: 0.55 | UK94: 0.55 | UL94: 0.55 | UM94: 0.55 | UN94: 0.55 | UP94: 0.55 | UQ94: 0.55 | UR94: 0.55 | US94: 0.55 | UT94: 0.55 | UU94: 0.55 | UW94: 0.55 | UX94: 0.55 | UY94: 0.55 | UZ94: 0.55 | VA94: 0.55 | VB94: 0.55 | VD94: 0.55 | VE94: 0.55 | VF94: 0.55 | VG94: 0.55 | VH94: 0.74 | VI94: 1.31 | VK94: 1.31 | VL94: 1.31 | VM94: 1.31 | VN94: 1.31 | VO94: 1.31 | VP94: 1.31 | VR94: 1.31 | VS94: 1.25 | VT94: 1.08 | VU94: 1.08 | VV94: 1.08 | VW94: 1.08 | VY94: 0.94 | VZ94: 0.53 | WA94: 0.53 | WB94: 0.53 | WC94: 0.53 | WD94: 0.53 | WF94: 0.53 | WG94: 0.73 | WH94: 1.68 | WI94: 2.73 | WJ94: 2.61 | WK94: 2.23 | WM94: 2.23 | WN94: 2.23 | WO94: 2.23 | WQ94: 2.23 | WR94: 2.23 | WT94: 2.23 | WU94: 2.6 | WV94: 4.07 | WW94: 4.83 | WX94: 3.21 | WY94: 2.17 | XA94: 2.92 | XB94: 1.59 | XC94: 1.93 | XD94: 2.93 | XE94: 3.08 | XF94: 3.08 | XH94: 1.61 | XI94: 1.52 | XJ94: 1.89 | XK94: 1.6 | XL94: 1.6 | XM94: 1.6 | XO94: 1.6 | XP94: 1.6 | XQ94: 1.6 | XR94: 1.55 | XS94: 1.97 | XT94: 3.73 | XV94: 3.58 | XW94: 3.11 | XX94: 3.11 | XY94: 3.11 | XZ94: 3.11 | YA94: 3.11 | YC94: 3.11 | YD94: 2.33 | YF94: 0.05 | YG94: 0.2 | YH94: 0.2 | YJ94: 0.2 | YK94: 0.2 | YL94: 0.41 | YM94: 1.05 | YN94: 1.05 | YO94: 1.05 | YQ94: 1.05 | YR94: 1.23 | YS94: 1.77 | YT94: 1.77 | YU94: 1.77 | YV94: 1.33 | YZ94: 0.05 | ZA94: 0.2 | ZB94: 0.2 | ZC94: 0.2 | ZE94: 0.2 | ZF94: 0.15 | ZM94: 0.48 | ZN94: 1.93 | ZO94: 1.93 | ZP94: 1.93 | ZQ94: 1.93 | ZS94: 1.93 | ZT94: 1.93 | ZU94: 1.93 | ZV94: 1.93 | ZW94: 1.93 | ZX94: 1.45
A95: Stand. Arm. 1C 10MM2 | E95: 5900 | F95: 177 | G95: 737500 | H95: 737500 | I95: =F95 -> 177 | Y95: 29.5 | Z95: 29.5 | AA95: 29.5 | AB95: 29.5 | AD95: 29.5 | AE95: 29.5 | VS95: 4.92 | VT95: 19.67 | VU95: 19.67 | VV95: 19.67 | VW95: 19.67 | VY95: 19.67 | VZ95: 34.75 | WA95: 80.01 | WB95: 80.01 | WC95: 80.01 | WD95: 80.01 | WF95: 80.01 | WG95: 98.87 | WH95: 155.44 | WI95: 155.44 | WJ95: 155.44 | WK95: 155.44 | WM95: 155.44 | WN95: 158.73 | WO95: 168.59 | WQ95: 143.7 | WR95: 69.03 | WT95: 69.03 | WU95: 69.03 | WV95: 74.19 | WW95: 89.69 | WX95: 89.69 | WY95: 89.69 | XA95: 89.69 | XB95: 89.69 | XC95: 80.64 | XD95: 45.03 | XE95: 19.67 | XF95: 21.31 | XH95: 26.24 | XI95: 26.24 | XJ95: 26.24 | XK95: 26.24 | XL95: 26.24 | XM95: 26.24 | XO95: 26.24 | XP95: 26.24 | XQ95: 26.24 | XR95: 26.24 | XS95: 31.71 | XT95: 46.47 | XV95: 44.13 | XW95: 51.9 | XX95: 51.9 | XY95: 51.9 | XZ95: 51.9 | YA95: 51.9 | YC95: 51.9 | YD95: 61.2 | YE95: 89.08 | YF95: 95.24 | YG95: 113.71 | YH95: 113.71 | YJ95: 113.71 | YK95: 113.71 | YL95: 112.51 | YM95: 108.91 | YN95: 108.91 | YO95: 89.29 | YQ95: 30.81 | YR95: 31.95 | YS95: 31.95 | YT95: 31.95 | YU95: 31.95 | YV95: 28.07 | YX95: 16.4 | YY95: 22.77 | YZ95: 41.89 | ZA95: 41.89 | ZB95: 41.89 | ZC95: 41.89 | ZE95: 37.79 | ZF95: 25.49 | ZG95: 22.09 | ZH95: 11.9 | ZI95: 11.9 | ZJ95: 11.9 | ZL95: 11.9 | ZM95: 23.67 | ZN95: 59 | ZO95: 59 | ZP95: 59 | ZQ95: 59 | ZS95: 59 | ZT95: 59 | ZU95: 59 | ZV95: 59 | ZW95: 59 | ZX95: 44.25
A96: Stand. Arm. 1C 16MM2 | E96: 910 | F96: 27.3 | G96: 118300 | H96: 118300 | I96: =F96 -> 27.3 | Y96: 4.55 | Z96: 4.55 | AA96: 4.55 | AB96: 4.55 | AD96: 4.55 | AE96: 4.55 | VS96: 0.76 | VT96: 3.03 | VU96: 3.03 | VV96: 3.03 | VW96: 3.03 | VY96: 3.03 | VZ96: 3.03 | WA96: 3.03 | WB96: 3.03 | WC96: 3.03 | WD96: 3.03 | WF96: 3.03 | WG96: 3.03 | WH96: 3.03 | WI96: 3.03 | WJ96: 3.03 | WK96: 3.03 | WM96: 3.03 | WN96: 3.03 | WO96: 3.03 | WQ96: 3.03 | WR96: 3.03 | WT96: 3.03 | WU96: 3.03 | WV96: 3.03 | WW96: 3.03 | WX96: 3.03 | WY96: 3.03 | XA96: 3.03 | XB96: 3.03 | XC96: 3.03 | XD96: 3.03 | XE96: 3.03 | XF96: 3.03 | XH96: 3.03 | XI96: 3.03 | XJ96: 3.03 | XK96: 3.03 | XL96: 3.03 | XM96: 3.03 | XO96: 3.03 | XP96: 3.03 | XQ96: 3.03 | XR96: 3.03 | XS96: 3.03 | XT96: 3.03 | XV96: 6.42 | XW96: 16.58 | XX96: 16.58 | XY96: 16.58 | XZ96: 16.58 | YA96: 16.58 | YC96: 16.58 | YD96: 16.58 | YE96: 16.58 | YF96: 24.63 | YG96: 48.76 | YH96: 48.76 | YJ96: 48.76 | YK96: 48.76 | YL96: 48 | YM96: 45.73 | YN96: 45.73 | YO96: 39.38 | YQ96: 20.32 | YR96: 20.32 | YS96: 20.32 | YT96: 20.32 | YU96: 20.32 | YV96: 15.24 | ZM96: 2.28 | ZN96: 9.1 | ZO96: 9.1 | ZP96: 9.1 | ZQ96: 9.1 | ZS96: 9.1 | ZT96: 9.1 | ZU96: 9.1 | ZV96: 9.1 | ZW96: 9.1 | ZX96: 6.83
A97: Stand. Arm. 4C 16MM2 | E97: 5900 | F97: 177 | G97: 1091500 | H97: 1091500 | I97: =F97 -> 177 | Y97: 29.5 | Z97: 29.5 | AA97: 29.5 | AB97: 29.5 | AD97: 29.5 | AE97: 29.5 | VS97: 4.92 | VT97: 19.67 | VU97: 19.67 | VV97: 19.67 | VW97: 19.67 | VY97: 19.67 | VZ97: 34.75 | WA97: 80.01 | WB97: 80.01 | WC97: 80.01 | WD97: 80.01 | WF97: 80.01 | WG97: 98.87 | WH97: 155.44 | WI97: 155.44 | WJ97: 155.44 | WK97: 155.44 | WM97: 155.44 | WN97: 158.73 | WO97: 168.6 | WQ97: 143.7 | WR97: 69.03 | WT97: 69.03 | WU97: 69.03 | WV97: 65.74 | WW97: 55.87 | WX97: 55.87 | WY97: 65.74 | XA97: 95.33 | XB97: 95.33 | XC97: 86.28 | XD97: 59.12 | XE97: 59.12 | XF97: 50.9 | XH97: 26.24 | XI97: 26.24 | XJ97: 26.24 | XK97: 26.24 | XL97: 26.24 | XM97: 26.24 | XO97: 26.24 | XP97: 26.24 | XQ97: 26.24 | XR97: 26.24 | XS97: 31.71 | XT97: 46.47 | XV97: 44.13 | XW97: 51.9 | XX97: 51.9 | XY97: 51.9 | XZ97: 51.9 | YA97: 51.9 | YC97: 51.9 | YD97: 46.44 | YE97: 44.8 | YF97: 95.23 | YG97: 113.7 | YH97: 113.7 | YJ97: 113.7 | YK97: 113.7 | YL97: 112.51 | YM97: 108.91 | YN97: 108.91 | YO97: 104.05 | YQ97: 81.46 | YR97: 57.45 | YS97: 57.45 | YT97: 57.45 | YU97: 57.45 | YV97: 53.56 | YX97: 41.89 | YY97: 35.52 | YZ97: 16.4 | ZA97: 16.4 | ZB97: 16.4 | ZC97: 16.4 | ZE97: 12.3 | ZG97: 2.97 | ZH97: 11.9 | ZI97: 11.9 | ZJ97: 11.9 | ZL97: 11.9 | ZM97: 23.67 | ZN97: 59 | ZO97: 59 | ZP97: 59 | ZQ97: 59 | ZS97: 59 | ZT97: 59 | ZU97: 59 | ZV97: 59 | ZW97: 59 | ZX97: 44.25
A98: Stand. Arm. 4C 25MM2 | E98: 910 | F98: 27.3 | G98: 200200 | H98: 200200 | I98: =F98 -> 27.3 | Y98: 4.55 | Z98: 4.55 | AA98: 4.55 | AB98: 4.55 | AD98: 4.55 | AE98: 4.55 | VS98: 0.76 | VT98: 3.03 | VU98: 3.03 | VV98: 3.03 | VW98: 3.03 | VY98: 3.03 | VZ98: 3.03 | WA98: 3.03 | WB98: 3.03 | WC98: 3.03 | WD98: 3.03 | WF98: 3.03 | WG98: 3.03 | WH98: 3.03 | WI98: 3.03 | WJ98: 3.03 | WK98: 3.03 | WM98: 3.03 | WN98: 3.03 | WO98: 3.03 | WQ98: 3.03 | WR98: 3.03 | WT98: 3.03 | WU98: 3.03 | WV98: 3.03 | WW98: 3.03 | WX98: 3.03 | WY98: 3.03 | XA98: 3.03 | XB98: 3.03 | XC98: 3.03 | XD98: 3.03 | XE98: 3.03 | XF98: 3.03 | XH98: 3.03 | XI98: 3.03 | XJ98: 3.03 | XK98: 3.03 | XL98: 3.03 | XM98: 3.03 | XO98: 3.03 | XP98: 3.03 | XQ98: 3.03 | XR98: 3.03 | XS98: 3.03 | XT98: 3.03 | XV98: 6.42 | XW98: 16.58 | XX98: 16.58 | XY98: 16.58 | XZ98: 16.58 | YA98: 16.58 | YC98: 16.58 | YD98: 16.58 | YE98: 16.58 | YF98: 24.63 | YG98: 48.76 | YH98: 48.76 | YJ98: 48.76 | YK98: 48.76 | YL98: 48 | YM98: 45.73 | YN98: 45.73 | YO98: 39.38 | YQ98: 20.32 | YR98: 20.32 | YS98: 20.32 | YT98: 20.32 | YU98: 20.32 | YV98: 15.24 | ZM98: 2.28 | ZN98: 9.1 | ZO98: 9.1 | ZP98: 9.1 | ZQ98: 9.1 | ZS98: 9.1 | ZT98: 9.1 | ZU98: 9.1 | ZV98: 9.1 | ZW98: 9.1 | ZX98: 6.83
A99: Stand. Arm. 4C 35MM2 | E99: 15 | F99: 0.45 | G99: 3750 | H99: 3750 | I99: =F99 -> 0.45 | Y99: 0.08 | Z99: 0.08 | AA99: 0.08 | AB99: 0.08 | AD99: 0.08 | AE99: 0.08 | VS99: 0.01 | VT99: 0.05 | VU99: 0.05 | VV99: 0.05 | VW99: 0.05 | VY99: 0.05 | VZ99: 0.05 | WA99: 0.05 | WB99: 0.05 | WC99: 0.05 | WD99: 0.05 | WF99: 0.05 | WG99: 0.05 | WH99: 0.05 | WI99: 0.05 | WJ99: 0.05 | WK99: 0.05 | WM99: 0.05 | WN99: 0.05 | WO99: 0.05 | WQ99: 0.05 | WR99: 0.05 | WT99: 0.05 | WU99: 0.05 | WV99: 0.05 | WW99: 0.05 | WX99: 0.05 | WY99: 0.05 | XA99: 0.05 | XB99: 0.05 | XC99: 0.05 | XD99: 0.05 | XE99: 0.05 | XF99: 0.05 | XH99: 0.05 | XI99: 0.05 | XJ99: 0.05 | XK99: 0.05 | XL99: 0.05 | XM99: 0.05 | XO99: 0.05 | XP99: 0.05 | XQ99: 0.05 | XR99: 0.05 | XS99: 0.05 | XT99: 0.05 | XV99: 0.11 | XW99: 0.27 | XX99: 0.27 | XY99: 0.27 | XZ99: 0.27 | YA99: 0.27 | YC99: 0.27 | YD99: 0.27 | YE99: 0.27 | YF99: 0.43 | YG99: 0.91 | YH99: 0.91 | YJ99: 0.91 | YK99: 0.91 | YL99: 0.9 | YM99: 0.86 | YN99: 0.65 | YO99: 0.08 | YQ99: 0.34 | YR99: 0.34 | YS99: 0.34 | YT99: 0.34 | YU99: 0.34 | YV99: 0.25 | ZM99: 0.04 | ZN99: 0.15 | ZO99: 0.15 | ZP99: 0.15 | ZQ99: 0.15 | ZS99: 0.15 | ZT99: 0.15 | ZU99: 0.15 | ZV99: 0.15 | ZW99: 0.15 | ZX99: 0.11
A100: Storm 1000 mm depth: 1.5 - 2.5m | E100: 485 | F100: 14.55 | G100: 1100950 | H100: 1100950 | I100: =F100 -> 14.55 | J100: 1.82 | K100: 1.82 | L100: 1.82 | M100: 1.82 | N100: 1.82 | P100: 1.82 | Q100: 1.82 | R100: 1.82 | BX100: 0.45 | BY100: 0.45 | CA100: 0.45 | CB100: 0.45 | CC100: 0.45 | CD100: 0.45 | CJ100: 0.61 | CK100: 0.61 | CL100: 0.61 | CM100: 0.61 | CO100: 0.61 | CP100: 0.61 | CQ100: 0.61 | CR100: 0.61 | CS100: 0.61 | CT100: 0.61 | CV100: 0.61 | CW100: 0.61 | CX100: 0.61 | CY100: 0.61 | CZ100: 0.61 | DA100: 0.61 | DC100: 0.61 | DD100: 0.61 | DE100: 0.61 | DF100: 0.61 | DG100: 0.61 | DH100: 0.61 | DJ100: 0.61 | DK100: 0.61 | DL100: 0.61 | DM100: 0.61 | DN100: 0.61 | DO100: 0.61 | DQ100: 0.61 | DR100: 0.61 | DS100: 0.61 | DT100: 0.61 | DU100: 0.61 | DV100: 0.61 | DX100: 0.61 | DY100: 0.61 | DZ100: 0.61 | EA100: 0.61 | EB100: 0.61 | EC100: 0.61 | EE100: 0.61 | EF100: 0.61 | EG100: 0.61 | EH100: 0.61 | EI100: 0.61 | EJ100: 0.61 | EL100: 0.61 | EM100: 0.61 | EN100: 0.61 | EO100: 0.61 | EP100: 0.61 | EQ100: 0.61 | ES100: 0.61 | ET100: 0.61 | EZ100: 0.61 | FA100: 0.61 | FB100: 0.61 | FC100: 0.61 | FD100: 0.61 | FE100: 0.61 | FG100: 0.61 | FH100: 0.61 | FI100: 0.61 | FJ100: 0.61 | FK100: 0.61 | FL100: 0.61 | FN100: 0.61 | FO100: 0.61 | FP100: 0.61 | FQ100: 0.61 | FR100: 0.61 | FS100: 0.61 | FU100: 0.61 | FV100: 0.61 | FW100: 0.61 | FX100: 0.61 | FY100: 0.61 | FZ100: 0.61 | GB100: 0.61 | GC100: 0.61 | GD100: 4.09 | GE100: 7.57 | GF100: 7.57 | GG100: 7.57 | GI100: 7.57 | GJ100: 7.57 | GK100: 7.57 | GL100: 8.15 | GM100: 8.73 | GN100: 8.73 | GP100: 8.73 | GQ100: 20.92 | GR100: 33.1 | GS100: 33.1 | GT100: 33.1 | GU100: 33.1 | GW100: 20.1 | GX100: 7.11 | GY100: 7.11 | GZ100: 7.11 | HA100: 7.11 | HB100: 7.92 | HD100: 8.73 | HE100: 8.73 | HF100: 8.73 | HG100: 8.73 | HH100: 8.73 | HI100: 4.67 | HK100: 0.61 | HL100: 0.61 | HM100: 0.61 | HN100: 0.61 | HO100: 0.61 | HP100: 0.61 | HR100: 0.61 | HS100: 0.61 | HT100: 0.61 | HU100: 0.61 | HV100: 0.61 | HW100: 0.61 | HY100: 0.61 | HZ100: 0.61 | IA100: 0.61 | IB100: 0.61 | IC100: 0.61 | ID100: 0.61 | IF100: 0.61 | IG100: 0.61 | IH100: 0.61 | II100: 0.61 | IJ100: 0.61 | IK100: 0.61 | IM100: 0.61 | IN100: 0.61 | IP100: 0.61 | IQ100: 0.61 | IR100: 0.61 | IT100: 0.61 | IU100: 0.61 | IV100: 0.61 | IW100: 0.61 | IX100: 0.61 | IY100: 0.61 | JA100: 0.61 | JB100: 0.61 | JC100: 0.61 | JD100: 0.61 | JE100: 0.61 | JF100: 0.61 | JH100: 0.61 | JI100: 0.61 | JJ100: 0.61 | JK100: 0.61 | JL100: 0.61 | JM100: 0.61 | JO100: 0.3 | YA100: 1.52 | YC100: 6.06 | YD100: 6.06 | YE100: 6.06 | YF100: 6.06 | YG100: 6.06 | YH100: 6.06 | YJ100: 6.06 | YK100: 4.55
A101: Storm 1000 mm depth: 2.5 - 3.5m | E101: 410 | F101: 12.3 | G101: 1016800 | H101: 1016800 | I101: =F101 -> 12.3 | J101: 1.54 | K101: 1.54 | L101: 1.54 | M101: 1.54 | N101: 1.54 | P101: 1.54 | Q101: 1.54 | R101: 1.54 | BX101: 0.38 | BY101: 0.38 | CA101: 0.38 | CB101: 0.38 | CC101: 0.38 | CD101: 0.38 | CJ101: 0.51 | CK101: 0.51 | CL101: 0.51 | CM101: 0.51 | CO101: 0.51 | CP101: 0.51 | CQ101: 0.51 | CR101: 0.51 | CS101: 0.51 | CT101: 0.51 | CV101: 0.51 | CW101: 0.51 | CX101: 0.51 | CY101: 0.51 | CZ101: 0.51 | DA101: 0.51 | DC101: 0.51 | DD101: 0.51 | DE101: 0.51 | DF101: 0.51 | DG101: 0.51 | DH101: 0.51 | DJ101: 0.51 | DK101: 0.51 | DL101: 0.51 | DM101: 0.51 | DN101: 0.51 | DO101: 0.51 | DQ101: 0.51 | DR101: 0.51 | DS101: 0.51 | DT101: 0.51 | DU101: 0.51 | DV101: 0.51 | DX101: 0.51 | DY101: 0.51 | DZ101: 0.51 | EA101: 0.51 | EB101: 0.51 | EC101: 0.51 | EE101: 0.51 | EF101: 0.51 | EG101: 0.51 | EH101: 0.51 | EI101: 0.51 | EJ101: 0.51 | EL101: 0.51 | EM101: 0.51 | EN101: 0.51 | EO101: 0.51 | EP101: 0.51 | EQ101: 0.51 | ES101: 0.51 | ET101: 0.51 | EZ101: 0.51 | FA101: 0.51 | FB101: 0.51 | FC101: 0.51 | FD101: 0.51 | FE101: 0.51 | FG101: 0.51 | FH101: 0.51 | FI101: 0.51 | FJ101: 0.51 | FK101: 0.51 | FL101: 0.51 | FN101: 0.51 | FO101: 0.51 | FP101: 0.51 | FQ101: 0.51 | FR101: 0.51 | FS101: 0.51 | FU101: 0.51 | FV101: 0.51 | FW101: 0.51 | FX101: 0.51 | FY101: 0.51 | FZ101: 0.51 | GB101: 0.51 | GC101: 0.51 | GD101: 0.51 | GE101: 0.51 | GF101: 0.51 | GG101: 0.51 | GI101: 0.51 | GJ101: 0.51 | GK101: 0.51 | GL101: 2.57 | GM101: 4.63 | GN101: 4.63 | GP101: 4.63 | GQ101: 4.63 | GR101: 4.63 | GS101: 4.22 | GT101: 3.81 | GU101: 3.81 | GW101: 3.81 | GX101: 3.81 | GY101: 10.4 | GZ101: 16.98 | HA101: 16.98 | HB101: 16.98 | HD101: 16.98 | HE101: 10.4 | HF101: 3.81 | HG101: 3.81 | HH101: 3.81 | HI101: 3.81 | HK101: 4.63 | HL101: 5.45 | HM101: 5.45 | HN101: 5.45 | HO101: 5.45 | HP101: 2.98 | HR101: 0.51 | HS101: 0.51 | HT101: 0.51 | HU101: 0.51 | HV101: 0.51 | HW101: 0.51 | HY101: 0.51 | HZ101: 0.51 | IA101: 0.51 | IB101: 0.51 | IC101: 0.51 | ID101: 0.51 | IF101: 0.51 | IG101: 0.51 | IH101: 0.51 | II101: 0.51 | IJ101: 0.51 | IK101: 0.51 | IM101: 0.51 | IN101: 0.51 | IP101: 0.51 | IQ101: 0.51 | IR101: 0.51 | IT101: 0.51 | IU101: 0.51 | IV101: 0.51 | IW101: 0.51 | IX101: 0.51 | IY101: 0.51 | JA101: 0.51 | JB101: 0.51 | JC101: 0.51 | JD101: 0.51 | JE101: 0.51 | JF101: 0.51 | JH101: 0.51 | JI101: 0.51 | JJ101: 0.51 | JK101: 0.51 | JL101: 0.51 | JM101: 0.51 | JO101: 0.26 | LA101: 2.06 | LB101: 4.12 | LC101: 4.12 | LE101: 4.12 | LF101: 4.81 | LG101: 5.5 | LH101: 11.91 | LI101: 18.33 | LJ101: 18.33 | LL101: 11.91 | LM101: 5.5 | LN101: 5.5 | LO101: 5.5 | LP101: 5.5 | LQ101: 2.75 | YA101: 1.28 | YC101: 5.13 | YD101: 5.13 | YE101: 5.13 | YF101: 5.13 | YG101: 5.13 | YH101: 5.13 | YJ101: 5.13 | YK101: 3.84
